Workbook

Sheet Partner1992
A1: Reporter Name | B1: Partner Name | C1: Year | D1: Import Partner Share (%) | E1: Trade Flow | F1: No Of exported HS6 digit Products | G1: No Of imported HS6 digit Products | H1: Export Share in Total Products (%) | I1: Import Share in Total Products (%) | J1: Trade Balance (US$ Thousand) | K1: Export (US$ Thousand) | L1: Import (US$ Thousand) | M1: Export Partner Share (%) | N1: AHS Simple Average (%) | O1: AHS Weighted Average (%) | P1: AHS Total Tariff Lines | Q1: AHS Dutiable Tariff Lines Share (%) | R1: AHS Duty Free Tariff Lines Share (%) | S1: AHS Specific Tariff Lines Share (%) | T1: AHS AVE Tariff Lines Share (%) | U1: AHS MaxRate (%) | V1: AHS MinRate (%) | W1: AHS SpecificDuty Imports(US$ Thousand) | X1: AHS Dutiable Imports (US$ Thousand) | Y1: AHS Duty Free Imports (US$ Thousand) | Z1: MFN Simple Average (%) | AA1: MFN Weighted Average (%) | AB1: MFN Total Tariff Lines | AC1: MFN Dutiable Tariff Lines Share (%) | AD1: MFN Duty Free Tariff Lines Share (%) | AE1: MFN Specific Tariff Lines Share (%) | AF1: MFN AVE Tariff Lines Share (%) | AG1: MFN MaxRate (%) | AH1: MFN MinRate (%) | AI1: MFN SpecificDuty Imports (US$ Thousand) | AJ1: MFN Dutiable Imports (US$ Thousand) | AK1: MFN Duty Free Imports (US$ Thousand) | AL1: No Of Tariff Agreement
A2: Hungary | B2: World | C2: 1992 | D2: 100 | E2: Exports & Imports | F2: 2878 | G2: 4186 | H2: 100 | I2: 100 | J2: -818605.06 | K2: 10054975 | L2: 10873581 | M2: 100
A3: Hungary | B3: Europe & Central Asia | C3: 1992 | D3: 82.25 | E3: Exports & Imports | F3: 2855 | G3: 4174 | H3: 99.2 | I3: 99.71 | J3: -472564.1 | K3: 8470842 | L3: 8943406.1 | M3: 84.25
A4: Hungary | B4: Germany | C4: 1992 | D4: 23.84 | E4: Exports & Imports | F4: 2284 | G4: 3861 | H4: 79.36 | I4: 92.24 | J4: 288537.86 | K4: 2880841 | L4: 2592303.1 | M4: 28.65
A5: Hungary | B5: Russian Federation | C5: 1992 | D5: 16.47 | E5: Exports & Imports | F5: 1749 | G5: 1238 | H5: 60.77 | I5: 29.57 | J5: -442352 | K5: 1348554 | L5: 1790906 | M5: 13.41
A6: Hungary | B6: Austria | C6: 1992 | D6: 14.59 | E6: Exports & Imports | F6: 1974 | G6: 3545 | H6: 68.59 | I6: 84.69 | J6: -506808.96 | K6: 1079298.1 | L6: 1586107 | M6: 10.73
A7: Hungary | B7: Italy | C7: 1992 | D7: 6.39 | E7: Exports & Imports | F7: 1220 | G7: 2659 | H7: 42.39 | I7: 63.52 | J7: 203292.03 | K7: 897590.02 | L7: 694297.98 | M7: 8.93
A8: Hungary | B8: Czechoslovakia | C8: 1992 | D8: 4.29 | E8: Exports & Imports | F8: 1555 | G8: 2025 | H8: 54.03 | I8: 48.38 | J8: -218100.99 | K8: 248355.01 | L8: 466456 | M8: 2.47
A9: Hungary | B9: East Asia & Pacific | C9: 1992 | D9: 4.26 | E9: Exports & Imports | F9: 619 | G9: 1764 | H9: 21.51 | I9: 42.14 | J9: -263343.99 | K9: 200210 | L9: 463553.99 | M9: 1.99
A10: Hungary | B10: North America | C10: 1992 | D10: 3.26 | E10: Exports & Imports | F10: 810 | G10: 2034 | H10: 28.14 | I10: 48.59 | J10: 23292.99 | K10: 377760.98 | L10: 354467.99 | M10: 3.76
A11: Hungary | B11: Switzerland | C11: 1992 | D11: 3.18 | E11: Exports & Imports | F11: 945 | G11: 2268 | H11: 32.84 | I11: 54.18 | J11: -151863.01 | K11: 194079.01 | L11: 345942.02 | M11: 1.93
A12: Hungary | B12: France | C12: 1992 | D12: 3.12 | E12: Exports & Imports | F12: 826 | G12: 2250 | H12: 28.7 | I12: 53.75 | J12: -4752 | K12: 334199.01 | L12: 338951.01 | M12: 3.32
A13: Hungary | B13: Netherlands | C13: 1992 | D13: 3.01 | E13: Exports & Imports | F13: 877 | G13: 2237 | H13: 30.47 | I13: 53.44 | J13: -97635.98 | K13: 230182 | L13: 327817.98 | M13: 2.29
... A27: Hungary | B27: Romania | C27: 1992 | D27: 0.57 | E27: Exports & Imports | F27: 1333 | G27: 694 | H27: 46.32 | I27: 16.58 | J27: 117930.99 | K27: 179828.99 | L27: 61898 | M27: 1.79
A28: Hungary | B28: Other Asia, nes | C28: 1992 | D28: 0.54 | E28: Exports & Imports | J28: -24637 | K28: 34524 | L28: 59161 | M28: 0.34
A29: Hungary | B29: Korea, Rep. | C29: 1992 | D29: 0.5 | E29: Exports & Imports | F29: 68 | G29: 363 | H29: 2.36 | I29: 8.67 | J29: -40929 | K29: 13011 | L29: 53940 | M29: 0.13
A30: Hungary | B30: Middle East & North Africa | C30: 1992 | D30: 0.43 | E30: Exports & Imports | F30: 799 | G30: 670 | H30: 27.76 | I30: 16.01 | J30: 299895 | K30: 347170 | L30: 47275 | M30: 3.45
A31: Hungary | B31: China | C31: 1992 | D31: 0.37 | E31: Exports & Imports | F31: 112 | G31: 618 | H31: 3.89 | I31: 14.76 | J31: -24783 | K31: 14963 | L31: 39746 | M31: 0.15
A32: Hungary | B32: Canada | C32: 1992 | D32: 0.35 | E32: Exports & Imports | F32: 264 | G32: 515 | H32: 9.17 | I32: 12.3 | J32: 9095 | K32: 46859 | L32: 37764 | M32: 0.47
A33: Hungary | B33: Sub-Saharan Africa | C33: 1992 | D33: 0.34 | E33: Exports & Imports | F33: 343 | G33: 260 | H33: 11.92 | I33: 6.21 | J33: -13177 | K33: 23975 | L33: 37152 | M33: 0.24
A34: Hungary | B34: South Asia | C34: 1992 | D34: 0.31 | E34: Exports & Imports | F34: 200 | G34: 366 | H34: 6.95 | I34: 8.74 | J34: 20181 | K34: 54154 | L34: 33973 | M34: 0.54
A35: Hungary | B35: Singapore | C35: 1992 | D35: 0.31 | E35: Exports & Imports | F35: 78 | G35: 243 | H35: 2.71 | I35: 5.81 | J35: -26603 | K35: 6930 | L35: 33533 | M35: 0.07
A36: Hungary | B36: Greece | C36: 1992 | D36: 0.29 | E36: Exports & Imports | F36: 444 | G36: 316 | H36: 15.43 | I36: 7.55 | J36: 41710 | K36: 72794 | L36: 31084 | M36: 0.72
A37: Hungary | B37: Israel | C37: 1992 | D37: 0.28 | E37: Exports & Imports | F37: 199 | G37: 415 | H37: 6.91 | I37: 9.91 | J37: 1505 | K37: 31997 | L37: 30492 | M37: 0.32
A38: Hungary | B38: India | C38: 1992 | D38: 0.26 | E38: Exports & Imports | F38: 110 | G38: 305 | H38: 3.82 | I38: 7.29 | J38: -8868 | K38: 19114 | L38: 27982 | M38: 0.19
A39: Hungary | B39: Turkey | C39: 1992 | D39: 0.24 | E39: Exports & Imports | F39: 307 | G39: 427 | H39: 10.67 | I39: 10.2 | J39: 96111 | K39: 121880 | L39: 25769 | M39: 1.21
A40: Hungary | B40: Indonesia | C40: 1992 | D40: 0.18 | E40: Exports & Imports | F40: 55 | G40: 137 | H40: 1.91 | I40: 3.27 | J40: -10942 | K40: 8760 | L40: 19702 | M40: 0.09
... A94: Hungary | B94: Bahamas, The | C94: 1992 | D94: 0 | E94: Exports & Imports | F94: 9 | G94: 13 | H94: 0.31 | I94: 0.31 | J94: 287 | K94: 423 | L94: 136 | M94: 0
A95: Hungary | B95: Belize | C95: 1992 | D95: 0 | E95: Exports & Imports | G95: 1 | I95: 0.02 | L95: 5
A96: Hungary | B96: Bermuda | C96: 1992 | D96: 0 | E96: Exports & Imports | F96: 6 | G96: 1 | H96: 0.21 | I96: 0.02 | J96: 365 | K96: 492 | L96: 127 | M96: 0
A97: Hungary | B97: Bolivia | C97: 1992 | D97: 0 | E97: Exports & Imports | F97: 4 | G97: 2 | H97: 0.14 | I97: 0.05 | J97: 23 | K97: 47 | L97: 24 | M97: 0
A98: Hungary | B98: Barbados | C98: 1992 | D98: 0 | E98: Exports & Imports | F98: 3 | G98: 1 | H98: 0.1 | I98: 0.02 | J98: 119 | K98: 120 | L98: 1 | M98: 0
A99: Hungary | B99: Central African Republic | C99: 1992 | D99: 0 | E99: Exports & Imports | F99: 1 | G99: 3 | H99: 0.03 | I99: 0.07 | J99: -1 | K99: 3 | L99: 4 | M99: 0
A100: Hungary | B100: Cameroon | C100: 1992 | D100: 0 | E100: Exports & Imports | F100: 4 | G100: 5 | H100: 0.14 | I100: 0.12 | J100: 411 | K100: 578 | L100: 167 | M100: 0.01
A101: Hungary | B101: Congo, Rep. | C101: 1992 | D101: 0 | E101: Exports & Imports | F101: 3 | G101: 5 | H101: 0.1 | I101: 0.12 | J101: 2 | K101: 18 | L101: 16 | M101: 0
A102: Hungary | B102: Comoros | C102: 1992 | D102: 0 | E102: Exports & Imports | F102: 1 | G102: 1 | H102: 0.03 | I102: 0.02 | J102: -1 | K102: 4 | L102: 5 | M102: 0
A103: Hungary | B103: Cuba | C103: 1992 | D103: 0 | E103: Exports & Imports | F103: 28 | G103: 8 | H103: 0.97 | I103: 0.19 | J103: 7974 | K103: 8173 | L103: 199 | M103: 0.08
A104: Hungary | B104: Djibouti | C104: 1992 | D104: 0 | E104: Exports & Imports | F104: 1 | G104: 2 | H104: 0.03 | I104: 0.05 | J104: 23 | K104: 29 | L104: 6 | M104: 0
A105: Hungary | B105: Dominican Republic | C105: 1992 | D105: 0 | E105: Exports & Imports | F105: 6 | G105: 3 | H105: 0.21 | I105: 0.07 | J105: 616 | K105: 667 | L105: 51 | M105: 0.01
A106: Hungary | B106: Falkland Island | C106: 1992 | D106: 0 | E106: Exports & Imports | F106: 1 | G106: 2 | H106: 0.03 | I106: 0.05 | J106: 19 | K106: 37 | L106: 18 | M106: 0
A107: Hungary | B107: Gabon | C107: 1992 | D107: 0 | E107: Exports & Imports | F107: 2 | G107: 2 | H107: 0.07 | I107: 0.05 | J107: 4 | K107: 21 | L107: 17 | M107: 0
... A110: Hungary | B110: Guinea-Bissau | C110: 1992 | D110: 0 | E110: Exports & Imports | F110: 5 | G110: 3 | H110: 0.17 | I110: 0.07 | J110: -6 | K110: 46 | L110: 52 | M110: 0
A111: Hungary | B111: Grenada | C111: 1992 | D111: 0 | E111: Exports & Imports | G111: 1 | I111: 0.02 | L111: 1
A112: Hungary | B112: Guyana | C112: 1992 | D112: 0 | E112: Exports & Imports | F112: 1 | G112: 1 | H112: 0.03 | I112: 0.02 | J112: 125 | K112: 126 | L112: 1 | M112: 0
A113: Hungary | B113: Haiti | C113: 1992 | D113: 0 | E113: Exports & Imports | F113: 7 | G113: 2 | H113: 0.24 | I113: 0.05 | J113: 39 | K113: 47 | L113: 8 | M113: 0
A114: Hungary | B114: Jamaica | C114: 1992 | D114: 0 | E114: Exports & Imports | F114: 13 | G114: 22 | H114: 0.45 | I114: 0.53 | J114: 451 | K114: 655 | L114: 204 | M114: 0.01
A115: Hungary | B115: Jordan | C115: 1992 | D115: 0 | E115: Exports & Imports | F115: 104 | G115: 4 | H115: 3.61 | I115: 0.1 | J115: 9243 | K115: 9275 | L115: 32 | M115: 0.09
A116: Hungary | B116: Kenya | C116: 1992 | D116: 0 | E116: Exports & Imports | F116: 30 | G116: 13 | H116: 1.04 | I116: 0.31 | J116: 483 | K116: 954 | L116: 471 | M116: 0.01
A117: Hungary | B117: Cambodia | C117: 1992 | D117: 0 | E117: Exports & Imports | F117: 1 | G117: 2 | H117: 0.03 | I117: 0.05 | J117: 57 | K117: 63 | L117: 6 | M117: 0
A118: Hungary | B118: Kuwait | C118: 1992 | D118: 0 | E118: Exports & Imports | F118: 151 | G118: 3 | H118: 5.25 | I118: 0.07 | J118: 20001 | K118: 20004 | L118: 3 | M118: 0.2
A119: Hungary | B119: Lao PDR | C119: 1992 | D119: 0 | E119: Exports & Imports | F119: 1 | G119: 4 | H119: 0.03 | I119: 0.1 | J119: -50 | K119: 11 | L119: 61 | M119: 0
A120: Hungary | B120: Lebanon | C120: 1992 | D120: 0 | E120: Exports & Imports | F120: 140 | G120: 27 | H120: 4.86 | I120: 0.65 | J120: 25165 | K120: 25458 | L120: 293 | M120: 0.25
A121: Hungary | B121: Liberia | C121: 1992 | D121: 0 | E121: Exports & Imports | F121: 3 | G121: 3 | H121: 0.1 | I121: 0.07 | J121: 318 | K121: 333 | L121: 15 | M121: 0
A122: Hungary | B122: Libya | C122: 1992 | D122: 0 | E122: Exports & Imports | F122: 39 | G122: 7 | H122: 1.36 | I122: 0.17 | J122: 7115 | K122: 7294 | L122: 179 | M122: 0.07
A123: Hungary | B123: St. Lucia | C123: 1992 | D123: 0 | E123: Exports & Imports | G123: 1 | I123: 0.02 | L123: 22
A124: Hungary | B124: Macao | C124: 1992 | D124: 0 | E124: Exports & Imports | F124: 6 | G124: 10 | H124: 0.21 | I124: 0.24 | J124: -143 | K124: 20 | L124: 163 | M124: 0
A125: Hungary | B125: Mali | C125: 1992 | D125: 0 | E125: Exports & Imports | F125: 1 | G125: 4 | H125: 0.03 | I125: 0.1 | J125: -20 | K125: 20 | L125: 40 | M125: 0
A126: Hungary | B126: Malta | C126: 1992 | D126: 0 | E126: Exports & Imports | F126: 68 | G126: 18 | H126: 2.36 | I126: 0.43 | J126: 3315 | K126: 3812 | L126: 497 | M126: 0.04
A127: Hungary | B127: Myanmar | C127: 1992 | D127: 0 | E127: Exports & Imports | F127: 22 | G127: 11 | H127: 0.76 | I127: 0.26 | J127: 182 | K127: 390 | L127: 208 | M127: 0
A128: Hungary | B128: Mongolia | C128: 1992 | D128: 0 | E128: Exports & Imports | F128: 23 | G128: 11 | H128: 0.8 | I128: 0.26 | J128: 2187 | K128: 2210 | L128: 23 | M128: 0.02
A129: Hungary | B129: Mauritania | C129: 1992 | D129: 0 | E129: Exports & Imports | F129: 5 | G129: 3 | H129: 0.17 | I129: 0.07 | J129: -132 | K129: 47 | L129: 179 | M129: 0
A130: Hungary | B130: Mauritius | C130: 1992 | D130: 0 | E130: Exports & Imports | F130: 13 | G130: 3 | H130: 0.45 | I130: 0.07 | J130: 377 | K130: 415 | L130: 38 | M130: 0
A131: Hungary | B131: Niger | C131: 1992 | D131: 0 | E131: Exports & Imports | F131: 8 | G131: 5 | H131: 0.28 | I131: 0.12 | J131: 216 | K131: 258 | L131: 42 | M131: 0
A132: Hungary | B132: Nepal | C132: 1992 | D132: 0 | E132: Exports & Imports | F132: 7 | G132: 10 | H132: 0.24 | I132: 0.24 | J132: 163 | K132: 179 | L132: 16 | M132: 0
A133: Hungary | B133: Nauru | C133: 1992 | D133: 0 | E133: Exports & Imports | F133: 4 | G133: 5 | H133: 0.14 | I133: 0.12 | J133: 56 | K133: 80 | L133: 24 | M133: 0
A134: Hungary | B134: Papua New Guinea | C134: 1992 | D134: 0 | E134: Exports & Imports | F134: 1 | G134: 2 | H134: 0.03 | I134: 0.05 | J134: 271 | K134: 278 | L134: 7 | M134: 0
A135: Hungary | B135: Qatar | C135: 1992 | D135: 0 | E135: Exports & Imports | F135: 19 | G135: 1 | H135: 0.66 | I135: 0.02 | J135: 2237 | K135: 2255 | L135: 18 | M135: 0.02
... A142: Hungary | B142: Somalia | C142: 1992 | D142: 0 | E142: Exports & Imports | F142: 3 | G142: 7 | H142: 0.1 | I142: 0.17 | J142: -96 | K142: 36 | L142: 132 | M142: 0
A143: Hungary | B143: Sao Tome and Principe | C143: 1992 | D143: 0 | E143: Exports & Imports | G143: 6 | I143: 0.14 | L143: 96
A144: Hungary | B144: Seychelles | C144: 1992 | D144: 0 | E144: Exports & Imports | F144: 3 | G144: 3 | H144: 0.1 | I144: 0.07 | J144: -13 | K144: 3 | L144: 16 | M144: 0
A145: Hungary | B145: Trinidad and Tobago | C145: 1992 | D145: 0 | E145: Exports & Imports | F145: 2 | G145: 12 | H145: 0.07 | I145: 0.29 | J145: -2 | K145: 31 | L145: 33 | M145: 0
A146: Hungary | B146: Tunisia | C146: 1992 | D146: 0 | E146: Exports & Imports | F146: 139 | G146: 19 | H146: 4.83 | I146: 0.45 | J146: 8770 | K146: 9081 | L146: 311 | M146: 0.09
A147: Hungary | B147: Tanzania | C147: 1992 | D147: 0 | E147: Exports & Imports | F147: 11 | G147: 2 | H147: 0.38 | I147: 0.05 | J147: 708 | K147: 995 | L147: 287 | M147: 0.01
A148: Hungary | B148: Us Msc.Pac.I | C148: 1992 | D148: 0 | E148: Exports & Imports | F148: 2 | G148: 7 | H148: 0.07 | I148: 0.17 | J148: -21 | K148: 22 | L148: 43 | M148: 0
A149: Hungary | B149: Vanuatu | C149: 1992 | D149: 0 | E149: Exports & Imports | G149: 1 | I149: 0.02 | L149: 4
A150: Hungary | B150: Yemen | C150: 1992 | D150: 0 | E150: Exports & Imports | F150: 28 | G150: 17 | H150: 0.97 | I150: 0.41 | J150: 6156 | K150: 6502 | L150: 346 | M150: 0.06
A151: Hungary | B151: Zambia | C151: 1992 | D151: 0 | E151: Exports & Imports | F151: 7 | G151: 1 | H151: 0.24 | I151: 0.02 | J151: 28 | K151: 92 | L151: 64 | M151: 0

Sheet Partner2001
A1: Reporter Name | B1: Partner Name | C1: Import Partner Share (%) | D1: Year | E1: Trade Flow | F1: No Of exported HS6 digit Products | G1: No Of imported HS6 digit Products | H1: Export Share in Total Products (%) | I1: Import Share in Total Products (%) | J1: Trade Balance (US$ Thousand) | K1: Export (US$ Thousand) | L1: Import (US$ Thousand) | M1: Import Partner Share (%) | N1: Export Partner Share (%) | O1: AHS Simple Average (%) | P1: AHS Weighted Average (%) | Q1: AHS Total Tariff Lines | R1: AHS Dutiable Tariff Lines Share (%) | S1: AHS Duty Free Tariff Lines Share (%) | T1: AHS Specific Tariff Lines Share (%) | U1: AHS AVE Tariff Lines Share (%) | V1: AHS MaxRate (%) | W1: AHS MinRate (%) | X1: AHS SpecificDuty Imports(US$ Thousand) | Y1: AHS Dutiable Imports (US$ Thousand) | Z1: AHS Duty Free Imports (US$ Thousand) | AA1: MFN Simple Average (%) | AB1: MFN Weighted Average (%) | AC1: MFN Total Tariff Lines | AD1: MFN Dutiable Tariff Lines Share (%) | AE1: MFN Duty Free Tariff Lines Share (%) | AF1: MFN Specific Tariff Lines Share (%) | AG1: MFN AVE Tariff Lines Share (%) | AH1: MFN MaxRate (%) | AI1: MFN MinRate (%) | AJ1: MFN SpecificDuty Imports (US$ Thousand) | AK1: MFN Dutiable Imports (US$ Thousand) | AL1: MFN Duty Free Imports (US$ Thousand) | AM1: No Of Tariff Agreement
A2: Hungary | B2: World | C2: 100 | D2: 2001 | E2: Exports & Imports | F2: 3353 | G2: 4358 | H2: 100 | I2: 100 | J2: -3184015 | K2: 30497719 | L2: 33681734 | M2: 100 | N2: 100
A3: Hungary | B3: Europe & Central Asia | C3: 76.67 | D3: 2001 | E3: Exports & Imports | F3: 3345 | G3: 4314 | H3: 99.76 | I3: 98.99 | J3: 1760937 | K3: 27586086 | L3: 25825149 | M3: 76.67 | N3: 90.45
A4: Hungary | B4: Germany | C4: 24.92 | D4: 2001 | E4: Exports & Imports | F4: 2582 | G4: 3849 | H4: 77.01 | I4: 88.32 | J4: 2466361 | K4: 10858885 | L4: 8392524 | M4: 24.92 | N4: 35.61
A5: Hungary | B5: East Asia & Pacific | C5: 15.04 | D5: 2001 | E5: Exports & Imports | F5: 1018 | G5: 2831 | H5: 30.36 | I5: 64.96 | J5: -4372212 | K5: 693186 | L5: 5065398 | M5: 15.04 | N5: 2.27
A6: Hungary | B6: Italy | C6: 7.86 | D6: 2001 | E6: Exports & Imports | F6: 1756 | G6: 3351 | H6: 52.37 | I6: 76.89 | J6: -742247 | K6: 1905165 | L6: 2647412 | M6: 7.86 | N6: 6.25
A7: Hungary | B7: Austria | C7: 7.39 | D7: 2001 | E7: Exports & Imports | F7: 2248 | G7: 3077 | H7: 67.04 | I7: 70.61 | J7: -71025 | K7: 2416789 | L7: 2487814 | M7: 7.39 | N7: 7.92
A8: Hungary | B8: Russian Federation | C8: 7.03 | D8: 2001 | E8: Exports & Imports | F8: 1058 | G8: 677 | H8: 31.55 | I8: 15.53 | J8: -1896981 | K8: 472337 | L8: 2369318 | M8: 7.03 | N8: 1.55
A9: Hungary | B9: France | C9: 4.69 | D9: 2001 | E9: Exports & Imports | F9: 1391 | G9: 2961 | H9: 41.49 | I9: 67.94 | J9: 239652 | K9: 1818804 | L9: 1579152 | M9: 4.69 | N9: 5.96
A10: Hungary | B10: Japan | C10: 4.62 | D10: 2001 | E10: Exports & Imports | F10: 452 | G10: 1665 | H10: 13.48 | I10: 38.21 | J10: -1382587 | K10: 172775 | L10: 1555362 | M10: 4.62 | N10: 0.57
A11: Hungary | B11: North America | C11: 4.43 | D11: 2001 | E11: Exports & Imports | F11: 1337 | G11: 2659 | H11: 39.87 | I11: 61.01 | J11: 79175 | K11: 1571342 | L11: 1492167 | M11: 4.43 | N11: 5.15
A12: Hungary | B12: United States | C12: 4.23 | D12: 2001 | E12: Exports & Imports | F12: 1266 | G12: 2588 | H12: 37.76 | I12: 59.38 | J12: 101064 | K12: 1525300 | L12: 1424236 | M12: 4.23 | N12: 5
A13: Hungary | B13: China | C13: 3.96 | D13: 2001 | E13: Exports & Imports | F13: 304 | G13: 1980 | H13: 9.07 | I13: 45.43 | J13: -1220876 | K13: 112698 | L13: 1333574 | M13: 3.96 | N13: 0.37
... A21: Hungary | B21: Singapore | C21: 1.54 | D21: 2001 | E21: Exports & Imports | F21: 201 | G21: 398 | H21: 5.99 | I21: 9.13 | J21: -369837 | K21: 148515 | L21: 518352 | M21: 1.54 | N21: 0.49
A22: Hungary | B22: Other Asia, nes | C22: 1.44 | D22: 2001 | E22: Exports & Imports | J22: -437335 | K22: 47599 | L22: 484934 | M22: 1.44 | N22: 0.16
A23: Hungary | B23: Malaysia | C23: 1.42 | D23: 2001 | E23: Exports & Imports | F23: 136 | G23: 561 | H23: 4.06 | I23: 12.87 | J23: -425456 | K23: 52107 | L23: 477563 | M23: 1.42 | N23: 0.17
A24: Hungary | B24: Switzerland | C24: 1.39 | D24: 2001 | E24: Exports & Imports | F24: 1198 | G24: 1985 | H24: 35.73 | I24: 45.55 | J24: -86067 | K24: 382378 | L24: 468445 | M24: 1.39 | N24: 1.25
A25: Hungary | B25: Korea, Rep. | C25: 1.23 | D25: 2001 | E25: Exports & Imports | F25: 197 | G25: 1065 | H25: 5.88 | I25: 24.44 | J25: -376489 | K25: 36687 | L25: 413176 | M25: 1.23 | N25: 0.12
A26: Hungary | B26: Latin America & Caribbean | C26: 1.21 | D26: 2001 | E26: Exports & Imports | F26: 514 | G26: 912 | H26: 15.33 | I26: 20.93 | J26: -243239 | K26: 165654 | L26: 408893 | M26: 1.21 | N26: 0.54
A27: Hungary | B27: Romania | C27: 1.07 | D27: 2001 | E27: Exports & Imports | F27: 2485 | G27: 1169 | H27: 74.11 | I27: 26.82 | J27: 402187 | K27: 764230 | L27: 362043 | M27: 1.07 | N27: 2.51
A28: Hungary | B28: Finland | C28: 1.05 | D28: 2001 | E28: Exports & Imports | F28: 553 | G28: 1030 | H28: 16.49 | I28: 23.63 | J28: -160024 | K28: 193624 | L28: 353648 | M28: 1.05 | N28: 0.63
A29: Hungary | B29: Sweden | C29: 1.03 | D29: 2001 | E29: Exports & Imports | F29: 788 | G29: 1564 | H29: 23.5 | I29: 35.89 | J29: -47182 | K29: 301182 | L29: 348364 | M29: 1.03 | N29: 0.99
A30: Hungary | B30: Ukraine | C30: 0.88 | D30: 2001 | E30: Exports & Imports | F30: 1359 | G30: 624 | H30: 40.53 | I30: 14.32 | J30: -85943 | K30: 209282 | L30: 295225 | M30: 0.88 | N30: 0.69
A31: Hungary | B31: Thailand | C31: 0.77 | D31: 2001 | E31: Exports & Imports | F31: 127 | G31: 741 | H31: 3.79 | I31: 17 | J31: -243323 | K31: 16365 | L31: 259688 | M31: 0.77 | N31: 0.05
A32: Hungary | B32: Brazil | C32: 0.67 | D32: 2001 | E32: Exports & Imports | F32: 213 | G32: 412 | H32: 6.35 | I32: 9.45 | J32: -169604 | K32: 56094 | L32: 225698 | M32: 0.67 | N32: 0.18
A33: Hungary | B33: Denmark | C33: 0.58 | D33: 2001 | E33: Exports & Imports | F33: 581 | G33: 1363 | H33: 17.33 | I33: 31.28 | J33: -39144 | K33: 156384 | L33: 195528 | M33: 0.58 | N33: 0.51
A34: Hungary | B34: Ireland | C34: 0.56 | D34: 2001 | E34: Exports & Imports | F34: 254 | G34: 566 | H34: 7.58 | I34: 12.99 | J34: 142345 | K34: 329507 | L34: 187162 | M34: 0.56 | N34: 1.08
... A112: Hungary | B112: Congo, Rep. | C112: 0 | D112: 2001 | E112: Exports & Imports | F112: 2 | G112: 1 | H112: 0.06 | I112: 0.02 | J112: -21 | K112: 6 | L112: 27 | M112: 0 | N112: 0
A113: Hungary | B113: Comoros | C113: 0 | D113: 2001 | E113: Exports & Imports | G113: 2 | I113: 0.05 | L113: 16 | M113: 0
A114: Hungary | B114: Cuba | C114: 0 | D114: 2001 | E114: Exports & Imports | F114: 25 | G114: 8 | H114: 0.75 | I114: 0.18 | J114: -139 | K114: 269 | L114: 408 | M114: 0 | N114: 0
A115: Hungary | B115: Cayman Islands | C115: 0 | D115: 2001 | E115: Exports & Imports | F115: 2 | G115: 1 | H115: 0.06 | I115: 0.02 | J115: 214 | K115: 215 | L115: 1 | M115: 0 | N115: 0
A116: Hungary | B116: Dominica | C116: 0 | D116: 2001 | E116: Exports & Imports | F116: 3 | G116: 7 | H116: 0.09 | I116: 0.16 | J116: -92 | K116: 28 | L116: 120 | M116: 0 | N116: 0
A117: Hungary | B117: Dominican Republic | C117: 0 | D117: 2001 | E117: Exports & Imports | F117: 7 | G117: 22 | H117: 0.21 | I117: 0.5 | J117: 380 | K117: 757 | L117: 377 | M117: 0 | N117: 0
A118: Hungary | B118: Algeria | C118: 0 | D118: 2001 | E118: Exports & Imports | F118: 78 | G118: 3 | H118: 2.33 | I118: 0.07 | J118: 10877 | K118: 11016 | L118: 139 | M118: 0 | N118: 0.04
A119: Hungary | B119: Ethiopia(excludes Eritrea) | C119: 0 | D119: 2001 | E119: Exports & Imports | F119: 31 | G119: 6 | H119: 0.92 | I119: 0.14 | J119: 2296 | K119: 2449 | L119: 153 | M119: 0 | N119: 0.01
A120: Hungary | B120: Fiji | C120: 0 | D120: 2001 | E120: Exports & Imports | F120: 5 | G120: 4 | H120: 0.15 | I120: 0.09 | J120: 12 | K120: 19 | L120: 7 | M120: 0 | N120: 0
A121: Hungary | B121: Falkland Island | C121: 0 | D121: 2001 | E121: Exports & Imports | G121: 3 | I121: 0.07 | L121: 3 | M121: 0
A122: Hungary | B122: Micronesia, Fed. Sts. | C122: 0 | D122: 2001 | E122: Exports & Imports | G122: 1 | I122: 0.02 | L122: 10 | M122: 0
A123: Hungary | B123: Gabon | C123: 0 | D123: 2001 | E123: Exports & Imports | F123: 17 | G123: 4 | H123: 0.51 | I123: 0.09 | J123: -19 | K123: 161 | L123: 180 | M123: 0 | N123: 0
A124: Hungary | B124: Georgia | C124: 0 | D124: 2001 | E124: Exports & Imports | F124: 50 | G124: 8 | H124: 1.49 | I124: 0.18 | J124: 5476 | K124: 5495 | L124: 19 | M124: 0 | N124: 0.02
A125: Hungary | B125: Ghana | C125: 0 | D125: 2001 | E125: Exports & Imports | F125: 16 | G125: 11 | H125: 0.48 | I125: 0.25 | J125: 128 | K125: 743 | L125: 615 | M125: 0 | N125: 0
A126: Hungary | B126: Gibraltar | C126: 0 | D126: 2001 | E126: Exports & Imports | F126: 15 | G126: 1 | H126: 0.45 | I126: 0.02 | J126: 444 | K126: 461 | L126: 17 | M126: 0 | N126: 0
A127: Hungary | B127: Gambia, The | C127: 0 | D127: 2001 | E127: Exports & Imports | F127: 7 | G127: 3 | H127: 0.21 | I127: 0.07 | J127: -8 | K127: 11 | L127: 19 | M127: 0 | N127: 0
A128: Hungary | B128: Equatorial Guinea | C128: 0 | D128: 2001 | E128: Exports & Imports | G128: 1 | I128: 0.02 | L128: 1 | M128: 0
A129: Hungary | B129: Grenada | C129: 0 | D129: 2001 | E129: Exports & Imports | F129: 1 | G129: 2 | H129: 0.03 | I129: 0.05 | J129: 106 | K129: 120 | L129: 14 | M129: 0 | N129: 0
A130: Hungary | B130: Guatemala | C130: 0 | D130: 2001 | E130: Exports & Imports | F130: 14 | G130: 17 | H130: 0.42 | I130: 0.39 | J130: -537 | K130: 264 | L130: 801 | M130: 0 | N130: 0
A131: Hungary | B131: Guyana | C131: 0 | D131: 2001 | E131: Exports & Imports | F131: 1 | G131: 4 | H131: 0.03 | I131: 0.09 | J131: 4 | K131: 12 | L131: 8 | M131: 0 | N131: 0
A132: Hungary | B132: Honduras | C132: 0 | D132: 2001 | E132: Exports & Imports | F132: 5 | G132: 16 | H132: 0.15 | I132: 0.37 | J132: -395 | K132: 471 | L132: 866 | M132: 0 | N132: 0
A133: Hungary | B133: Haiti | C133: 0 | D133: 2001 | E133: Exports & Imports | F133: 3 | G133: 5 | H133: 0.09 | I133: 0.11 | J133: 223 | K133: 233 | L133: 10 | M133: 0 | N133: 0
A134: Hungary | B134: Iceland | C134: 0 | D134: 2001 | E134: Exports & Imports | F134: 57 | G134: 35 | H134: 1.7 | I134: 0.8 | J134: 1795 | K134: 2274 | L134: 479 | M134: 0 | N134: 0.01
A135: Hungary | B135: Jamaica | C135: 0 | D135: 2001 | E135: Exports & Imports | F135: 28 | G135: 11 | H135: 0.84 | I135: 0.25 | J135: 2671 | K135: 2734 | L135: 63 | M135: 0 | N135: 0.01
A136: Hungary | B136: Jordan | C136: 0 | D136: 2001 | E136: Exports & Imports | F136: 57 | G136: 9 | H136: 1.7 | I136: 0.21 | J136: 6309 | K136: 6348 | L136: 39 | M136: 0 | N136: 0.02
A137: Hungary | B137: Kenya | C137: 0 | D137: 2001 | E137: Exports & Imports | F137: 46 | G137: 24 | H137: 1.37 | I137: 0.55 | J137: 632 | K137: 1352 | L137: 720 | M137: 0 | N137: 0
A138: Hungary | B138: Kyrgyz Republic | C138: 0 | D138: 2001 | E138: Exports & Imports | F138: 24 | G138: 2 | H138: 0.72 | I138: 0.05 | J138: 1001 | K138: 1746 | L138: 745 | M138: 0 | N138: 0.01
A139: Hungary | B139: Cambodia | C139: 0 | D139: 2001 | E139: Exports & Imports | F139: 5 | G139: 34 | H139: 0.15 | I139: 0.78 | J139: -522 | K139: 117 | L139: 639 | M139: 0 | N139: 0
A140: Hungary | B140: Kiribati | C140: 0 | D140: 2001 | E140: Exports & Imports | G140: 3 | I140: 0.07 | L140: 3 | M140: 0
A141: Hungary | B141: St. Kitts and Nevis | C141: 0 | D141: 2001 | E141: Exports & Imports | G141: 9 | I141: 0.21 | L141: 146 | M141: 0
A142: Hungary | B142: Kuwait | C142: 0 | D142: 2001 | E142: Exports & Imports | F142: 69 | G142: 1 | H142: 2.06 | I142: 0.02 | J142: 17688 | K142: 17689 | L142: 1 | M142: 0 | N142: 0.06
A143: Hungary | B143: Lao PDR | C143: 0 | D143: 2001 | E143: Exports & Imports | F143: 10 | G143: 27 | H143: 0.3 | I143: 0.62 | J143: -1389 | K143: 41 | L143: 1430 | M143: 0 | N143: 0
A144: Hungary | B144: Lebanon | C144: 0 | D144: 2001 | E144: Exports & Imports | F144: 86 | G144: 17 | H144: 2.56 | I144: 0.39 | J144: 14349 | K144: 15468 | L144: 1119 | M144: 0 | N144: 0.05
A145: Hungary | B145: Libya | C145: 0 | D145: 2001 | E145: Exports & Imports | F145: 50 | G145: 2 | H145: 1.49 | I145: 0.05 | J145: 4687 | K145: 4928 | L145: 241 | M145: 0 | N145: 0.02
A146: Hungary | B146: St. Lucia | C146: 0 | D146: 2001 | E146: Exports & Imports | F146: 2 | G146: 4 | H146: 0.06 | I146: 0.09 | J146: 20 | K146: 28 | L146: 8 | M146: 0 | N146: 0
A147: Hungary | B147: Macao | C147: 0 | D147: 2001 | E147: Exports & Imports | F147: 3 | G147: 78 | H147: 0.09 | I147: 1.79 | J147: -1484 | K147: 72 | L147: 1556 | M147: 0 | N147: 0
A148: Hungary | B148: Madagascar | C148: 0 | D148: 2001 | E148: Exports & Imports | F148: 6 | G148: 29 | H148: 0.18 | I148: 0.67 | J148: -338 | K148: 58 | L148: 396 | M148: 0 | N148: 0
A149: Hungary | B149: Maldives | C149: 0 | D149: 2001 | E149: Exports & Imports | F149: 3 | G149: 4 | H149: 0.09 | I149: 0.09 | J149: 65 | K149: 97 | L149: 32 | M149: 0 | N149: 0
A150: Hungary | B150: Mali | C150: 0 | D150: 2001 | E150: Exports & Imports | F150: 7 | G150: 11 | H150: 0.21 | I150: 0.25 | J150: 185 | K150: 348 | L150: 163 | M150: 0 | N150: 0
A151: Hungary | B151: Myanmar | C151: 0 | D151: 2001 | E151: Exports & Imports | F151: 6 | G151: 43 | H151: 0.18 | I151: 0.99 | J151: -748 | K151: 274 | L151: 1022 | M151: 0 | N151: 0
A152: Hungary | B152: Mongolia | C152: 0 | D152: 2001 | E152: Exports & Imports | F152: 25 | G152: 1 | H152: 0.75 | I152: 0.02 | J152: 1583 | K152: 1589 | L152: 6 | M152: 0 | N152: 0.01
A153: Hungary | B153: Mozambique | C153: 0 | D153: 2001 | E153: Exports & Imports | F153: 5 | G153: 6 | H153: 0.15 | I153: 0.14 | J153: -291 | K153: 35 | L153: 326 | M153: 0 | N153: 0
A154: Hungary | B154: Mauritania | C154: 0 | D154: 2001 | E154: Exports & Imports | F154: 5 | G154: 8 | H154: 0.15 | I154: 0.18 | J154: 797 | K154: 834 | L154: 37 | M154: 0 | N154: 0
A155: Hungary | B155: Montserrat | C155: 0 | D155: 2001 | E155: Exports & Imports | G155: 1 | I155: 0.02 | L155: 3 | M155: 0
A156: Hungary | B156: Mauritius | C156: 0 | D156: 2001 | E156: Exports & Imports | F156: 27 | G156: 27 | H156: 0.81 | I156: 0.62 | J156: 403 | K156: 788 | L156: 385 | M156: 0 | N156: 0
A157: Hungary | B157: Namibia | C157: 0 | D157: 2001 | E157: Exports & Imports | F157: 6 | G157: 6 | H157: 0.18 | I157: 0.14 | J157: 12 | K157: 31 | L157: 19 | M157: 0 | N157: 0
A158: Hungary | B158: New Caledonia | C158: 0 | D158: 2001 | E158: Exports & Imports | F158: 1 | G158: 1 | H158: 0.03 | I158: 0.02 | J158: 13 | K158: 14 | L158: 1 | M158: 0 | N158: 0
A159: Hungary | B159: Nigeria | C159: 0 | D159: 2001 | E159: Exports & Imports | F159: 59 | G159: 9 | H159: 1.76 | I159: 0.21 | J159: 5052 | K159: 5557 | L159: 505 | M159: 0 | N159: 0.02
A160: Hungary | B160: Nicaragua | C160: 0 | D160: 2001 | E160: Exports & Imports | F160: 3 | G160: 19 | H160: 0.09 | I160: 0.44 | J160: -553 | K160: 116 | L160: 669 | M160: 0 | N160: 0
A161: Hungary | B161: Nepal | C161: 0 | D161: 2001 | E161: Exports & Imports | F161: 7 | G161: 39 | H161: 0.21 | I161: 0.89 | J161: -119 | K161: 59 | L161: 178 | M161: 0 | N161: 0
A162: Hungary | B162: Oman | C162: 0 | D162: 2001 | E162: Exports & Imports | F162: 34 | G162: 4 | H162: 1.01 | I162: 0.09 | J162: 1744 | K162: 1753 | L162: 9 | M162: 0 | N162: 0.01
A163: Hungary | B163: Panama | C163: 0 | D163: 2001 | E163: Exports & Imports | F163: 45 | G163: 16 | H163: 1.34 | I163: 0.37 | J163: -224 | K163: 1237 | L163: 1461 | M163: 0 | N163: 0
A164: Hungary | B164: Papua New Guinea | C164: 0 | D164: 2001 | E164: Exports & Imports | G164: 4 | I164: 0.09 | L164: 153 | M164: 0
A165: Hungary | B165: Korea, Dem. Rep. | C165: 0 | D165: 2001 | E165: Exports & Imports | F165: 27 | G165: 68 | H165: 0.81 | I165: 1.56 | J165: -34 | K165: 488 | L165: 522 | M165: 0 | N165: 0
A166: Hungary | B166: Paraguay | C166: 0 | D166: 2001 | E166: Exports & Imports | F166: 3 | G166: 3 | H166: 0.09 | I166: 0.07 | J166: -691 | K166: 106 | L166: 797 | M166: 0 | N166: 0
A167: Hungary | B167: Qatar | C167: 0 | D167: 2001 | E167: Exports & Imports | F167: 24 | G167: 1 | H167: 0.72 | I167: 0.02 | J167: 1034 | K167: 1035 | L167: 1 | M167: 0 | N167: 0
A168: Hungary | B168: Rwanda | C168: 0 | D168: 2001 | E168: Exports & Imports | F168: 2 | G168: 5 | H168: 0.06 | I168: 0.11 | J168: -435 | K168: 10 | L168: 445 | M168: 0 | N168: 0
A169: Hungary | B169: Fm Sudan | C169: 0 | D169: 2001 | E169: Exports & Imports | F169: 10 | G169: 6 | H169: 0.3 | I169: 0.14 | J169: -347 | K169: 390 | L169: 737 | M169: 0 | N169: 0
A170: Hungary | B170: Senegal | C170: 0 | D170: 2001 | E170: Exports & Imports | F170: 25 | G170: 19 | H170: 0.75 | I170: 0.44 | J170: 501 | K170: 581 | L170: 80 | M170: 0 | N170: 0
A171: Hungary | B171: Sierra Leone | C171: 0 | D171: 2001 | E171: Exports & Imports | F171: 34 | G171: 30 | H171: 1.01 | I171: 0.69 | J171: 571 | K171: 939 | L171: 368 | M171: 0 | N171: 0
A172: Hungary | B172: El Salvador | C172: 0 | D172: 2001 | E172: Exports & Imports | F172: 8 | G172: 13 | H172: 0.24 | I172: 0.3 | J172: -32 | K172: 302 | L172: 334 | M172: 0 | N172: 0
A173: Hungary | B173: San Marino | C173: 0 | D173: 2001 | E173: Exports & Imports | F173: 8 | G173: 7 | H173: 0.24 | I173: 0.16 | J173: 108 | K173: 172 | L173: 64 | M173: 0 | N173: 0
A174: Hungary | B174: Sao Tome and Principe | C174: 0 | D174: 2001 | E174: Exports & Imports | F174: 1 | G174: 7 | H174: 0.03 | I174: 0.16 | J174: -30 | K174: 2 | L174: 32 | M174: 0 | N174: 0
A175: Hungary | B175: Suriname | C175: 0 | D175: 2001 | E175: Exports & Imports | F175: 3 | G175: 2 | H175: 0.09 | I175: 0.05 | J175: -21 | K175: 26 | L175: 47 | M175: 0 | N175: 0
A176: Hungary | B176: Eswatini | C176: 0 | D176: 2001 | E176: Exports & Imports | G176: 10 | I176: 0.23 | L176: 86 | M176: 0
A177: Hungary | B177: Seychelles | C177: 0 | D177: 2001 | E177: Exports & Imports | F177: 62 | G177: 5 | H177: 1.85 | I177: 0.11 | J177: 699 | K177: 1235 | L177: 536 | M177: 0 | N177: 0
A178: Hungary | B178: Syrian Arab Republic | C178: 0 | D178: 2001 | E178: Exports & Imports | F178: 176 | G178: 47 | H178: 5.25 | I178: 1.08 | J178: 17977 | K178: 19168 | L178: 1191 | M178: 0 | N178: 0.06
A179: Hungary | B179: Chad | C179: 0 | D179: 2001 | E179: Exports & Imports | F179: 2 | G179: 2 | H179: 0.06 | I179: 0.05 | J179: -412 | K179: 44 | L179: 456 | M179: 0 | N179: 0
A180: Hungary | B180: Turkmenistan | C180: 0 | D180: 2001 | E180: Exports & Imports | F180: 59 | G180: 4 | H180: 1.76 | I180: 0.09 | J180: 1010 | K180: 1472 | L180: 462 | M180: 0 | N180: 0
A181: Hungary | B181: Tonga | C181: 0 | D181: 2001 | E181: Exports & Imports | G181: 1 | I181: 0.02 | L181: 2 | M181: 0
A182: Hungary | B182: Trinidad and Tobago | C182: 0 | D182: 2001 | E182: Exports & Imports | F182: 6 | G182: 3 | H182: 0.18 | I182: 0.07 | J182: 146 | K182: 153 | L182: 7 | M182: 0 | N182: 0
A183: Hungary | B183: Tuvalu | C183: 0 | D183: 2001 | E183: Exports & Imports | G183: 2 | I183: 0.05 | L183: 9 | M183: 0
A184: Hungary | B184: Uruguay | C184: 0 | D184: 2001 | E184: Exports & Imports | F184: 35 | G184: 15 | H184: 1.04 | I184: 0.34 | J184: 696 | K184: 1157 | L184: 461 | M184: 0 | N184: 0
...

Sheet Partner2008
A1: Reporter Name | B1: Partner Name | C1: Import Partner Share (%) | D1: Year | E1: Trade Flow | F1: No Of exported HS6 digit Products | G1: No Of imported HS6 digit Products | H1: Export Share in Total Products (%) | I1: Import Share in Total Products (%) | J1: Trade Balance (US$ Thousand) | K1: Export (US$ Thousand) | L1: Import (US$ Thousand) | M1: Import Partner Share (%) | N1: Export Partner Share (%) | O1: AHS Simple Average (%) | P1: AHS Weighted Average (%) | Q1: AHS Total Tariff Lines | R1: AHS Dutiable Tariff Lines Share (%) | S1: AHS Duty Free Tariff Lines Share (%) | T1: AHS Specific Tariff Lines Share (%) | U1: AHS AVE Tariff Lines Share (%) | V1: AHS MaxRate (%) | W1: AHS MinRate (%) | X1: AHS SpecificDuty Imports(US$ Thousand) | Y1: AHS Dutiable Imports (US$ Thousand) | Z1: AHS Duty Free Imports (US$ Thousand) | AA1: MFN Simple Average (%) | AB1: MFN Weighted Average (%) | AC1: MFN Total Tariff Lines | AD1: MFN Dutiable Tariff Lines Share (%) | AE1: MFN Duty Free Tariff Lines Share (%) | AF1: MFN Specific Tariff Lines Share (%) | AG1: MFN AVE Tariff Lines Share (%) | AH1: MFN MaxRate (%) | AI1: MFN MinRate (%) | AJ1: MFN SpecificDuty Imports (US$ Thousand) | AK1: MFN Dutiable Imports (US$ Thousand) | AL1: MFN Duty Free Imports (US$ Thousand) | AM1: No Of Tariff Agreement
A2: Hungary | B2: World | C2: 100 | D2: 2008 | E2: Exports & Imports | F2: 3057 | G2: 3977 | H2: 100 | I2: 100 | J2: -573558 | K2: 108211166 | L2: 108784724 | M2: 100 | N2: 100 | O2: 2.27 | P2: 1.11 | Q2: 83800 | R2: 37.47 | S2: 58.42 | T2: 0.9 | U2: 3.21 | V2: 174.79 | W2: 0 | X2: 37026 | Y2: 9521416 | Z2: 19567735 | AA2: 5.46 | AB2: 1.74 | AC2: 14237 | AD2: 62.98 | AE2: 26.52 | AF2: 0.19 | AG2: 1.59 | AH2: 457.68 | AI2: 0 | AJ2: 40353 | AK2: 14280897 | AL2: 14808254
A3: Hungary | B3: Europe & Central Asia | C3: 82.04 | D3: 2008 | E3: Exports & Imports | F3: 3048 | G3: 3967 | H3: 99.71 | I3: 99.75 | J3: 9585438 | K3: 98834544 | L3: 89249106 | M3: 82.04 | N3: 91.33 | O3: 1.07 | P3: 0.68 | Q3: 23806 | R3: 15.25 | S3: 80.57 | T3: 0.87 | U3: 3.32 | V3: 174.79 | W3: 0 | X3: 6492 | Y3: 587386 | Z3: 9189477 | AA3: 4.5 | AB3: 1.49 | AC3: 8894 | AD3: 67.01 | AE3: 25.7 | AF3: 0.39 | AG3: 2.33 | AH3: 174.79 | AI3: 0 | AJ3: 9485 | AK3: 2762470 | AL3: 7014393
A4: Hungary | B4: Germany | C4: 25.53 | D4: 2008 | E4: Exports & Imports | F4: 2102 | G4: 3709 | H4: 68.76 | I4: 93.26 | J4: 1132719 | K4: 28909331 | L4: 27776612 | M4: 25.53 | N4: 26.72
A5: Hungary | B5: East Asia & Pacific | C5: 12.96 | D5: 2008 | E5: Exports & Imports | F5: 1219 | G5: 2506 | H5: 39.88 | I5: 63.01 | J5: -11372201 | K5: 2723239 | L5: 14095440 | M5: 12.96 | N5: 2.52 | O5: 2.73 | P5: 1.1 | Q5: 29597 | R5: 49.8 | S5: 47.5 | T5: 0.71 | U5: 1.99 | V5: 174.79 | W5: 0 | X5: 8740 | Y5: 5978915 | Z5: 7980931 | AA5: 4.35 | AB5: 1.75 | AC5: 8543 | AD5: 69.34 | AE5: 26.06 | AF5: 0.23 | AG5: 1.1 | AH5: 174.79 | AI5: 0 | AJ5: 8740 | AK5: 8218106 | AL5: 5741740
A6: Hungary | B6: Russian Federation | C6: 9.34 | D6: 2008 | E6: Exports & Imports | F6: 1096 | G6: 448 | H6: 35.85 | I6: 11.26 | J6: -6285083 | K6: 3872211 | L6: 10157294 | M6: 9.34 | N6: 3.58 | O6: 0.97 | P6: 0.06 | Q6: 2292 | R6: 20.2 | S6: 74.3 | T6: 1 | U6: 4.49 | V6: 50.15 | W6: 0 | X6: 520 | Y6: 112430 | Z6: 5379981 | AA6: 2.97 | AB6: 0.4 | AC6: 2292 | AD6: 59.42 | AE6: 34.9 | AF6: 1 | AG6: 4.67 | AH6: 50.15 | AI6: 0 | AJ6: 520 | AK6: 801032 | AL6: 4691379
A7: Hungary | B7: Austria | C7: 6.17 | D7: 2008 | E7: Exports & Imports | F7: 1796 | G7: 3173 | H7: 58.75 | I7: 79.78 | J7: -1412072 | K7: 5303746 | L7: 6715818 | M7: 6.17 | N7: 4.9
A8: Hungary | B8: China | C8: 5.63 | D8: 2008 | E8: Exports & Imports | F8: 656 | G8: 2161 | H8: 21.46 | I8: 54.34 | J8: -5019133 | K8: 1110516 | L8: 6129649 | M8: 5.63 | N8: 1.03 | O8: 2.06 | P8: 0.31 | Q8: 7330 | R8: 31.79 | S8: 65.58 | T8: 0.76 | U8: 1.87 | V8: 174.79 | W8: 0 | X8: 2132 | Y8: 1556512 | Z8: 4553777 | AA8: 4.28 | AB8: 1.56 | AC8: 7330 | AD8: 70.53 | AE8: 26.62 | AF8: 0.76 | AG8: 2.09 | AH8: 174.79 | AI8: 0 | AJ8: 2132 | AK8: 3422054 | AL8: 2688235
A9: Hungary | B9: Netherlands | C9: 4.52 | D9: 2008 | E9: Exports & Imports | F9: 1005 | G9: 2577 | H9: 32.88 | I9: 64.8 | J9: -1832993 | K9: 3087636 | L9: 4920629 | M9: 4.52 | N9: 2.85
A10: Hungary | B10: France | C10: 4.35 | D10: 2008 | E10: Exports & Imports | F10: 1168 | G10: 2583 | H10: 38.21 | I10: 64.95 | J10: 343386 | K10: 5072915 | L10: 4729529 | M10: 4.35 | N10: 4.69
A11: Hungary | B11: Italy | C11: 4.24 | D11: 2008 | E11: Exports & Imports | F11: 1404 | G11: 2951 | H11: 45.93 | I11: 74.2 | J11: 1146600 | K11: 5759189 | L11: 4612589 | M11: 4.24 | N11: 5.32
A12: Hungary | B12: Poland | C12: 3.96 | D12: 2008 | E12: Exports & Imports | F12: 1456 | G12: 2250 | H12: 47.63 | I12: 56.58 | J12: -4203 | K12: 4302175 | L12: 4306378 | M12: 3.96 | N12: 3.98
A13: Hungary | B13: Czech Republic | C13: 3.79 | D13: 2008 | E13: Exports & Imports | F13: 1706 | G13: 2338 | H13: 55.81 | I13: 58.79 | J13: 183914 | K13: 4306426 | L13: 4122512 | M13: 3.79 | N13: 3.98
A14: Hungary | B14: Slovak Republic | C14: 3.53 | D14: 2008 | E14: Exports & Imports | F14: 2147 | G14: 2218 | H14: 70.23 | I14: 55.77 | J14: 1266404 | K14: 5104987 | L14: 3838583 | M14: 3.53 | N14: 4.72
A15: Hungary | B15: Japan | C15: 2.58 | D15: 2008 | E15: Exports & Imports | F15: 592 | G15: 1106 | H15: 19.37 | I15: 27.81 | J15: -2316248 | K15: 492511 | L15: 2808759 | M15: 2.58 | N15: 0.46 | O15: 3.22 | P15: 2.17 | Q15: 4164 | R15: 70.53 | S15: 28.7 | T15: 0.34 | U15: 0.43 | V15: 40.6 | W15: 0 | X15: 50 | Y15: 1854157 | Z15: 850141 | AA15: 3.22 | AB15: 2.17 | AC15: 4164 | AD15: 70.53 | AE15: 28.7 | AF15: 0.34 | AG15: 0.43 | AH15: 40.6 | AI15: 0 | AJ15: 50 | AK15: 1854157 | AL15: 850141
A16: Hungary | B16: Belgium | C16: 2.32 | D16: 2008 | E16: Exports & Imports | F16: 901 | G16: 2045 | H16: 29.47 | I16: 51.42 | J16: -693900 | K16: 1832948 | L16: 2526848 | M16: 2.32 | N16: 1.69
A17: Hungary | B17: Romania | C17: 2.15 | D17: 2008 | E17: Exports & Imports | F17: 2452 | G17: 1500 | H17: 80.21 | I17: 37.72 | J17: 3398348 | K17: 5739594 | L17: 2341246 | M17: 2.15 | N17: 5.3
A18: Hungary | B18: North America | C18: 2.02 | D18: 2008 | E18: Exports & Imports | F18: 1155 | G18: 2155 | H18: 37.78 | I18: 54.19 | J18: 495611 | K18: 2695194 | L18: 2199583 | M18: 2.02 | N18: 2.49 | O18: 3.73 | P18: 1.53 | Q18: 10187 | R18: 66.49 | S18: 29.32 | T18: 1.16 | U18: 3.03 | V18: 174.79 | W18: 0 | X18: 19345 | Y18: 1061612 | Z18: 1092760 | AA18: 3.9 | AB18: 1.53 | AC18: 7467 | AD18: 66.81 | AE18: 28.61 | AF18: 0.75 | AG18: 2.61 | AH18: 174.79 | AI18: 0 | AJ18: 19345 | AK18: 1061612 | AL18: 1092760
A19: Hungary | B19: United Kingdom | C19: 1.95 | D19: 2008 | E19: Exports & Imports | F19: 973 | G19: 2101 | H19: 31.83 | I19: 52.83 | J19: 2935588 | K19: 5055838 | L19: 2120250 | M19: 1.95 | N19: 4.67
A20: Hungary | B20: Other Asia, nes | C20: 1.8 | D20: 2008 | E20: Exports & Imports | J20: -1901035 | K20: 61321 | L20: 1962356 | M20: 1.8 | N20: 0.06
A21: Hungary | B21: United States | C21: 1.8 | D21: 2008 | E21: Exports & Imports | F21: 1086 | G21: 2094 | H21: 35.52 | I21: 52.65 | J21: 515920 | K21: 2478477 | L21: 1962557 | M21: 1.8 | N21: 2.29 | O21: 3.88 | P21: 1.56 | Q21: 7333 | R21: 66.89 | S21: 28.49 | T21: 1.02 | U21: 3.6 | V21: 174.79 | W21: 0 | X21: 18895 | Y21: 961302 | Z21: 956742 | AA21: 3.88 | AB21: 1.56 | AC21: 7333 | AD21: 66.89 | AE21: 28.49 | AF21: 1.02 | AG21: 3.6 | AH21: 174.79 | AI21: 0 | AJ21: 18895 | AK21: 961302 | AL21: 956742
A22: Hungary | B22: Korea, Rep. | C22: 1.69 | D22: 2008 | E22: Exports & Imports | F22: 307 | G22: 790 | H22: 10.04 | I22: 19.86 | J22: -1473411 | K22: 366267 | L22: 1839678 | M22: 1.69 | N22: 0.34 | O22: 3.4 | P22: 2.38 | Q22: 3245 | R22: 71.03 | S22: 27.49 | T22: 0.09 | U22: 1.39 | V22: 33.93 | W22: 0 | X22: 292 | Y22: 1343477 | Z22: 493650 | AA22: 3.4 | AB22: 2.38 | AC22: 3245 | AD22: 71.03 | AE22: 27.49 | AF22: 0.09 | AG22: 1.39 | AH22: 33.93 | AI22: 0 | AJ22: 292 | AK22: 1343477 | AL22: 493650
A23: Hungary | B23: Spain | C23: 1.47 | D23: 2008 | E23: Exports & Imports | F23: 737 | G23: 1736 | H23: 24.11 | I23: 43.65 | J23: 1412171 | K23: 3011143 | L23: 1598972 | M23: 1.47 | N23: 2.78
A24: Hungary | B24: Ukraine | C24: 1.44 | D24: 2008 | E24: Exports & Imports | F24: 1748 | G24: 697 | H24: 57.18 | I24: 17.53 | J24: 603619 | K24: 2165828 | L24: 1562209 | M24: 1.44 | N24: 2 | O24: 2.05 | P24: 0.36 | Q24: 2788 | R24: 21.81 | S24: 75.07 | T24: 0.86 | U24: 2.26 | V24: 174.79 | W24: 0 | X24: 35 | Y24: 141730 | Z24: 1334422 | AA24: 4.07 | AB24: 1.02 | AC24: 2788 | AD24: 65.96 | AE24: 30.92 | AF24: 0.86 | AG24: 2.26 | AH24: 174.79 | AI24: 0 | AJ24: 35 | AK24: 415157 | AL24: 1060995
A25: Hungary | B25: Hong Kong, China | C25: 1.2 | D25: 2008 | E25: Exports & Imports | F25: 351 | G25: 1008 | H25: 11.48 | I25: 25.35 | J25: -1076190 | K25: 230230 | L25: 1306420 | M25: 1.2 | N25: 0.21 | O25: 3.87 | P25: 1.68 | Q25: 3453 | R25: 72.84 | S25: 26.38 | T25: 0.17 | U25: 0.61 | V25: 34.47 | W25: 0 | X25: 2 | Y25: 838120 | Z25: 466123 | AA25: 3.87 | AB25: 1.68 | AC25: 3453 | AD25: 72.84 | AE25: 26.38 | AF25: 0.17 | AG25: 0.61 | AH25: 34.47 | AI25: 0 | AJ25: 2 | AK25: 838120 | AL25: 466123
A26: Hungary | B26: Slovenia | C26: 0.9 | D26: 2008 | E26: Exports & Imports | F26: 1423 | G26: 1252 | H26: 46.55 | I26: 31.48 | J26: 273075 | K26: 1255332 | L26: 982257 | M26: 0.9 | N26: 1.16
A27: Hungary | B27: Switzerland | C27: 0.89 | D27: 2008 | E27: Exports & Imports | F27: 1281 | G27: 1712 | H27: 41.9 | I27: 43.05 | J27: 396277 | K27: 1363649 | L27: 967372 | M27: 0.89 | N27: 1.26 | O27: 0.28 | P27: 0.03 | Q27: 6161 | R27: 1.74 | S27: 96.14 | T27: 0.03 | U27: 2.09 | V27: 174.79 | W27: 0 | X27: 1 | Y27: 3706 | Z27: 957114 | AA27: 4.01 | AB27: 1.34 | AC27: 6161 | AD27: 67.08 | AE27: 27.66 | AF27: 1.3 | AG27: 3.96 | AH27: 174.79 | AI27: 0 | AJ27: 2899 | AK27: 367208 | AL27: 593612
A28: Hungary | B28: Sweden | C28: 0.88 | D28: 2008 | E28: Exports & Imports | F28: 732 | G28: 1187 | H28: 23.95 | I28: 29.85 | J28: 142853 | K28: 1100585 | L28: 957732 | M28: 0.88 | N28: 1.02
A29: Hungary | B29: Finland | C29: 0.76 | D29: 2008 | E29: Exports & Imports | F29: 491 | G29: 735 | H29: 16.06 | I29: 18.48 | J29: -277058 | K29: 549499 | L29: 826557 | M29: 0.76 | N29: 0.51
A30: Hungary | B30: Singapore | C30: 0.73 | D30: 2008 | E30: Exports & Imports | F30: 277 | G30: 385 | H30: 9.06 | I30: 9.68 | J30: -586857 | K30: 210892 | L30: 797749 | M30: 0.73 | N30: 0.19 | O30: 2.73 | P30: 0.4 | Q30: 1757 | R30: 70.18 | S30: 28.91 | T30: 0.28 | U30: 0.63 | V30: 29.16 | W30: 0 | X30: 79 | Y30: 163026 | Z30: 633988 | AA30: 2.73 | AB30: 0.4 | AC30: 1757 | AD30: 70.18 | AE30: 28.91 | AF30: 0.28 | AG30: 0.63 | AH30: 29.16 | AI30: 0 | AJ30: 79 | AK30: 163026 | AL30: 633988
A31: Hungary | B31: Denmark | C31: 0.7 | D31: 2008 | E31: Exports & Imports | F31: 592 | G31: 1110 | H31: 19.37 | I31: 27.91 | J31: 22120 | K31: 778629 | L31: 756509 | M31: 0.7 | N31: 0.72
A32: Hungary | B32: Turkey | C32: 0.55 | D32: 2008 | E32: Exports & Imports | F32: 743 | G32: 1400 | H32: 24.3 | I32: 35.2 | J32: 757958 | K32: 1353370 | L32: 595412 | M32: 0.55 | N32: 1.25 | O32: 0.28 | P32: 0.18 | Q32: 4993 | R32: 0.24 | S32: 93.73 | T32: 1.36 | U32: 4.67 | V32: 174.79 | W32: 0 | X32: 3657 | Y32: 13713 | Z32: 578001 | AA32: 5.01 | AB32: 4.17 | AC32: 4993 | AD32: 73.08 | AE32: 20.39 | AF32: 1.36 | AG32: 5.17 | AH32: 174.79 | AI32: 0 | AJ32: 3657 | AK32: 452855 | AL32: 138859
A33: Hungary | B33: South Asia | C33: 0.53 | D33: 2008 | E33: Exports & Imports | F33: 487 | G33: 899 | H33: 15.93 | I33: 22.61 | J33: -329418 | K33: 243102 | L33: 572520 | M33: 0.53 | N33: 0.22 | O33: 3.74 | P33: 2.18 | Q33: 4144 | R33: 59.24 | S33: 37.16 | T33: 0.8 | U33: 2.8 | V33: 174.79 | W33: 0 | X33: 36 | Y33: 317387 | Z33: 252851 | AA33: 4.44 | AB33: 2.3 | AC33: 3415 | AD33: 70.13 | AE33: 27.03 | AF33: 0.41 | AG33: 1.93 | AH33: 174.79 | AI33: 0 | AJ33: 36 | AK33: 325908 | AL33: 244330
A34: Hungary | B34: India | C34: 0.5 | D34: 2008 | E34: Exports & Imports | F34: 411 | G34: 794 | H34: 13.44 | I34: 19.96 | J34: -398587 | K34: 146955 | L34: 545542 | M34: 0.5 | N34: 0.14 | O34: 4.03 | P34: 1.91 | Q34: 3111 | R34: 68.27 | S34: 28.77 | T34: 0.55 | U34: 2.41 | V34: 174.79 | W34: 0 | X34: 18 | Y34: 303784 | Z34: 239737 | AA34: 4.03 | AB34: 1.91 | AC34: 3111 | AD34: 68.27 | AE34: 28.77 | AF34: 0.55 | AG34: 2.41 | AH34: 174.79 | AI34: 0 | AJ34: 18 | AK34: 303784 | AL34: 239737
A35: Hungary | B35: Malaysia | C35: 0.43 | D35: 2008 | E35: Exports & Imports | F35: 181 | G35: 357 | H35: 5.92 | I35: 8.98 | J35: -427476 | K35: 40279 | L35: 467755 | M35: 0.43 | N35: 0.04 | O35: 1.05 | P35: 0.42 | Q35: 1725 | R35: 18.78 | S35: 79.71 | T35: 0.99 | U35: 0.52 | V35: 25.66 | W35: 0 | X35: 325 | Y35: 70304 | Z35: 394332 | AA35: 3.13 | AB35: 1.62 | AC35: 1725 | AD35: 68.35 | AE35: 30.03 | AF35: 0.99 | AG35: 0.64 | AH35: 29.16 | AI35: 0 | AJ35: 325 | AK35: 214300 | AL35: 250336
A36: Hungary | B36: Ireland | C36: 0.39 | D36: 2008 | E36: Exports & Imports | F36: 318 | G36: 442 | H36: 10.4 | I36: 11.11 | J36: 15838 | K36: 438787 | L36: 422949 | M36: 0.39 | N36: 0.41
A37: Hungary | B37: Croatia | C37: 0.36 | D37: 2008 | E37: Exports & Imports | F37: 1963 | G37: 810 | H37: 64.21 | I37: 20.37 | J37: 1314379 | K37: 1706556 | L37: 392177 | M37: 0.36 | N37: 1.58
A38: Hungary | B38: Latin America & Caribbean | C38: 0.33 | D38: 2008 | E38: Exports & Imports | F38: 643 | G38: 608 | H38: 21.03 | I38: 15.29 | J38: 188864 | K38: 546354 | L38: 357490 | M38: 0.33 | N38: 0.5 | O38: 0.99 | P38: 0.98 | Q38: 4744 | R38: 11.64 | S38: 81.13 | T38: 1.52 | U38: 5.71 | V38: 73.51 | W38: 0 | X38: 1526 | Y38: 48359 | Z38: 288621 | AA38: 4.13 | AB38: 2.43 | AC38: 3002 | AD38: 66.22 | AE38: 23.85 | AF38: 1.08 | AG38: 5.21 | AH38: 74.9 | AI38: 0 | AJ38: 1859 | AK38: 178570 | AL38: 158410
A39: Hungary | B39: Serbia, FR(Serbia/Montenegro) | C39: 0.33 | D39: 2008 | E39: Exports & Imports | F39: 2036 | G39: 791 | H39: 66.6 | I39: 19.89 | J39: 1181446 | K39: 1540510 | L39: 359064 | M39: 0.33 | N39: 1.42 | O39: 4.16 | P39: 15.49 | Q39: 3517 | R39: 65.06 | S39: 26.16 | T39: 2.1 | U39: 6.68 | V39: 174.79 | W39: 0 | X39: 2087 | Y39: 222271 | Z39: 120507 | AA39: 4.16 | AB39: 15.49 | AC39: 3517 | AD39: 65.06 | AE39: 26.16 | AF39: 2.1 | AG39: 6.68 | AH39: 174.79 | AI39: 0 | AJ39: 2087 | AK39: 222271 | AL39: 120507
A40: Hungary | B40: Middle East & North Africa | C40: 0.28 | D40: 2008 | E40: Exports & Imports | F40: 1043 | G40: 905 | H40: 34.12 | I40: 22.76 | J40: 2256108 | K40: 2561114 | L40: 305006 | M40: 0.28 | N40: 2.37 | O40: 1.26 | P40: 0.48 | Q40: 6196 | R40: 10.44 | S40: 79.86 | T40: 1.65 | U40: 8.05 | V40: 93.85 | W40: 0 | X40: 873 | Y40: 20170 | Z40: 269217 | AA40: 5.03 | AB40: 3.09 | AC40: 4229 | AD40: 66.47 | AE40: 21.73 | AF40: 1.26 | AG40: 6.79 | AH40: 93.85 | AI40: 0 | AJ40: 874 | AK40: 202556 | AL40: 86831
A41: Hungary | B41: Thailand | C41: 0.26 | D41: 2008 | E41: Exports & Imports | F41: 194 | G41: 443 | H41: 6.35 | I41: 11.14 | J41: -237183 | K41: 47419 | L41: 284602 | M41: 0.26 | N41: 0.04 | O41: 2.71 | P41: 0.88 | Q41: 2207 | R41: 36.47 | S41: 57.05 | T41: 0.86 | U41: 5.62 | V41: 85.3 | W41: 0 | X41: 5582 | Y41: 79124 | Z41: 205330 | AA41: 5.11 | AB41: 2.68 | AC41: 2207 | AD41: 71.05 | AE41: 22.34 | AF41: 0.86 | AG41: 5.75 | AH41: 85.3 | AI41: 0 | AJ41: 5582 | AK41: 204120 | AL41: 80334
A42: Hungary | B42: Philippines | C42: 0.25 | D42: 2008 | E42: Exports & Imports | F42: 98 | G42: 127 | H42: 3.21 | I42: 3.19 | J42: -263857 | K42: 12369 | L42: 276226 | M42: 0.25 | N42: 0.01 | O42: 1.12 | P42: 0.03 | Q42: 698 | R42: 17.05 | S42: 80.23 | T42: 0 | U42: 2.72 | V42: 52.91 | W42: 0 | X42: 0 | Y42: 17648 | Z42: 257489 | AA42: 3.24 | AB42: 0.38 | AC42: 698 | AD42: 70.2 | AE42: 27.08 | AF42: 0 | AG42: 2.72 | AH42: 56.41 | AI42: 0 | AJ42: 0 | AK42: 60171 | AL42: 214966
A43: Hungary | B43: Canada | C43: 0.22 | D43: 2008 | E43: Exports & Imports | F43: 424 | G43: 711 | H43: 13.87 | I43: 17.88 | J43: -20536 | K43: 216469 | L43: 237005 | M43: 0.22 | N43: 0.2 | O43: 3.29 | P43: 1.33 | Q43: 2850 | R43: 65.54 | S43: 31.37 | T43: 1.51 | U43: 1.58 | V43: 174.79 | W43: 0 | X43: 450 | Y43: 100310 | Z43: 135997 | AA43: 3.29 | AB43: 1.33 | AC43: 2850 | AD43: 65.54 | AE43: 31.37 | AF43: 1.51 | AG43: 1.58 | AH43: 174.79 | AI43: 0 | AJ43: 450 | AK43: 100310 | AL43: 135997
A44: Hungary | B44: Bosnia and Herzegovina | C44: 0.17 | D44: 2008 | E44: Exports & Imports | F44: 1117 | G44: 152 | H44: 36.54 | I44: 3.82 | J44: 389652 | K44: 579443 | L44: 189791 | M44: 0.17 | N44: 0.54 | O44: 0 | P44: 0 | Q44: 746 | R44: 0.8 | S44: 99.2 | T44: 0 | U44: 0 | V44: 2.2 | W44: 0 | X44: 0 | Y44: 8 | Z44: 188270 | AA44: 2.55 | AB44: 3.58 | AC44: 746 | AD44: 71.05 | AE44: 28.15 | AF44: 0.67 | AG44: 0.13 | AH44: 26.07 | AI44: 0 | AJ44: 28 | AK44: 162779 | AL44: 25499
A45: Hungary | B45: Belarus | C45: 0.17 | D45: 2008 | E45: Exports & Imports | F45: 514 | G45: 176 | H45: 16.81 | I45: 4.43 | J45: 17975 | K45: 202737 | L45: 184762 | M45: 0.17 | N45: 0.19 | O45: 0.68 | P45: 0.53 | Q45: 842 | R45: 8.43 | S45: 91.21 | T45: 0 | U45: 0.36 | V45: 9.8 | W45: 0 | X45: 0 | Y45: 31067 | Z45: 152929 | AA45: 2.9 | AB45: 2.75 | AC45: 842 | AD45: 70.9 | AE45: 28.74 | AF45: 0 | AG45: 0.36 | AH45: 14.1 | AI45: 0 | AJ45: 0 | AK45: 155089 | AL45: 28907
A46: Hungary | B46: Portugal | C46: 0.17 | D46: 2008 | E46: Exports & Imports | F46: 364 | G46: 383 | H46: 11.91 | I46: 9.63 | J46: 380168 | K46: 568586 | L46: 188418 | M46: 0.17 | N46: 0.53
A47: Hungary | B47: Israel | C47: 0.16 | D47: 2008 | E47: Exports & Imports | F47: 421 | G47: 645 | H47: 13.77 | I47: 16.22 | J47: 169267 | K47: 341531 | L47: 172264 | M47: 0.16 | N47: 0.32 | O47: 0.93 | P47: 0.26 | Q47: 3159 | R47: 7.22 | S47: 84.68 | T47: 2.44 | U47: 5.67 | V47: 93.85 | W47: 0 | X47: 629 | Y47: 4292 | Z47: 166589 | AA47: 4.47 | AB47: 2.84 | AC47: 3159 | AD47: 66.19 | AE47: 25.36 | AF47: 2.44 | AG47: 6.01 | AH47: 93.85 | AI47: 0 | AJ47: 629 | AK47: 99134 | AL47: 71747
A48: Hungary | B48: Mexico | C48: 0.16 | D48: 2008 | E48: Exports & Imports | F48: 314 | G48: 291 | H48: 10.27 | I48: 7.32 | J48: 146592 | K48: 320737 | L48: 174145 | M48: 0.16 | N48: 0.3 | O48: 0.03 | P48: 0 | Q48: 1387 | R48: 2.09 | S48: 95.96 | T48: 1.3 | U48: 0.65 | V48: 12.68 | W48: 0 | X48: 277 | Y48: 296 | Z48: 173570 | AA48: 2.85 | AB48: 0.72 | AC48: 1387 | AD48: 70.3 | AE48: 27.76 | AF48: 1.3 | AG48: 0.65 | AH48: 74.9 | AI48: 0 | AJ48: 277 | AK48: 52202 | AL48: 121664
A49: Hungary | B49: Turkmenistan | C49: 0.16 | D49: 2008 | E49: Exports & Imports | F49: 56 | G49: 3 | H49: 1.83 | I49: 0.08 | J49: -164130 | K49: 6518 | L49: 170648 | M49: 0.16 | N49: 0.01 | O49: 0 | P49: 0 | Q49: 28 | R49: 0 | S49: 100 | T49: 0 | U49: 0 | V49: 0 | W49: 0 | X49: 0 | Y49: 0 | Z49: 170648 | AA49: 0.77 | AB49: 0 | AC49: 28 | AD49: 53.57 | AE49: 46.43 | AF49: 0 | AG49: 0 | AH49: 4.7 | AI49: 0 | AJ49: 0 | AK49: 74 | AL49: 170574
A50: Hungary | B50: Bulgaria | C50: 0.15 | D50: 2008 | E50: Exports & Imports | F50: 1243 | G50: 444 | H50: 40.66 | I50: 11.16 | J50: 951455 | K50: 1110210 | L50: 158755 | M50: 0.15 | N50: 1.03
A51: Hungary | B51: Uzbekistan | C51: 0.15 | D51: 2008 | E51: Exports & Imports | F51: 88 | G51: 12 | H51: 2.88 | I51: 0.3 | J51: -130847 | K51: 32107 | L51: 162954 | M51: 0.15 | N51: 0.03 | O51: 2.5 | P51: 1.03 | Q51: 29 | R51: 68.97 | S51: 31.03 | T51: 0 | U51: 0 | V51: 6.5 | W51: 0 | X51: 0 | Y51: 37617 | Z51: 125304 | AA51: 3.55 | AB51: 1.5 | AC51: 29 | AD51: 68.97 | AE51: 31.03 | AF51: 0 | AG51: 0 | AH51: 8 | AI51: 0 | AJ51: 0 | AK51: 37617 | AL51: 125304
A52: Hungary | B52: Brazil | C52: 0.13 | D52: 2008 | E52: Exports & Imports | F52: 312 | G52: 274 | H52: 10.21 | I52: 6.89 | J52: -11875 | K52: 125126 | L52: 137001 | M52: 0.13 | N52: 0.12 | O52: 2.28 | P52: 1.82 | Q52: 1252 | R52: 26.6 | S52: 68.21 | T52: 2.24 | U52: 2.96 | V52: 73.51 | W52: 0 | X52: 144 | Y52: 28047 | Z52: 89878 | AA52: 4.6 | AB52: 4.01 | AC52: 1252 | AD52: 73.56 | AE52: 21.25 | AF52: 2.24 | AG52: 2.96 | AH52: 74.9 | AI52: 0 | AJ52: 144 | AK52: 96174 | AL52: 21751
A53: Hungary | B53: Greece | C53: 0.1 | D53: 2008 | E53: Exports & Imports | F53: 583 | G53: 412 | H53: 19.07 | I53: 10.36 | J53: 553287 | K53: 660243 | L53: 106956 | M53: 0.1 | N53: 0.61
A54: Hungary | B54: Kazakhstan | C54: 0.1 | D54: 2008 | E54: Exports & Imports | F54: 444 | G54: 16 | H54: 14.52 | I54: 0.4 | J54: 292175 | K54: 403286 | L54: 111111 | M54: 0.1 | N54: 0.37 | O54: 1.4 | P54: 0.66 | Q54: 44 | R54: 13.64 | S54: 86.36 | T54: 0 | U54: 0 | V54: 15.4 | W54: 0 | X54: 0 | Y54: 11718 | Z54: 99337 | AA54: 2.31 | AB54: 1.63 | AC54: 44 | AD54: 36.36 | AE54: 63.64 | AF54: 0 | AG54: 0 | AH54: 22 | AI54: 0 | AJ54: 0 | AK54: 104624 | AL54: 6431
A55: Hungary | B55: Luxembourg | C55: 0.1 | D55: 2008 | E55: Exports & Imports | F55: 146 | G55: 318 | H55: 4.78 | I55: 8 | J55: -11408 | K55: 101121 | L55: 112529 | M55: 0.1 | N55: 0.09
A56: Hungary | B56: Indonesia | C56: 0.08 | D56: 2008 | E56: Exports & Imports | F56: 162 | G56: 312 | H56: 5.3 | I56: 7.85 | J56: -75704 | K56: 14838 | L56: 90542 | M56: 0.08 | N56: 0.01 | O56: 2.31 | P56: 1.8 | Q56: 1396 | R56: 33.38 | S56: 65.69 | T56: 0.72 | U56: 0.21 | V56: 40.3 | W56: 0 | X56: 80 | Y56: 25539 | Z56: 64933 | AA56: 4.51 | AB56: 3.59 | AC56: 1396 | AD56: 77.01 | AE56: 22.06 | AF56: 0.72 | AG56: 0.21 | AH56: 57.6 | AI56: 0 | AJ56: 80 | AK56: 49426 | AL56: 41046
A57: Hungary | B57: United Arab Emirates | C57: 0.07 | D57: 2008 | E57: Exports & Imports | F57: 340 | G57: 221 | H57: 11.12 | I57: 5.56 | J57: 554039 | K57: 629689 | L57: 75650 | M57: 0.07 | N57: 0.58 | O57: 1.93 | P57: 0.6 | Q57: 1052 | R57: 22.34 | S57: 76.43 | T57: 0 | U57: 1.24 | V57: 52.4 | W57: 0 | X57: 0 | Y57: 5239 | Z57: 68255 | AA57: 4.38 | AB57: 2.27 | AC57: 1052 | AD57: 77.28 | AE57: 21.2 | AF57: 0 | AG57: 1.52 | AH57: 74.9 | AI57: 0 | AJ57: 0 | AK57: 64862 | AL57: 8632
A58: Hungary | B58: Cyprus | C58: 0.06 | D58: 2008 | E58: Exports & Imports | F58: 230 | G58: 106 | H58: 7.52 | I58: 2.67 | J58: -3057 | K58: 60295 | L58: 63352 | M58: 0.06 | N58: 0.06
A59: Hungary | B59: Lithuania | C59: 0.06 | D59: 2008 | E59: Exports & Imports | F59: 579 | G59: 185 | H59: 18.94 | I59: 4.65 | J59: 227960 | K59: 289008 | L59: 61048 | M59: 0.06 | N59: 0.27
A60: Hungary | B60: Vietnam | C60: 0.05 | D60: 2008 | E60: Exports & Imports | F60: 166 | G60: 205 | H60: 5.43 | I60: 5.15 | J60: -9846 | K60: 40594 | L60: 50440 | M60: 0.05 | N60: 0.04 | O60: 3.76 | P60: 1.48 | Q60: 1213 | R60: 48.23 | S60: 42.29 | T60: 1.65 | U60: 7.83 | V60: 45.62 | W60: 0 | X60: 25 | Y60: 9231 | Z60: 41095 | AA60: 6.2 | AB60: 3.2 | AC60: 1213 | AD60: 77.16 | AE60: 13.36 | AF60: 1.65 | AG60: 7.83 | AH60: 49.12 | AI60: 0 | AJ60: 25 | AK60: 46136 | AL60: 4190
A61: Hungary | B61: Norway | C61: 0.04 | D61: 2008 | E61: Exports & Imports | F61: 499 | G61: 278 | H61: 16.32 | I61: 6.99 | J61: 212484 | K61: 254199 | L61: 41715 | M61: 0.04 | N61: 0.23 | O61: 0.27 | P61: 0.04 | Q61: 1321 | R61: 2.95 | S61: 94.32 | T61: 1.06 | U61: 1.67 | V61: 174.79 | W61: 0 | X61: 107 | Y61: 258 | Z61: 41189 | AA61: 2.74 | AB61: 1.86 | AC61: 1321 | AD61: 68.43 | AE61: 28.84 | AF61: 1.06 | AG61: 1.67 | AH61: 174.79 | AI61: 0 | AJ61: 107 | AK61: 23931 | AL61: 17516
A62: Hungary | B62: Argentina | C62: 0.03 | D62: 2008 | E62: Exports & Imports | F62: 171 | G62: 83 | H62: 5.59 | I62: 2.09 | J62: -8621 | K62: 21100 | L62: 29721 | M62: 0.03 | N62: 0.02 | O62: 1.54 | P62: 2.94 | Q62: 568 | R62: 26.76 | S62: 51.76 | T62: 0.35 | U62: 21.13 | V62: 33.93 | W62: 0 | X62: 172 | Y62: 15430 | Z62: 14159 | AA62: 3.65 | AB62: 4.32 | AC62: 568 | AD62: 57.92 | AE62: 20.6 | AF62: 0.35 | AG62: 21.13 | AH62: 33.93 | AI62: 0 | AJ62: 172 | AK62: 17976 | AL62: 11613
A63: Hungary | B63: Sub-Saharan Africa | C63: 0.03 | D63: 2008 | E63: Exports & Imports | F63: 503 | G63: 212 | H63: 16.45 | I63: 5.33 | J63: 505292 | K63: 542174 | L63: 36882 | M63: 0.03 | N63: 0.5 | O63: 0.07 | P63: 0 | Q63: 1393 | R63: 2.44 | S63: 90.81 | T63: 1.15 | U63: 5.6 | V63: 12.68 | W63: 0 | X63: 14 | Y63: 101 | Z63: 35681 | AA63: 3.53 | AB63: 2.66 | AC63: 1080 | AD63: 67.59 | AE63: 21.48 | AF63: 1.15 | AG63: 7.32 | AH63: 74.9 | AI63: 0 | AJ63: 14 | AK63: 19135 | AL63: 16647
A64: Hungary | B64: Australia | C64: 0.02 | D64: 2008 | E64: Exports & Imports | F64: 381 | G64: 230 | H64: 12.46 | I64: 5.78 | J64: 113103 | K64: 132989 | L64: 19886 | M64: 0.02 | N64: 0.12 | O64: 2.62 | P64: 1.28 | Q64: 1215 | R64: 51.28 | S64: 37.86 | T64: 3.7 | U64: 7.16 | V64: 35.24 | W64: 0 | X64: 164 | Y64: 10314 | Z64: 7968 | AA64: 2.62 | AB64: 1.28 | AC64: 1215 | AD64: 51.28 | AE64: 37.86 | AF64: 3.7 | AG64: 7.16 | AH64: 35.24 | AI64: 0 | AJ64: 164 | AK64: 10314 | AL64: 7968
A65: Hungary | B65: Estonia | C65: 0.02 | D65: 2008 | E65: Exports & Imports | F65: 467 | G65: 163 | H65: 15.28 | I65: 4.1 | J65: 119016 | K65: 144271 | L65: 25255 | M65: 0.02 | N65: 0.13
A66: Hungary | B66: Latvia | C66: 0.02 | D66: 2008 | E66: Exports & Imports | F66: 457 | G66: 79 | H66: 14.95 | I66: 1.99 | J66: 154239 | K66: 181367 | L66: 27128 | M66: 0.02 | N66: 0.17
A67: Hungary | B67: Macao | C67: 0.02 | D67: 2008 | E67: Exports & Imports | F67: 13 | G67: 37 | H67: 0.43 | I67: 0.93 | J67: -17022 | K67: 3515 | L67: 20537 | M67: 0.02 | N67: 0 | O67: 0.73 | P67: 0.29 | Q67: 284 | R67: 13.73 | S67: 86.27 | T67: 0 | U67: 0 | V67: 9.6 | W67: 0 | X67: 0 | Y67: 9919 | Z67: 10581 | AA67: 2.56 | AB67: 1.69 | AC67: 284 | AD67: 73.94 | AE67: 26.06 | AF67: 0 | AG67: 0 | AH67: 12 | AI67: 0 | AJ67: 0 | AK67: 10892 | AL67: 9608
A68: Hungary | B68: Pakistan | C68: 0.02 | D68: 2008 | E68: Exports & Imports | F68: 115 | G68: 180 | H68: 3.76 | I68: 4.53 | J68: 65713 | K68: 86766 | L68: 21053 | M68: 0.02 | N68: 0.08 | O68: 5.17 | P68: 9.97 | Q68: 595 | R68: 55.63 | S68: 37.98 | T68: 0 | U68: 6.39 | V68: 40.85 | W68: 0 | X68: 0 | Y68: 13585 | Z68: 7309 | AA68: 7.39 | AB68: 11.4 | AC68: 595 | AD68: 81.01 | AE68: 12.61 | AF68: 0 | AG68: 6.39 | AH68: 40.85 | AI68: 0 | AJ68: 0 | AK68: 16910 | AL68: 3984
A69: Hungary | B69: South Africa | C69: 0.02 | D69: 2008 | E69: Exports & Imports | F69: 329 | G69: 147 | H69: 10.76 | I69: 3.7 | J69: 267548 | K69: 285368 | L69: 17820 | M69: 0.02 | N69: 0.26 | O69: 0.13 | P69: 0.01 | Q69: 800 | R69: 4.25 | S69: 84 | T69: 2 | U69: 9.75 | V69: 12.68 | W69: 0 | X69: 14 | Y69: 101 | Z69: 17449 | AA69: 2.68 | AB69: 1.76 | AC69: 800 | AD69: 64.63 | AE69: 23.63 | AF69: 2 | AG69: 9.75 | AH69: 29.62 | AI69: 0 | AJ69: 14 | AK69: 12984 | AL69: 4566
A70: Hungary | B70: Albania | C70: 0.01 | D70: 2008 | E70: Exports & Imports | F70: 411 | G70: 15 | H70: 13.44 | I70: 0.38 | J70: 83999 | K70: 90512 | L70: 6513 | M70: 0.01 | N70: 0.08 | O70: 0 | P70: 0 | Q70: 80 | R70: 0 | S70: 100 | T70: 0 | U70: 0 | V70: 0 | W70: 0 | X70: 0 | Y70: 0 | Z70: 6422 | AA70: 2.6 | AB70: 0.14 | AC70: 80 | AD70: 72.5 | AE70: 23.75 | AF70: 0 | AG70: 3.75 | AH70: 16 | AI70: 0 | AJ70: 0 | AK70: 250 | AL70: 6172
A71: Hungary | B71: Cote d'Ivoire | C71: 0.01 | D71: 2008 | E71: Exports & Imports | F71: 20 | G71: 3 | H71: 0.65 | I71: 0.08 | J71: -4023 | K71: 3461 | L71: 7484 | M71: 0.01 | N71: 0 | O71: 0 | P71: 0 | Q71: 9 | R71: 0 | S71: 100 | T71: 0 | U71: 0 | V71: 0 | W71: 0 | X71: 0 | Y71: 0 | Z71: 7480 | AA71: 1.99 | AB71: 0.04 | AC71: 9 | AD71: 77.78 | AE71: 22.22 | AF71: 0 | AG71: 0 | AH71: 6 | AI71: 0 | AJ71: 0 | AK71: 68 | AL71: 7412
A72: Hungary | B72: Egypt, Arab Rep. | C72: 0.01 | D72: 2008 | E72: Exports & Imports | F72: 273 | G72: 108 | H72: 8.93 | I72: 2.72 | J72: 249714 | K72: 262180 | L72: 12466 | M72: 0.01 | N72: 0.24 | O72: 1.45 | P72: 2.16 | Q72: 426 | R72: 8.22 | S72: 67.84 | T72: 0.23 | U72: 23.71 | V72: 36.89 | W72: 0 | X72: 225 | Y72: 3720 | Z72: 8500 | AA72: 6.04 | AB72: 7.76 | AC72: 426 | AD72: 53.52 | AE72: 22.07 | AF72: 0.23 | AG72: 24.18 | AH72: 74.9 | AI72: 0 | AJ72: 225 | AK72: 10711 | AL72: 1509
A73: Hungary | B73: Iceland | C73: 0.01 | D73: 2008 | E73: Exports & Imports | F73: 95 | G73: 20 | H73: 3.11 | I73: 0.5 | J73: 6844 | K73: 14232 | L73: 7388 | M73: 0.01 | N73: 0.01 | O73: 0 | P73: 0 | Q73: 95 | R73: 0 | S73: 100 | T73: 0 | U73: 0 | V73: 0 | W73: 0 | X73: 0 | Y73: 0 | Z73: 7379 | AA73: 1.16 | AB73: 0.01 | AC73: 95 | AD73: 40 | AE73: 60 | AF73: 0 | AG73: 0 | AH73: 12.5 | AI73: 0 | AJ73: 0 | AK73: 22 | AL73: 7357
A74: Hungary | B74: Jordan | C74: 0.01 | D74: 2008 | E74: Exports & Imports | F74: 145 | G74: 19 | H74: 4.74 | I74: 0.48 | J74: 185558 | K74: 192614 | L74: 7056 | M74: 0.01 | N74: 0.18 | O74: 2.72 | P74: 0.44 | Q74: 87 | R74: 6.9 | S74: 37.93 | T74: 0 | U74: 55.17 | V74: 59.1 | W74: 0 | X74: 0 | Y74: 220 | Z74: 6835 | AA74: 11.43 | AB74: 5.58 | AC74: 87 | AD74: 26.44 | AE74: 16.09 | AF74: 0 | AG74: 57.47 | AH74: 74.9 | AI74: 0 | AJ74: 0 | AK74: 6623 | AL74: 432
A75: Hungary | B75: Morocco | C75: 0.01 | D75: 2008 | E75: Exports & Imports | F75: 161 | G75: 31 | H75: 5.27 | I75: 0.78 | J75: 61950 | K75: 67629 | L75: 5679 | M75: 0.01 | N75: 0.06 | O75: 0.95 | P75: 1.08 | Q75: 170 | R75: 1.76 | S75: 86.47 | T75: 0 | U75: 11.76 | V75: 31.59 | W75: 0 | X75: 0 | Y75: 342 | Z75: 5266 | AA75: 4.15 | AB75: 5.31 | AC75: 170 | AD75: 64.71 | AE75: 23.53 | AF75: 0 | AG75: 11.76 | AH75: 36.89 | AI75: 0 | AJ75: 0 | AK75: 5493 | AL75: 115
A76: Hungary | B76: Moldova | C76: 0.01 | D76: 2008 | E76: Exports & Imports | F76: 574 | G76: 24 | H76: 18.78 | I76: 0.6 | J76: 86477 | K76: 97501 | L76: 11024 | M76: 0.01 | N76: 0.09 | O76: 2.19 | P76: 0.07 | Q76: 96 | R76: 0 | S76: 97.92 | T76: 0 | U76: 2.08 | V76: 78.9 | W76: 0 | X76: 0 | Y76: 14 | Z76: 10832 | AA76: 6 | AB76: 0.96 | AC76: 96 | AD76: 59.38 | AE76: 29.17 | AF76: 8.33 | AG76: 3.13 | AH76: 78.9 | AI76: 0 | AJ76: 58 | AK76: 1904 | AL76: 8942
A77: Hungary | B77: North Macedonia | C77: 0.01 | D77: 2008 | E77: Exports & Imports | F77: 761 | G77: 79 | H77: 24.89 | I77: 1.99 | J77: 187263 | K77: 194452 | L77: 7189 | M77: 0.01 | N77: 0.18 | O77: 0.01 | P77: 0 | Q77: 489 | R77: 1.23 | S77: 98.57 | T77: 0.2 | U77: 0 | V77: 2.2 | W77: 0 | X77: 85 | Y77: 97 | Z77: 6986 | AA77: 6.2 | AB77: 5.04 | AC77: 489 | AD77: 61.35 | AE77: 18.2 | AF77: 6.34 | AG77: 14.11 | AH77: 59.1 | AI77: 0 | AJ77: 94 | AK77: 3546 | AL77: 3537
A78: Hungary | B78: Malta | C78: 0.01 | D78: 2008 | E78: Exports & Imports | F78: 125 | G78: 29 | H78: 4.09 | I78: 0.73 | J78: -1875 | K78: 8629 | L78: 10504 | M78: 0.01 | N78: 0.01
A79: Hungary | B79: Montenegro | C79: 0.01 | D79: 2008 | E79: Exports & Imports | F79: 557 | G79: 11 | H79: 18.22 | I79: 0.28 | J79: 61345 | K79: 69950 | L79: 8605 | M79: 0.01 | N79: 0.06 | O79: 0 | P79: 0 | Q79: 80 | R79: 0 | S79: 100 | T79: 0 | U79: 0 | V79: 0 | W79: 0 | X79: 0 | Y79: 0 | Z79: 8459 | AA79: 4.13 | AB79: 0.31 | AC79: 80 | AD79: 23.75 | AE79: 66.25 | AF79: 0 | AG79: 10 | AH79: 39.69 | AI79: 0 | AJ79: 0 | AK79: 132 | AL79: 8327
A80: Hungary | B80: Tajikistan | C80: 0.01 | D80: 2008 | E80: Exports & Imports | F80: 40 | G80: 3 | H80: 1.31 | I80: 0.08 | J80: -4003 | K80: 8871 | L80: 12874 | M80: 0.01 | N80: 0.01 | O80: 3.17 | P80: 3.39 | Q80: 5 | R80: 60 | S80: 40 | T80: 0 | U80: 0 | V80: 6.5 | W80: 0 | X80: 0 | Y80: 12753 | Z80: 121 | AA80: 3.17 | AB80: 3.39 | AC80: 5 | AD80: 60 | AE80: 40 | AF80: 0 | AG80: 0 | AH80: 6.5 | AI80: 0 | AJ80: 0 | AK80: 12753 | AL80: 121
A81: Hungary | B81: Tunisia | C81: 0.01 | D81: 2008 | E81: Exports & Imports | F81: 271 | G81: 52 | H81: 8.86 | I81: 1.31 | J81: 54803 | K81: 62589 | L81: 7786 | M81: 0.01 | N81: 0.06 | O81: 0.05 | P81: 0.16 | Q81: 339 | R81: 0.59 | S81: 99.41 | T81: 0 | U81: 0 | V81: 4.2 | W81: 0 | X81: 0 | Y81: 426 | Z81: 7078 | AA81: 3.86 | AB81: 4.17 | AC81: 339 | AD81: 80.53 | AE81: 19.47 | AF81: 0 | AG81: 0 | AH81: 12 | AI81: 0 | AJ81: 0 | AK81: 5817 | AL81: 1687
A82: Hungary | B82: British Virgin Islands | C82: 0.01 | D82: 2008 | E82: Exports & Imports | F82: 27 | G82: 32 | H82: 0.88 | I82: 0.8 | J82: -3765 | K82: 1696 | L82: 5461 | M82: 0.01 | N82: 0 | O82: 0 | P82: 0 | Q82: 258 | R82: 0 | S82: 100 | T82: 0 | U82: 0 | V82: 0 | W82: 0 | X82: 0 | Y82: 0 | Z82: 4589 | AA82: 4.4 | AB82: 1.72 | AC82: 258 | AD82: 82.17 | AE82: 17.83 | AF82: 0 | AG82: 0 | AH82: 17 | AI82: 0 | AJ82: 0 | AK82: 4363 | AL82: 226
A83: Hungary | B83: Aruba | C83: 0 | D83: 2008 | E83: Exports & Imports | F83: 12 | G83: 1 | H83: 0.39 | I83: 0.03 | J83: 151 | K83: 152 | L83: 1 | M83: 0 | N83: 0
A84: Hungary | B84: Afghanistan | C84: 0 | D84: 2008 | E84: Exports & Imports | F84: 25 | G84: 3 | H84: 0.82 | I84: 0.08 | J84: 2332 | K84: 2349 | L84: 17 | M84: 0 | N84: 0 | O84: 0 | P84: 0 | Q84: 4 | R84: 0 | S84: 100 | T84: 0 | U84: 0 | V84: 0 | W84: 0 | X84: 0 | Y84: 0 | Z84: 16 | AA84: 5.19 | AB84: 5.46 | AC84: 4 | AD84: 75 | AE84: 0 | AF84: 0 | AG84: 25 | AH84: 8 | AI84: 3 | AJ84: 0 | AK84: 16 | AL84: 0
A85: Hungary | B85: Netherlands Antilles | C85: 0 | D85: 2008 | E85: Exports & Imports | F85: 25 | G85: 4 | H85: 0.82 | I85: 0.1 | J85: 398 | K85: 1001 | L85: 603 | M85: 0 | N85: 0 | O85: 0 | P85: 0 | Q85: 23 | R85: 0 | S85: 100 | T85: 0 | U85: 0 | V85: 0 | W85: 0 | X85: 0 | Y85: 0 | Z85: 602 | AA85: 4.63 | AB85: 5.95 | AC85: 23 | AD85: 100 | AE85: 0 | AF85: 0 | AG85: 0 | AH85: 6.5 | AI85: 2 | AJ85: 0 | AK85: 602 | AL85: 0
A86: Hungary | B86: Armenia | C86: 0 | D86: 2008 | E86: Exports & Imports | F86: 148 | G86: 5 | H86: 4.84 | I86: 0.13 | J86: 19720 | K86: 19778 | L86: 58 | M86: 0 | N86: 0.02 | O86: 0 | P86: 0 | Q86: 25 | R86: 0 | S86: 100 | T86: 0 | U86: 0 | V86: 0 | W86: 0 | X86: 0 | Y86: 0 | Z86: 56 | AA86: 1.18 | AB86: 0.17 | AC86: 25 | AD86: 32 | AE86: 68 | AF86: 0 | AG86: 0 | AH86: 6.5 | AI86: 0 | AJ86: 0 | AK86: 2 | AL86: 54
A87: Hungary | B87: Azerbaijan | C87: 0 | D87: 2008 | E87: Exports & Imports | F87: 167 | G87: 6 | H87: 5.46 | I87: 0.15 | J87: 85698 | K87: 85733 | L87: 35 | M87: 0 | N87: 0.08 | O87: 0.53 | P87: 0.37 | Q87: 20 | R87: 5 | S87: 95 | T87: 0 | U87: 0 | V87: 3.2 | W87: 0 | X87: 0 | Y87: 4 | Z87: 31 | AA87: 1.62 | AB87: 2.38 | AC87: 20 | AD87: 40 | AE87: 60 | AF87: 0 | AG87: 0 | AH87: 6 | AI87: 0 | AJ87: 0 | AK87: 28 | AL87: 7
A88: Hungary | B88: Bangladesh | C88: 0 | D88: 2008 | E88: Exports & Imports | F88: 36 | G88: 43 | H88: 1.18 | I88: 1.08 | J88: 2079 | K88: 4730 | L88: 2651 | M88: 0 | N88: 0 | O88: 0 | P88: 0 | Q88: 111 | R88: 0 | S88: 100 | T88: 0 | U88: 0 | V88: 0 | W88: 0 | X88: 0 | Y88: 0 | Z88: 2579 | AA88: 10.7 | AB88: 10.71 | AC88: 111 | AD88: 97.3 | AE88: 2.7 | AF88: 0 | AG88: 0 | AH88: 15 | AI88: 0 | AJ88: 0 | AK88: 2569 | AL88: 10
A89: Hungary | B89: Bahrain | C89: 0 | D89: 2008 | E89: Exports & Imports | F89: 93 | G89: 8 | H89: 3.04 | I89: 0.2 | J89: 22747 | K89: 25181 | L89: 2434 | M89: 0 | N89: 0.02 | O89: 2.2 | P89: 3.04 | Q89: 20 | R89: 35 | S89: 65 | T89: 0 | U89: 0 | V89: 8.4 | W89: 0 | X89: 0 | Y89: 2051 | Z89: 365 | AA89: 2.78 | AB89: 3.05 | AC89: 20 | AD89: 40 | AE89: 60 | AF89: 0 | AG89: 0 | AH89: 12 | AI89: 0 | AJ89: 0 | AK89: 2051 | AL89: 365
A90: Hungary | B90: Bahamas, The | C90: 0 | D90: 2008 | E90: Exports & Imports | F90: 11 | G90: 24 | H90: 0.36 | I90: 0.6 | J90: -2830 | K90: 197 | L90: 3027 | M90: 0 | N90: 0 | O90: 0 | P90: 0 | Q90: 214 | R90: 0 | S90: 100 | T90: 0 | U90: 0 | V90: 0 | W90: 0 | X90: 0 | Y90: 0 | Z90: 3024 | AA90: 3.99 | AB90: 1.01 | AC90: 214 | AD90: 84.58 | AE90: 15.42 | AF90: 0 | AG90: 0 | AH90: 14 | AI90: 0 | AJ90: 0 | AK90: 1418 | AL90: 1606
A91: Hungary | B91: Belize | C91: 0 | D91: 2008 | E91: Exports & Imports | F91: 3 | G91: 9 | H91: 0.1 | I91: 0.23 | J91: 186 | K91: 220 | L91: 34 | M91: 0 | N91: 0 | O91: 0 | P91: 0 | Q91: 98 | R91: 0 | S91: 100 | T91: 0 | U91: 0 | V91: 0 | W91: 0 | X91: 0 | Y91: 0 | Z91: 34 | AA91: 1.63 | AB91: 1.94 | AC91: 98 | AD91: 69.39 | AE91: 30.61 | AF91: 0 | AG91: 0 | AH91: 5 | AI91: 0 | AJ91: 0 | AK91: 27 | AL91: 7
A92: Hungary | B92: Bermuda | C92: 0 | D92: 2008 | E92: Exports & Imports | F92: 4 | G92: 2 | H92: 0.13 | I92: 0.05 | J92: 227 | K92: 248 | L92: 21 | M92: 0 | N92: 0 | O92: 0 | P92: 0 | Q92: 4 | R92: 0 | S92: 100 | T92: 0 | U92: 0 | V92: 0 | W92: 0 | X92: 0 | Y92: 0 | Z92: 21 | AA92: 0 | AB92: 0 | AC92: 4 | AD92: 0 | AE92: 100 | AF92: 0 | AG92: 0 | AH92: 0 | AI92: 0 | AJ92: 0 | AK92: 0 | AL92: 21
A93: Hungary | B93: Bolivia | C93: 0 | D93: 2008 | E93: Exports & Imports | F93: 54 | G93: 7 | H93: 1.77 | I93: 0.18 | J93: 2434 | K93: 2453 | L93: 19 | M93: 0 | N93: 0 | O93: 0 | P93: 0 | Q93: 31 | R93: 0 | S93: 100 | T93: 0 | U93: 0 | V93: 0 | W93: 0 | X93: 0 | Y93: 0 | Z93: 14 | AA93: 9.28 | AB93: 10.53 | AC93: 31 | AD93: 83.87 | AE93: 16.13 | AF93: 0 | AG93: 0 | AH93: 12 | AI93: 0 | AJ93: 0 | AK93: 14 | AL93: 0
A94: Hungary | B94: Barbados | C94: 0 | D94: 2008 | E94: Exports & Imports | F94: 15 | G94: 2 | H94: 0.49 | I94: 0.05 | J94: 459 | K94: 591 | L94: 132 | M94: 0 | N94: 0 | O94: 0 | P94: 0 | Q94: 103 | R94: 0 | S94: 100 | T94: 0 | U94: 0 | V94: 0 | W94: 0 | X94: 0 | Y94: 0 | Z94: 32 | AA94: 0.76 | AB94: 0.76 | AC94: 103 | AD94: 11.65 | AE94: 88.35 | AF94: 0 | AG94: 0 | AH94: 6.5 | AI94: 0 | AJ94: 0 | AK94: 32 | AL94: 0
A95: Hungary | B95: Brunei | C95: 0 | D95: 2008 | E95: Exports & Imports | F95: 8 | G95: 2 | H95: 0.26 | I95: 0.05 | J95: -80 | K95: 32 | L95: 112 | M95: 0 | N95: 0 | O95: 2.96 | P95: 0.05 | Q95: 7 | R95: 71.43 | S95: 28.57 | T95: 0 | U95: 0 | V95: 9.6 | W95: 0 | X95: 0 | Y95: 1 | Z95: 111 | AA95: 5.07 | AB95: 2.74 | AC95: 7 | AD95: 100 | AE95: 0 | AF95: 0 | AG95: 0 | AH95: 12 | AI95: 2.7 | AJ95: 0 | AK95: 112 | AL95: 0
... A108: Hungary | B108: Ethiopia(excludes Eritrea) | C108: 0 | D108: 2008 | E108: Exports & Imports | F108: 37 | G108: 4 | H108: 1.21 | I108: 0.1 | J108: 365 | K108: 1005 | L108: 640 | M108: 0 | N108: 0 | O108: 0 | P108: 0 | Q108: 6 | R108: 0 | S108: 100 | T108: 0 | U108: 0 | V108: 0 | W108: 0 | X108: 0 | Y108: 0 | Z108: 640 | AA108: 1.38 | AB108: 2.51 | AC108: 6 | AD108: 33.33 | AE108: 66.67 | AF108: 0 | AG108: 0 | AH108: 4 | AI108: 0 | AJ108: 0 | AK108: 489 | AL108: 151
A109: Hungary | B109: Falkland Island | C109: 0 | D109: 2008 | E109: Exports & Imports | G109: 1 | I109: 0.03 | L109: 70 | M109: 0 | O109: 0 | P109: 0 | Q109: 13 | R109: 0 | S109: 100 | T109: 0 | U109: 0 | V109: 0 | W109: 0 | X109: 0 | Y109: 0 | Z109: 70 | AA109: 15 | AB109: 15 | AC109: 13 | AD109: 100 | AE109: 0 | AF109: 0 | AG109: 0 | AH109: 15 | AI109: 15 | AJ109: 0 | AK109: 70 | AL109: 0
A110: Hungary | B110: Gabon | C110: 0 | D110: 2008 | E110: Exports & Imports | F110: 7 | G110: 3 | H110: 0.23 | I110: 0.08 | J110: 326 | K110: 337 | L110: 11 | M110: 0 | N110: 0 | O110: 0 | P110: 0 | Q110: 9 | R110: 0 | S110: 100 | T110: 0 | U110: 0 | V110: 0 | W110: 0 | X110: 0 | Y110: 0 | Z110: 11 | AA110: 0.41 | AB110: 0.22 | AC110: 9 | AD110: 22.22 | AE110: 77.78 | AF110: 0 | AG110: 0 | AH110: 5 | AI110: 0 | AJ110: 0 | AK110: 2 | AL110: 9
A111: Hungary | B111: Georgia | C111: 0 | D111: 2008 | E111: Exports & Imports | F111: 223 | G111: 5 | H111: 7.29 | I111: 0.13 | J111: 34938 | K111: 35042 | L111: 104 | M111: 0 | N111: 0.03 | O111: 0 | P111: 0 | Q111: 12 | R111: 0 | S111: 100 | T111: 0 | U111: 0 | V111: 0 | W111: 0 | X111: 0 | Y111: 0 | Z111: 102 | AA111: 1.18 | AB111: 1.84 | AC111: 12 | AD111: 50 | AE111: 50 | AF111: 0 | AG111: 0 | AH111: 4.7 | AI111: 0 | AJ111: 0 | AK111: 40 | AL111: 62
A112: Hungary | B112: Ghana | C112: 0 | D112: 2008 | E112: Exports & Imports | F112: 51 | G112: 6 | H112: 1.67 | I112: 0.15 | J112: 21638 | K112: 22216 | L112: 578 | M112: 0 | N112: 0.02 | O112: 0 | P112: 0 | Q112: 7 | R112: 0 | S112: 100 | T112: 0 | U112: 0 | V112: 0 | W112: 0 | X112: 0 | Y112: 0 | Z112: 577 | AA112: 1.08 | AB112: 0.02 | AC112: 7 | AD112: 42.86 | AE112: 57.14 | AF112: 0 | AG112: 0 | AH112: 3.2 | AI112: 0 | AJ112: 0 | AK112: 5 | AL112: 572
...

Sheet EUshare
A1: EU Import share
A2: 1992 | B2: =Partner1992!D4+Partner1992!D6+Partner1992!D7+Partner1992!D12+Partner1992!D13+Partner1992!D15+Partner1992!D17+Partner1992!D18+Partner1992!D23+Partner1992!D25+Partner1992!D26+Partner1992!D36+Partner1992!D43+Partner1992!D54 -> 60.53
A3: 2001 | B3: =Partner2001!C4+Partner2001!C6+Partner2001!C7+Partner2001!C9+Partner2001!C14+Partner2001!C16+Partner2001!C18+Partner2001!C19+Partner2001!C28+Partner2001!C29+Partner2001!C33+Partner2001!C34+Partner2001!C43+Partner2001!C51+Partner2001!C59 -> 57.8
A4: 2008 | B4: =Partner2008!C4+Partner2008!C7+Partner2008!C9+Partner2008!C10+Partner2008!C11+Partner2008!C16+Partner2008!C19+Partner2008!C23+Partner2008!C28+Partner2008!C29+Partner2008!C31 -> 52.89

Sheet Import_tariff_EU
A1: Selected Nomen | B1: Native Nomen | C1: Reporter | D1: Reporter Name | E1: Product | F1: Product Name | G1: Partner | H1: Partner Name | I1: Tariff Year | J1: Trade Year | K1: Trade Source | L1: DutyType | M1: Simple Average | N1: Weighted Average | O1: Standard Deviation | P1: Minimum Rate | Q1: Maximum Rate | R1: Nbr of Total Lines | S1: Nbr of DomesticPeaks | T1: Nbr of InternationalPeaks | U1: Imports Value in 1000 USD | V1: Binding Coverage
A2: HS | B2: H0 | C2: 348 | D2: Hungary | E2: Total | F2: Total Trade | H2: All countries All --- All | I2: 1991 | J2: 1991 | K2: TRN | L2: AHS | M2: 12.36 | N2: 10.07 | O2: 10.87 | P2: 0 | Q2: 500 | R2: 56759 | S2: 2460 | T2: 10758 | U2: 11115173
A3: HS | B3: H0 | C3: 348 | D3: Hungary | E3: Total | F3: Total Trade | H3: All countries All --- All | I3: 1993 | J3: 1993 | K3: CMT | L3: AHS | M3: 10.21 | N3: 8.96 | O3: 11.58 | P3: 0 | Q3: 800 | R3: 67175 | S3: 1613 | T3: 7494 | U3: 11376083
A4: HS | B4: H0 | C4: 348 | D4: Hungary | E4: Total | F4: Total Trade | H4: EU15 --- EU15 | I4: 1991 | J4: 1991 | K4: TRN | L4: AHS | M4: 12.66 | N4: 12.34 | O4: 10.62 | P4: 0 | Q4: 150 | R4: 31820 | S4: 1379 | T4: 6207 | U4: 6421851
A5: HS | B5: H0 | C5: 348 | D5: Hungary | E5: Total | F5: Total Trade | H5: EU15 --- EU15 | I5: 1993 | J5: 1993 | K5: CMT | L5: AHS | M5: 10.35 | N5: 10.56 | O5: 9.37 | P5: 0 | Q5: 150 | R5: 31692 | S5: 737 | T5: 3698 | U5: 6512201
A6: HS | B6: H0 | C6: 348 | D6: Hungary | E6: Total | F6: Total Trade | H6: EU25 --- EU25 members --- EU25 | I6: 1991 | J6: 1991 | K6: TRN | L6: AHS | M6: 12.66 | N6: 12.18 | O6: 10.63 | P6: 0 | Q6: 150 | R6: 33151 | S6: 1445 | T6: 6488 | U6: 6644519
A7: HS | B7: H0 | C7: 348 | D7: Hungary | E7: Total | F7: Total Trade | H7: EU25 --- EU25 members --- EU25 | I7: 1993 | J7: 1993 | K7: CMT | L7: AHS | M7: 10.34 | N7: 10.21 | O7: 9.18 | P7: 0 | Q7: 150 | R7: 42074 | S7: 936 | T7: 4735 | U7: 7479712
A8: HS | B8: H0 | C8: 348 | D8: Hungary | E8: Total | F8: Total Trade | H8: EU27 --- EU27 members --- EU27 | I8: 1991 | J8: 1991 | K8: TRN | L8: AHS | M8: 12.68 | N8: 12.16 | O8: 10.64 | P8: 0 | Q8: 150 | R8: 34505 | S8: 1515 | T8: 6783 | U8: 6740106
A9: HS | B9: H0 | C9: 348 | D9: Hungary | E9: Total | F9: Total Trade | H9: EU27 --- EU27 members --- EU27 | I9: 1993 | J9: 1993 | K9: CMT | L9: AHS | M9: 10.36 | N9: 10.16 | O9: 9.25 | P9: 0 | Q9: 150 | R9: 44302 | S9: 1015 | T9: 5009 | U9: 7632251
A10: HS | B10: H0 | C10: 348 | D10: Hungary | E10: Total | F10: Total Trade | H10: EU28 - EU members (excl. UK) --- EU-UK | I10: 1991 | J10: 1991 | K10: TRN | L10: AHS | M10: 12.68 | N10: 12.14 | O10: 10.65 | P10: 0 | Q10: 150 | R10: 31594 | S10: 1385 | T10: 6212 | U10: 6460277
A11: HS | B11: H0 | C11: 348 | D11: Hungary | E11: Total | F11: Total Trade | H11: EU28 - EU members (excl. UK) --- EU-UK | I11: 1993 | J11: 1993 | K11: CMT | L11: AHS | M11: 10.33 | N11: 10.14 | O11: 9.21 | P11: 0 | Q11: 150 | R11: 41134 | S11: 936 | T11: 4657 | U11: 7314124
A12: HS | B12: H1 | C12: 348 | D12: Hungary | E12: Total | F12: Total Trade | H12: All countries All --- All | I12: 1996 | J12: 1996 | K12: CMT | L12: AHS | M12: 10.32 | N12: 8.62 | O12: 14.1 | P12: 0 | Q12: 142.4 | R12: 164373 | S12: 6779 | T12: 23221 | U12: 16042644.016
A13: HS | B13: H1 | C13: 348 | D13: Hungary | E13: Total | F13: Total Trade | H13: All countries All --- All | I13: 1997 | J13: 1997 | K13: CMT | L13: AHS | M13: 5.85 | N13: 4.48 | O13: 14.68 | P13: 0 | Q13: 138.6 | R13: 179820 | S13: 8254 | T13: 18741 | U13: 20918387.016
... A31: HS | B31: H3 | C31: 348 | D31: Hungary | E31: Total | F31: Total Trade | H31: All countries All --- All | I31: 2008 | J31: 2008 | K31: CMT | L31: AHS | M31: 2.07 | N31: 0.93 | O31: 3.59 | P31: 0 | Q31: 57.6 | R31: 83800 | S31: 959 | T31: 819 | U31: 29089151

Sheet Importshares
A1: year | B1: Column1 | C1: import_share_WB
A2: 1991 | B2: =100*C2 -> 29.53255 | C2: 0.2953255
A3: 1992 | B3: =100*C3 -> 27.76957 | C3: 0.2776957
A4: 1993 | B4: =100*C4 -> 30.30694 | C4: 0.3030694
A5: 1994 | B5: =100*C5 -> 30.99572 | C5: 0.3099572
A6: 1995 | B6: =100*C6 -> 39.11579 | C6: 0.3911579
A7: 1996 | B7: =100*C7 -> 41.34083 | C7: 0.4134083
A8: 1997 | B8: =100*C8 -> 46.87738 | C8: 0.4687738
A9: 1998 | B9: =100*C9 -> 54.36175 | C9: 0.5436175
A10: 1999 | B10: =100*C10 -> 58.2079 | C10: 0.582079
A11: 2000 | B11: =100*C11 -> 70.31291 | C11: 0.7031291
A12: 2001 | B12: =100*C12 -> 65.96305 | C12: 0.6596305
A13: 2002 | B13: =100*C13 -> 59.97944 | C13: 0.5997944
... A28: 2017 | B28: =100*C28 -> 82.27032 | C28: 0.8227032

Sheet Foregin credit to NFC
A1: Links | B1: https://fred.stlouisfed.org/series/QHUNAM770A | C1: https://fred.stlouisfed.org/series/QHUPAM770A | D1: https://fred.stlouisfed.org/series/QHUPBM770A
B2: Credit_GDP_NFC | C2: Private to non-financial sector | D2: Domestic Banks to NFC | E2: Foreign ratio | F2: Relevant NFC Foreign credit | G2: Credit_GDP_NFC - no 1990 Foreign credit | H2: Corrected ratio | L2: (a known BIS data break/reclassification when Hungary transitioned to a market economy, that from what I gathered mostly affected the post 1987 Banking Act )
A3: 1970-12-31 | B3: 28.8 | C3: 35.3 | D3: 30 | E3: =(C3-D3)/C3 -> 0.15014164 | F3: 0 | G3: =B3-0 -> 28.8 | H3: =F3/G3 -> 0
A4: 1971-03-31 | B4: 29.6 | C4: 36.2 | D4: 31 | E4: =(C4-D4)/C4 -> 0.14364641 | F4: 0 | G4: =B4-0 -> 29.6 | H4: =F4/G4 -> 0
A5: 1971-06-30 | B5: 30.5 | C5: 37.3 | D5: 32 | E5: =(C5-D5)/C5 -> 0.14209115 | F5: 0 | G5: =B5-0 -> 30.5 | H5: =F5/G5 -> 0
A6: 1971-09-30 | B6: 31.4 | C6: 38.3 | D6: 33.1 | E6: =(C6-D6)/C6 -> 0.13577023 | F6: 0 | G6: =B6-0 -> 31.4 | H6: =F6/G6 -> 0
A7: 1971-12-31 | B7: 32.2 | C7: 39.3 | D7: 34 | E7: =(C7-D7)/C7 -> 0.13486005 | F7: 0 | G7: =B7-0 -> 32.2 | H7: =F7/G7 -> 0
A8: 1972-03-31 | B8: 32 | C8: 39.1 | D8: 33.8 | E8: =(C8-D8)/C8 -> 0.13554987 | F8: 0 | G8: =B8-0 -> 32 | H8: =F8/G8 -> 0
A9: 1972-06-30 | B9: 31.9 | C9: 39.2 | D9: 33.6 | E9: =(C9-D9)/C9 -> 0.14285714 | F9: 0 | G9: =B9-0 -> 31.9 | H9: =F9/G9 -> 0
A10: 1972-09-30 | B10: 31.7 | C10: 39.2 | D10: 33.4 | E10: =(C10-D10)/C10 -> 0.14795918 | F10: 0 | G10: =B10-0 -> 31.7 | H10: =F10/G10 -> 0
A11: 1972-12-31 | B11: 31.5 | C11: 39.1 | D11: 33.1 | E11: =(C11-D11)/C11 -> 0.15345269 | F11: 0 | G11: =B11-0 -> 31.5 | H11: =F11/G11 -> 0
A12: 1973-03-31 | B12: 31.6 | C12: 39.2 | D12: 32.9 | E12: =(C12-D12)/C12 -> 0.16071429 | F12: 0 | G12: =B12-0 -> 31.6 | H12: =F12/G12 -> 0
A13: 1973-06-30 | B13: 31.5 | C13: 39.3 | D13: 32.5 | E13: =(C13-D13)/C13 -> 0.17302799 | F13: 0 | G13: =B13-0 -> 31.5 | H13: =F13/G13 -> 0
A14: 1973-09-30 | B14: 31.5 | C14: 39.4 | D14: 32.1 | E14: =(C14-D14)/C14 -> 0.18527919 | F14: 0 | G14: =B14-0 -> 31.5 | H14: =F14/G14 -> 0
... A67: 1986-12-31 | B67: 46.6 | C67: 66.6 | D67: 47.7 | E67: =(C67-D67)/C67 -> 0.28378378 | F67: 0 | G67: =B67-0 -> 46.6 | H67: =F67/G67 -> 0
A68: 1987-03-31 | B68: 47.1 | C68: 67.2 | D68: 48.1 | E68: =(C68-D68)/C68 -> 0.28422619 | F68: =B68*E68-$E$67*$B$67 -> 0.16272925 | G68: =B68-$E$67*$B$67 -> 33.875676 | H68: =F68/G68 -> 0.0048037196
A69: 1987-06-30 | B69: 46.8 | C69: 67.2 | D69: 48 | E69: =(C69-D69)/C69 -> 0.28571429 | F69: =B69*E69-$E$67*$B$67 -> 0.14710425 | G69: =B69-$E$67*$B$67 -> 33.575676 | H69: =F69/G69 -> 0.0043812744
A70: 1987-09-30 | B70: 46.5 | C70: 67 | D70: 47.9 | E70: =(C70-D70)/C70 -> 0.28507463 | F70: =B70*E70-$E$67*$B$67 -> 0.031645825 | G70: =B70-$E$67*$B$67 -> 33.275676 | H70: =F70/G70 -> 0.00095101976
A71: 1987-12-31 | B71: 46.8 | C71: 67.4 | D71: 48 | E71: =(C71-D71)/C71 -> 0.28783383 | F71: =B71*E71-$E$67*$B$67 -> 0.24629882 | G71: =B71-$E$67*$B$67 -> 33.575676 | H71: =F71/G71 -> 0.0073356326
A72: 1988-03-31 | B72: 45.9 | C72: 66.3 | D72: 46.4 | E72: =(C72-D72)/C72 -> 0.30015083 | F72: =B72*E72-$E$67*$B$67 -> 0.55259875 | G72: =B72-$E$67*$B$67 -> 32.675676 | H72: =F72/G72 -> 0.016911624
A73: 1988-06-30 | B73: 45.1 | C73: 65.4 | D73: 45.7 | E73: =(C73-D73)/C73 -> 0.30122324 | F73: =B73*E73-$E$67*$B$67 -> 0.36084387 | G73: =B73-$E$67*$B$67 -> 31.875676 | H73: =F73/G73 -> 0.011320352
A74: 1988-09-30 | B74: 44.7 | C74: 65.1 | D74: 45.3 | E74: =(C74-D74)/C74 -> 0.30414747 | F74: =B74*E74-$E$67*$B$67 -> 0.37106738 | G74: =B74-$E$67*$B$67 -> 31.475676 | H74: =F74/G74 -> 0.01178902
A75: 1988-12-31 | B75: 44.7 | C75: 64.7 | D75: 44.6 | E75: =(C75-D75)/C75 -> 0.31066461 | F75: =B75*E75-$E$67*$B$67 -> 0.66238356 | G75: =B75-$E$67*$B$67 -> 31.475676 | H75: =F75/G75 -> 0.0210443
A76: 1989-03-31 | B76: 46.3 | C76: 66 | D76: 46 | E76: =(C76-D76)/C76 -> 0.3030303 | F76: =B76*E76-$E$67*$B$67 -> 0.80597871 | G76: =B76-$E$67*$B$67 -> 33.075676 | H76: =F76/G76 -> 0.024367717
A77: 1989-06-30 | B77: 46.1 | C77: 65.8 | D77: 46 | E77: =(C77-D77)/C77 -> 0.30091185 | F77: =B77*E77-$E$67*$B$67 -> 0.64771215 | G77: =B77-$E$67*$B$67 -> 32.875676 | H77: =F77/G77 -> 0.019701866
A78: 1989-09-30 | B78: 47 | C78: 66.6 | D78: 47.3 | E78: =(C78-D78)/C78 -> 0.28978979 | F78: =B78*E78-$E$67*$B$67 -> 0.3957958 | G78: =B78-$E$67*$B$67 -> 33.775676 | H78: =F78/G78 -> 0.011718368
A79: 1989-12-31 | B79: 43 | C79: 61.1 | D79: 42.6 | E79: =(C79-D79)/C79 -> 0.30278232 | F79: =B79*E79-$E$67*$B$67 -> -0.20468439 | G79: =B79-$E$67*$B$67 -> 29.775676 | H79: =F79/G79 -> -0.0068742148
... A152: 2008-03-31 | B152: 78.6 | C152: 110.8 | D152: 53.8 | E152: =(C152-D152)/C152 -> 0.51444043 | F152: =B152*E152-$E$67*$B$67 -> 27.210694 | G152: =B152-$E$67*$B$67 -> 65.375676 | H152: =F152/G152 -> 0.41622046
A153: 2008-06-30 | B153: 74.5 | C153: 105.4 | D153: 51.2 | E153: =(C153-D153)/C153 -> 0.5142315 | F153: =B153*E153-$E$67*$B$67 -> 25.085922 | G153: =B153-$E$67*$B$67 -> 61.275676 | H153: =F153/G153 -> 0.40939446 | I153: This is the quarter before the crisis
A154: 2008-09-30 | B154: 77.8 | C154: 110.8 | D154: 54.3 | E154: =(C154-D154)/C154 -> 0.5099278 | F154: =B154*E154-$E$67*$B$67 -> 26.448058 | G154: =B154-$E$67*$B$67 -> 64.575676 | H154: =F154/G154 -> 0.40956689
A155: 2008-12-31 | B155: 81 | C155: 117.6 | D155: 58.1 | E155: =(C155-D155)/C155 -> 0.50595238 | F155: =B155*E155-$E$67*$B$67 -> 27.757819 | G155: =B155-$E$67*$B$67 -> 67.775676 | H155: =F155/G155 -> 0.40955429
A156: 2009-03-31 | B156: 94.9 | C156: 135.6 | D156: 64.4 | E156: =(C156-D156)/C156 -> 0.52507375 | F156: =B156*E156-$E$67*$B$67 -> 36.605174 | G156: =B156-$E$67*$B$67 -> 81.675676 | H156: =F156/G156 -> 0.44817718
A157: 2009-06-30 | B157: 88.7 | C157: 126.3 | D157: 59.5 | E157: =(C157-D157)/C157 -> 0.52889945 | F157: =B157*E157-$E$67*$B$67 -> 33.689057 | G157: =B157-$E$67*$B$67 -> 75.475676 | H157: =F157/G157 -> 0.44635647
A158: 2009-09-30 | B158: 87.5 | C158: 125.2 | D158: 59.3 | E158: =(C158-D158)/C158 -> 0.52635783 | F158: =B158*E158-$E$67*$B$67 -> 32.831986 | G158: =B158-$E$67*$B$67 -> 74.275676 | H158: =F158/G158 -> 0.44202877
A159: 2009-12-31 | B159: 91.5 | C159: 129.4 | D159: 58.9 | E159: =(C159-D159)/C159 -> 0.54482226 | F159: =B159*E159-$E$67*$B$67 -> 36.626912 | G159: =B159-$E$67*$B$67 -> 78.275676 | H159: =F159/G159 -> 0.46792202
A160: 2010-03-31 | B160: 90.7 | C160: 128.7 | D160: 58.5 | E160: =(C160-D160)/C160 -> 0.54545455 | F160: =B160*E160-$E$67*$B$67 -> 36.248403 | G160: =B160-$E$67*$B$67 -> 77.475676 | H160: =F160/G160 -> 0.46786817
A161: 2010-06-30 | B161: 94.2 | C161: 135.4 | D161: 61.8 | E161: =(C161-D161)/C161 -> 0.54357459 | F161: =B161*E161-$E$67*$B$67 -> 37.980402 | G161: =B161-$E$67*$B$67 -> 80.975676 | H161: =F161/G161 -> 0.46903471
A162: 2010-09-30 | B162: 88.4 | C162: 127.6 | D162: 59.3 | E162: =(C162-D162)/C162 -> 0.53526646 | F162: =B162*E162-$E$67*$B$67 -> 34.093231 | G162: =B162-$E$67*$B$67 -> 75.175676 | H162: =F162/G162 -> 0.45351412
A163: 2010-12-31 | B163: 86.5 | C163: 126.3 | D163: 59.4 | E163: =(C163-D163)/C163 -> 0.52969121 | F163: =B163*E163-$E$67*$B$67 -> 32.593965 | G163: =B163-$E$67*$B$67 -> 73.275676 | H163: =F163/G163 -> 0.4448129
A164: 2011-03-31 | B164: 83 | C164: 119.8 | D164: 55.5 | E164: =(C164-D164)/C164 -> 0.53672788 | F164: =B164*E164-$E$67*$B$67 -> 31.32409 | G164: =B164-$E$67*$B$67 -> 69.775676 | H164: =F164/G164 -> 0.44892564
A165: 2011-06-30 | B165: 82.6 | C165: 120.3 | D165: 55.9 | E165: =(C165-D165)/C165 -> 0.53532835 | F165: =B165*E165-$E$67*$B$67 -> 30.993797 | G165: =B165-$E$67*$B$67 -> 69.375676 | H165: =F165/G165 -> 0.44675308
... A218: 2024-09-30 | B218: 73.5 | C218: 90.5 | D218: 31.2 | E218: =(C218-D218)/C218 -> 0.65524862 | F218: =B218*E218-$E$67*$B$67 -> 34.936449 | G218: =B218-$E$67*$B$67 -> 60.275676 | H218: =F218/G218 -> 0.57961107
D219: 31.5
D220: 30.6
D221: 31
D222: 31.1

Sheet Real exchange rate
C1: Hungary REER | E1: Renormalized | G1: Real Broad Effective Exchange Rate for Hungary (RBHUBIS)
B2: 34335 | C2: 85.3 | E2: =C2/$C$89 -> 0.97352203
B3: 34366 | C3: 84.33 | E3: =C3/$C$89 -> 0.9624515
B4: 34394 | C4: 83.69 | E4: =C4/$C$89 -> 0.95514723
B5: 34425 | C5: 84.46 | E5: =C5/$C$89 -> 0.96393517
B6: 34455 | C6: 84.32 | E6: =C6/$C$89 -> 0.96233737
B7: 34486 | C7: 83.67 | E7: =C7/$C$89 -> 0.95491897
B8: 34516 | C8: 83.92 | E8: =C8/$C$89 -> 0.9577722
B9: 34547 | C9: 79.55 | E9: =C9/$C$89 -> 0.90789774
B10: 34578 | C10: 79.94 | E10: =C10/$C$89 -> 0.91234878
B11: 34608 | C11: 81.01 | E11: =C11/$C$89 -> 0.9245606
B12: 34639 | C12: 81.62 | E12: =C12/$C$89 -> 0.93152248
B13: 34669 | C13: 82.05 | E13: =C13/$C$89 -> 0.93643004
... B377: 45748 | C377: 108.23 | E377: =C377/$C$89 -> 1.2352203

Sheet Hungary Macro-facts
B3: GDP | C3: German GDP | D3: Hungary Savings rate | E3: Domestic saving rate | F3: EU GDP PPP per capita
A4: 1990 | B4: 9133.1414 | F4: 14969.244 | K4: German growth from 1991 | O4: Hungary Growth from 1991 to 2008
A5: 1991 | B5: 8319.6312 | C5: 21058.077 | D5: 19.231289 | E5: 20.09358 | F5: 15561.193 | K5: =C22/C5-1 -> 0.82559591 | O5: =B22/B5 - 1 -> 1.4906756
A6: 1992 | B6: 8251.7195 | C6: 21806.21 | D6: 15.97877 | E6: 16.444505 | F6: 15975.576 | O6: Hungary Growth from 1991 to 2001
A7: 1993 | B7: 8408.2302 | C7: 21940.162 | D7: 11.878287 | E7: 12.419275 | F7: 16202.42 | O7: =B15/B5 - 1 -> 0.58803038
A8: 1994 | B8: 8852.9869 | C8: 22886.768 | D8: 15.696838 | E8: 16.354209 | F8: 16950.265 | H8: GDP per capita comparisons | M8: Savings rate from peak to trough
A9: 1995 | B9: 9186.0376 | C9: 23614.958 | D9: 19.334844 | E9: 23.138387 | F9: 17754.594 | I9: relative to Gerrmany | J9: relative to EU
A10: 1996 | B10: 9349.0138 | C10: 24160.067 | D10: 20.751594 | E10: 25.282405 | F10: 18349.809 | H10: 1991 | I10: =B5/C5 -> 0.3950803 | J10: =B5/F5 -> 0.53463969 | M10: 12% to 27%
A11: 1997 | B11: 9823.0258 | C11: 24643.683 | D11: 21.503298 | E11: 27.243836 | F11: 19070.095 | H11: 2001 | I11: =B15/C15 -> 0.46070855 | J11: =B15/F15 -> 0.56918649
A12: 1998 | B12: 10398.029 | C12: 25444.151 | D12: 21.345411 | E12: 27.145834 | F12: 19968.036 | H12: 2008 | I12: =B22/C22 -> 0.53901132 | J12: =B22/F22 -> 0.6351337
A13: 1999 | B13: 10873.248 | C13: 26517.934 | D13: 18.709648 | E13: 24.425674 | F13: 20767.773
A14: 2000 | B14: 11854.683 | C14: 27467.782 | D14: 19.251435 | E14: 24.374079 | F14: 22106.381
A15: 2001 | B15: 13211.827 | C15: 28677.191 | D15: 19.773596 | E15: 24.944788 | F15: 23211.772
A16: 2002 | B16: 14526.388 | C16: 29513.682 | D16: 18.543711 | E16: 23.557257 | F16: 24229.643 | K16: Wages Hungary | N16: Normalized
A17: 2003 | B17: 15479.101 | C17: 30305.258 | D17: 15.785717 | E17: 20.67199 | F17: 24762.903 | K17: 2001 | L17: 38.358 | N17: 100
A18: 2004 | B18: 16269.309 | C18: 31757.418 | D18: 16.696465 | E18: 23.063176 | F18: 25929.074 | K18: 2008 | L18: 69.574 | N18: =L18/L17 -> 1.8138068
A19: 2005 | B19: 17108.341 | C19: 32313.737 | D19: 16.57385 | E19: 23.188935 | F19: 26906.315
A20: 2006 | B20: 18383.632 | C20: 34748.754 | D20: 18.081168 | E20: 24.780828 | F20: 29244.406
A21: 2007 | B21: 19098.626 | C21: 36915.325 | D21: 16.764686 | E21: 24.963082 | F21: 31162.91 | K21: Adjusted for inflation | N21: =N18/(1+Inflation!C42/100)/(1+Inflation!C43/100)/(1+Inflation!C44/100)/(1+Inflation!C45/100)/(1+Inflation!C46/100)/(1+Inflation!C47/100)/(1+Inflation!C48/100)/(1+Inflation!C49/100) -> 1.4380517
A22: 2008 | B22: 20721.502 | C22: 38443.539 | D22: 17.773422 | E22: 25.101365 | F22: 32625.418
A23: 2009 | B23: 20722.065 | C23: 37554.443 | D23: 19.794322 | E23: 24.507258 | F23: 31983.937
A24: 2010 | B24: 21738.897 | C24: 39730.49 | D24: 20.785447 | E24: 25.934014 | F24: 33055.686
A25: 2011 | B25: 23029.447 | C25: 43398.344 | D25: 21.00328 | E25: 26.516162 | F25: 34733.959
A26: 2012 | B26: 23267.448 | C26: 44229.394 | D26: 21.132868 | E26: 26.270876 | F26: 35181.63
A27: 2013 | B27: 24547.981 | C27: 45889.017 | D27: 24.55524 | E27: 28.095385 | F27: 36304.696
A28: 2014 | B28: 25691.527 | C28: 47938.797 | D28: 24.623878 | E28: 29.907845 | F28: 37327.194
A29: 2015 | B29: 26806.045 | C29: 48558.443 | D29: 25.391992 | E29: 31.244766 | F29: 38512.787
A30: 2016 | B30: 27941.927 | C30: 51569.902 | D30: 25.773197 | E30: 29.954111 | F30: 40844.429
A31: 2017 | B31: 29496.164 | C31: 54110.254 | D31: 24.722459 | E31: 29.713862 | F31: 42966.669
A32: 2018 | B32: 31908.863 | C32: 56273.041 | D32: 26.79269 | E32: 31.059315 | F32: 44965.823
A33: 2019 | B33: 35152.604 | C33: 59270.728 | D33: 27.472152 | E33: 30.701075 | F33: 48546.645
... A37: 2023 | B37: 45021.301 | C37: 69205.883 | D37: 25.777703 | E37: 30.457844 | F37: 59044.973
A38: 2024

Sheet Hungary Imports
A1: Import tariff revenue | D1: Import value | G1: current LCU | K1: Implied tariff rate | N1: Summarized in https://www.ksh.hu/statszemle_archive/1997/1997_01/1997_01_045.pdf
N2: Can even go back to 1988, this one is until 1995, table 3
A3: 1990 | B3: 52400000000 | N3: Slight differences relative to the article because these are the official numbers from a website that has been made unavailable since then
A4: 1991 | B4: 62800000000 | E4: 768628466000 | K4: =B4/E4 -> 0.081703974
A5: 1992 | B5: 100200000000 | E5: 851291234000 | K5: =B5/E5 -> 0.11770355
A6: 1993 | B6: 128200000000 | E6: 1120277037000 | K6: =B6/E6 -> 0.11443598
A7: 1994 | B7: 150500000000 | E7: 1409401974000 | K7: =B7/E7 -> 0.10678288
A8: 1995 | B8: 249431000000 | E8: 2287681000000 | K8: =B8/E8 -> 0.10903225
A9: 1996 | B9: 248709000000 | E9: 2949305000000 | K9: =B9/E9 -> 0.084328003
A10: 1997 | B10: 161300000000 | E10: 4147234000000 | K10: =B10/E10 -> 0.038893393
A11: 1998 | B11: 131593000000 | E11: 5691306000000 | K11: =B11/E11 -> 0.023121758
A12: 1999 | B12: 141082000000 | E12: 6794246000000 | K12: =B12/E12 -> 0.020764924
A13: 2000 | B13: 137731000000 | E13: 9399947000000 | K13: =B13/E13 -> 0.014652317
A14: 2001 | B14: 125013000000 | E14: 10188973000000 | K14: =B14/E14 -> 0.012269441
A15: 2002 | B15: 129341000000 | E15: 10492243000000 | K15: =B15/E15 -> 0.012327297
A16: 2003 | B16: 132638000000 | E16: 11532525000000 | K16: =B16/E16 -> 0.011501211

Sheet Hungary TFP
B1: TFP | C1: TFP new base
A2: 1991 | B2: 0.7899068 | C2: =B2/$B$2 -> 1 | H2: Current price, from FRED
A3: 1992 | B3: 0.81926131 | C3: =B3/$B$2 -> 1.037162
A4: 1993 | B4: 0.84526825 | C4: =B4/$B$2 -> 1.0700861
A5: 1994 | B5: 0.84284204 | C5: =B5/$B$2 -> 1.0670145
A6: 1995 | B6: 0.85724908 | C6: =B6/$B$2 -> 1.0852535
A7: 1996 | B7: 0.85105383 | C7: =B7/$B$2 -> 1.0774104
A8: 1997 | B8: 0.85897702 | C8: =B8/$B$2 -> 1.087441
A9: 1998 | B9: 0.87395144 | C9: =B9/$B$2 -> 1.1063982
A10: 1999 | B10: 0.86976105 | C10: =B10/$B$2 -> 1.1010933
A11: 2000 | B11: 0.89250225 | C11: =B11/$B$2 -> 1.129883
A12: 2001 | B12: 0.9183045 | C12: =B12/$B$2 -> 1.1625479
A13: 2002 | B13: 0.94671416 | C13: =B13/$B$2 -> 1.1985138
A14: 2003 | B14: 0.96270871 | C14: =B14/$B$2 -> 1.2187624
... A19: 2008 | B19: 1.0457413 | C19: =B19/$B$2 -> 1.3238794
A20: 2009 | B20: 0.98531854
A21: 2010 | B21: 0.98756135
A22: 2011 | B22: 1.0024757
A23: 2012 | B23: 0.98101777
A24: 2013 | B24: 0.98400229
A25: 2014 | B25: 0.98199743
A26: 2015 | B26: 0.99385798
A27: 2016 | B27: 0.98001379
A28: 2017 | B28: 1
A29: 2018 | B29: 1.0274681
A30: 2019 | B30: 1.0431733
A31: 2020
A32: 2021
A33: 2022
A34: 2023
A35: 2024

Sheet Hungary Consumption
B1: Hungary Cons | D1: 1991 base
A2: 1991 | B2: 0.7899068 | D2: =B2/$B$2 -> 1 | F2: National Accounts: GDP by Expenditure: Current Prices: Private Final Consumption Expenditure for Hungary (HUNPFCEADSMEI)
A3: 1992 | B3: 0.81926131 | D3: =B3/$B$2 -> 1.037162
A4: 1993 | B4: 0.84526825 | D4: =B4/$B$2 -> 1.0700861
A5: 1994 | B5: 0.84284204 | D5: =B5/$B$2 -> 1.0670145
A6: 1995 | B6: 0.85724908 | D6: =B6/$B$2 -> 1.0852535
A7: 1996 | B7: 0.85105383 | D7: =B7/$B$2 -> 1.0774104
A8: 1997 | B8: 0.85897702 | D8: =B8/$B$2 -> 1.087441
A9: 1998 | B9: 0.87395144 | D9: =B9/$B$2 -> 1.1063982
A10: 1999 | B10: 0.86976105 | D10: =B10/$B$2 -> 1.1010933
A11: 2000 | B11: 0.89250225 | D11: =B11/$B$2 -> 1.129883
A12: 2001 | B12: 0.9183045 | D12: =B12/$B$2 -> 1.1625479
A13: 2002 | B13: 0.94671416 | D13: =B13/$B$2 -> 1.1985138
A14: 2003 | B14: 0.96270871 | D14: =B14/$B$2 -> 1.2187624
... A30: 2019 | B30: 1.0431733 | D30: =B30/$B$2 -> 1.3206283

Sheet Hungary Capital
B1: Capital | C1: with 1991
A2: 1970 | B2: 264960.91 | C2: =B2/$B$23 -> 0.36339812 | K2: Capital Stock at Constant National Prices for Hungary (RKNANPHUA666NRUG)
A3: 1971 | B3: 292100.53 | C3: =B3/$B$23 -> 0.40062055
A4: 1972 | B4: 316554.16 | C4: =B4/$B$23 -> 0.43415909
A5: 1973 | B5: 340340.59 | C5: =B5/$B$23 -> 0.46678257
A6: 1974 | B6: 366926.19 | C6: =B6/$B$23 -> 0.50324514
A7: 1975 | B7: 396781.62 | C7: =B7/$B$23 -> 0.54419235
A8: 1976 | B8: 424577.03 | C8: =B8/$B$23 -> 0.58231419
A9: 1977 | B9: 456782.81 | C9: =B9/$B$23 -> 0.62648493
A10: 1978 | B10: 489812.94 | C10: =B10/$B$23 -> 0.67178628
A11: 1979 | B11: 521105.78 | C11: =B11/$B$23 -> 0.71470491
A12: 1980 | B12: 547018.12 | C12: =B12/$B$23 -> 0.75024411
A13: 1981 | B13: 569271.12 | C13: =B13/$B$23 -> 0.78076445
A14: 1982 | B14: 589707.94 | C14: =B14/$B$23 -> 0.80879387
... A51: 2019 | B51: 1367535.8 | C51: =B51/$B$23 -> 1.8755972

Sheet Lending rate raw
A1: Column1 | B1: Column2 | C1: Column3 | D1: Column4 | E1: Column5 | F1: Column6 | G1: Column7 | H1: Column8 | I1: Column9 | J1: Column10 | K1: Column11 | L1: Column12 | M1: Column13 | N1: Column14 | O1: Column15 | P1: Column16 | Q1: Column17 | R1: Column18 | S1: Column19 | T1: Column20 | U1: Column21 | V1: Column22 | W1: Column23 | X1: Column24 | Y1: Column25 | Z1: Column26 | AA1: Column27 | AB1: Column28 | AC1: Column29 | AD1: Column30 | AE1: Column31 | AF1: Column32 | AG1: Column33 | AH1: Column34 | AI1: Column35 | AJ1: Column36 | AK1: Column37 | AL1: Column38 | AM1: Column39 | AN1: Column40 | AO1: Column41 | AP1: Column42 | AQ1: Column43 | AR1: Column44 | AS1: Column45 | AT1: Column46 | AU1: Column47 | AV1: Column48 | AW1: Column49 | AX1: Column50 | AY1: Column51 | AZ1: Column52 | BA1: Column53 | BB1: Column54 | BC1: Column55 | BD1: Column56 | BE1: Column57 | BF1: Column58 | BG1: Column59 | BH1: Column60 | BI1: Column61 | BJ1: Column62 | BK1: Column63 | BL1: Column64 | BM1: Column65 | BN1: Column66 | BO1: Column67 | BP1: Column68 | BQ1: Column69 | BR1: Column70
A2: Data Source | B2: World Development Indicators
A4: Last Updated Date | B4: 2025-04-15
A6: Country Name | B6: Country Code | C6: Indicator Name | D6: Indicator Code | E6: 1960 | F6: 1961 | G6: 1962 | H6: 1963 | I6: 1964 | J6: 1965 | K6: 1966 | L6: 1967 | M6: 1968 | N6: 1969 | O6: 1970 | P6: 1971 | Q6: 1972 | R6: 1973 | S6: 1974 | T6: 1975 | U6: 1976 | V6: 1977 | W6: 1978 | X6: 1979 | Y6: 1980 | Z6: 1981 | AA6: 1982 | AB6: 1983 | AC6: 1984 | AD6: 1985 | AE6: 1986 | AF6: 1987 | AG6: 1988 | AH6: 1989 | AI6: 1990 | AJ6: 1991 | AK6: 1992 | AL6: 1993 | AM6: 1994 | AN6: 1995 | AO6: 1996 | AP6: 1997 | AQ6: 1998 | AR6: 1999 | AS6: 2000 | AT6: 2001 | AU6: 2002 | AV6: 2003 | AW6: 2004 | AX6: 2005 | AY6: 2006 | AZ6: 2007 | BA6: 2008 | BB6: 2009 | BC6: 2010 | BD6: 2011 | BE6: 2012 | BF6: 2013 | BG6: 2014 | BH6: 2015 | BI6: 2016 | BJ6: 2017 | BK6: 2018 | BL6: 2019 | BM6: 2020 | BN6: 2021 | BO6: 2022 | BP6: 2023 | BQ6: 2024
A7: Aruba | B7: ABW | C7: Lending interest rate (%) | D7: FR.INR.LEND | AE7: 11 | AF7: 10.3 | AG7: 10.2416666666667 | AH7: 10.475 | AI7: 10.6 | AJ7: 10.675 | AK7: 10.6 | AL7: 10.6 | AM7: 10.6 | AN7: 10.6 | AO7: 10.375 | AP7: 10.25 | AQ7: 11.0416666666667 | AR7: 13.1416666666667 | AS7: 12.0666666666667 | AT7: 12.6 | AU7: 11.3 | AV7: 10.7 | AW7: 9.6 | AX7: 11 | AY7: 9.5 | AZ7: 10.4 | BA7: 10.5 | BB7: 10.7 | BC7: 10.3 | BD7: 9 | BE7: 8.4 | BF7: 8.5 | BG7: 7.3 | BH7: 7 | BI7: 6.9 | BJ7: 6.3 | BK7: 6 | BL7: 5.7 | BM7: 6.8 | BN7: 6.4 | BO7: 6.1 | BP7: 5.8
A8: Africa Eastern and Southern | B8: AFE | C8: Lending interest rate (%) | D8: FR.INR.LEND
A9: Afghanistan | B9: AFG | C9: Lending interest rate (%) | D9: FR.INR.LEND | AY9: 17.97 | AZ9: 18.135 | BA9: 14.9175 | BB9: 15 | BC9: 15.6122222222222 | BD9: 15.1458333333333 | BE9: 15 | BF9: 15.0791666666667 | BG9: 15 | BH9: 15 | BI9: 15 | BJ9: 14.8366666666667
A10: Africa Western and Central | B10: AFW | C10: Lending interest rate (%) | D10: FR.INR.LEND
A11: Angola | B11: AGO | C11: Lending interest rate (%) | D11: FR.INR.LEND | AN11: 206.25 | AO11: 217.875 | AP11: 37.75 | AQ11: 45 | AR11: 80.2966666666667 | AS11: 103.160174166667 | AT11: 95.9665608333333 | AU11: 97.3358333333333 | AV11: 96.115 | AW11: 82.3341666666667 | AX11: 67.7181307369684 | AY11: 19.5108144527911 | AZ11: 17.6988356005955 | BA11: 12.533605759663 | BB11: 15.682074235437 | BC11: 22.5435720221269 | BD11: 18.7572405365757 | BE11: 16.6564013212232 | BF11: 15.8086382955866 | BG11: 16.3822709411366 | BH11: 16.8818623998822 | BI11: 15.7805039391116 | BJ11: 15.8061003813255 | BK11: 20.6770040277157 | BL11: 19.295367205655 | BM11: 19.6558949254322 | BN11: 19.4031546297083 | BO11: 20.1172113762759 | BP11: 16.9208615225951 | BQ11: 19.3991553172159
A12: Albania | B12: ALB | C12: Lending interest rate (%) | D12: FR.INR.LEND | AE12: 1 | AF12: 1 | AG12: 1 | AH12: 1 | AI12: 1 | AJ12: 1 | AK12: 20.5833333333333 | AL12: 29.5833333333333 | AM12: 23.6666666666667 | AN12: 19.65 | AO12: 23.9583333333333 | AP12: 32.7083333333333 | AR12: 21.615 | AS12: 22.1025 | AT12: 19.6541666666667 | AU12: 15.3041666666667 | AV12: 14.2708333333333 | AW12: 11.7615218344487 | AX12: 13.075 | AY12: 12.9399428618515 | AZ12: 14.0996227871662 | BA12: 13.0196427128802 | BB12: 12.6609351537225 | BC12: 12.8223298853561 | BD12: 12.4320985987679 | BE12: 10.8803465425902 | BF12: 9.8266043443155 | BG12: 7.9725 | BH12: 7.8775 | BI12: 6.73416666666667 | BJ12: 6.22 | BK12: 5.9325 | BL12: 6.27583333333333 | BM12: 6.12083333333333 | BN12: 6.02166666666667 | BO12: 6.50666666666667 | BP12: 6.35166666666667 | BQ12: 6.44333333333333
A13: Andorra | B13: AND | C13: Lending interest rate (%) | D13: FR.INR.LEND
A14: Arab World | B14: ARB | C14: Lending interest rate (%) | D14: FR.INR.LEND
A15: United Arab Emirates | B15: ARE | C15: Lending interest rate (%) | D15: FR.INR.LEND
A16: Argentina | B16: ARG | C16: Lending interest rate (%) | D16: FR.INR.LEND | BC16: 10.5575 | BD16: 14.0875 | BE16: 14.0608333333333 | BF16: 17.1491666666667 | BG16: 24.0091666666667 | BH16: 24.9158333333333 | BI16: 31.2325 | BJ16: 26.5808333333333 | BK16: 48.5166666666667 | BL16: 67.2541666666667 | BM16: 29.3875 | BN16: 35.5583333333333 | BO16: 52.3991666666667 | BP16: 95.8941666666667 | BQ16: 61.7066666666667
A17: Armenia | B17: ARM | C17: Lending interest rate (%) | D17: FR.INR.LEND | AN17: 96.1 | AO17: 66.3583333333333 | AP17: 54.2275 | AQ17: 48.485 | AR17: 38.8483333333333 | AS17: 31.5660003908333 | AT17: 26.6875 | AU17: 21.1369819305524 | AV17: 20.8290544327249 | AW17: 18.6332851199601 | AX17: 17.9842728930413 | AY17: 16.5251037109246 | AZ17: 17.5156853679268 | BA17: 17.0494827336028 | BB17: 18.7644705946022 | BC17: 19.2004283143122 | BD17: 17.7544737854169 | BE17: 17.2300682381835 | BF17: 15.9949873679769 | BG17: 16.4086652627089 | BH17: 17.5903303177529 | BI17: 17.3567061146333 | BJ17: 14.4060016758329 | BK17: 12.793041927804 | BL17: 12.1419889531682 | BM17: 11.6198425058429 | BN17: 11.7619087610202 | BO17: 11.7194139566373 | BP17: 12.3852390680976 | BQ17: 13.149294481602
A18: American Samoa | B18: ASM | C18: Lending interest rate (%) | D18: FR.INR.LEND
A19: Antigua and Barbuda | B19: ATG | C19: Lending interest rate (%) | D19: FR.INR.LEND | AA19: 10.9200003306071 | AB19: 11.6200003517998 | AC19: 11.4800003475613 | AD19: 11.0600003348456 | AE19: 11.9000003602769 | AF19: 10.64000032213 | AG19: 9.380000283983 | AH19: 10.64000032213 | AI19: 10.64000032213 | AJ19: 12.6500000953674 | AK19: 12.7000000476837 | AL19: 12.6758596545235 | AM19: 13.1467623059324 | AN19: 12.695846968362 | AO19: 12.2591910606266 | AP19: 11.9825861100038 | AQ19: 12.1951114740288 | AR19: 12.071877641383 | AS19: 12.1715539440033 | AT19: 11.6243803976043 | AU19: 11.387913378312 | AV19: 12.8219814495275 | AW19: 11.9643907528209 | AX19: 11.3939380792616 | AY19: 10.8905898841823 | AZ19: 10.4385350357948 | BA19: 10.4291009360419 | BB19: 10.0653700920516 | BC19: 10.9993475073677 | BD19: 10.9144525231277 | BE19: 10.1571966422671 | BF19: 9.95235329417181 | BG19: 10.0718377079627 | BH19: 9.83508333333333 | BI19: 9.575 | BJ19: 9.31 | BK19: 8.976532 | BL19: 8.61132908333333 | BM19: 7.68383775 | BN19: 7.39227225 | BO19: 7.31490375 | BP19: 6.71453383333333 | BQ19: 6.525259
A20: Australia | B20: AUS | C20: Lending interest rate (%) | D20: FR.INR.LEND | E20: 5 | F20: 5.5 | G20: 5.5 | H20: 5.125 | I20: 5.07291666666667 | J20: 5.3125 | K20: 5.375 | L20: 5.375 | M20: 5.58333333333333 | N20: 5.875 | O20: 6.90625 | P20: 7.25 | Q20: 7.02083333333333 | R20: 7.34375 | S20: 9.375 | T20: 10.2708333333333 | U20: 9.91666666666667 | V20: 9.875 | W20: 9.375 | X20: 9.125 | Y20: 9.97916666666667 | Z20: 11.8333333333333 | AA20: 13.2916666666667 | AB20: 12.4166666666667 | AC20: 11.5 | AD20: 12.4166666666667 | AE20: 15 | AF20: 15.0833333333333 | AG20: 14.0833333333333 | AH20: 16.4583333333333 | AI20: 16.3541666666667 | AJ20: 13.4166666666667 | AK20: 10.5833333333333 | AL20: 9.41666666666667 | AM20: 9.0875 | AN20: 10.5 | AO20: 9.72916666666667 | AP20: 7.16666666666667 | AQ20: 6.68333333333333 | AR20: 6.56666666666667 | AS20: 7.71666666666667 | AT20: 6.84166666666667 | AU20: 6.3625 | AV20: 6.6125 | AW20: 7.05 | AX20: 7.25833333333333 | AY20: 7.6125 | AZ20: 8.19583333333333 | BA20: 8.90833333333333 | BB20: 6.02083333333333 | BC20: 7.27916666666667 | BD20: 7.7375 | BE20: 6.975 | BF20: 6.17916666666667 | BG20: 5.95 | BH20: 5.575 | BI20: 5.42083333333333 | BJ20: 5.2455 | BK20: 5.26083333333333 | BL20: 5.101
A21: Austria | B21: AUT | C21: Lending interest rate (%) | D21: FR.INR.LEND
A22: Azerbaijan | B22: AZE | C22: Lending interest rate (%) | D22: FR.INR.LEND | AQ22: 19.85 | AR22: 19.4833333333333 | AS22: 19.6558333333333 | AT22: 19.7058333333333 | AU22: 17.3708333333333 | AV22: 15.4566666666667 | AW22: 15.72 | AX22: 17.0283333333333 | AY22: 17.8633333333333 | AZ22: 19.1308333333333 | BA22: 19.7625 | BB22: 20.0291666666667 | BC22: 20.7 | BD22: 18.9883333333333 | BE22: 18.3458333333333 | BF22: 18.21 | BG22: 17.8575 | BH22: 17.5341666666667 | BI22: 16.3752267159245 | BJ22: 16.5425 | BK22: 17.4483333333333 | BL22: 17.2812151745262 | BM22: 17.1782012225111 | BN22: 16.4259638117337 | BO22: 14.5897924973182 | BP22: 13.9648868370787 | BQ22: 14.6710589959746
A23: Burundi | B23: BDI | C23: Lending interest rate (%) | D23: FR.INR.LEND | W23: 12 | X23: 12 | Y23: 12 | Z23: 12 | AA23: 12 | AB23: 12 | AC23: 12 | AD23: 12 | AE23: 12 | AF23: 12 | AG23: 12 | AH23: 12 | AI23: 12.3416666666667 | AJ23: 12.7833333333333 | AK23: 13.6583333333333 | AL23: 13.7666666666667 | AM23: 14.2 | AN23: 15.2583333333333 | AQ23: 15.4 | AR23: 15.2358333333333 | AS23: 15.77 | AT23: 16.8241666666667 | AU23: 19.4675 | AV23: 18.2308333333333 | AW23: 18.2541666666667 | AX23: 18.445 | AY23: 17.0725 | AZ23: 16.8433333333333 | BA23: 16.5208333333333 | BB23: 14.0758333333333 | BC23: 12.42 | BD23: 13.2325 | BE23: 14.32 | BF23: 15.1475 | BG23: 15.6683333333333 | BH23: 15.3291666666667 | BI23: 14.2383333333333 | BJ23: 14.7966666666667 | BK23: 14.7891666666667 | BL23: 14.5333333333333 | BM23: 12.195 | BN23: 12.8583333333333 | BO23: 11.7725 | BP23: 11.23
A24: Belgium | B24: BEL | C24: Lending interest rate (%) | D24: FR.INR.LEND
A25: Benin | B25: BEN | C25: Lending interest rate (%) | D25: FR.INR.LEND | AX25: 8.04416666666667 | AY25: 4.73666666666667 | AZ25: 4.75166666666667 | BA25: 4.98416666666667 | BB25: 4.9775 | BC25: 5.11333333333333 | BD25: 5.25591666666667 | BE25: 5.03916666666667 | BF25: 5.2875 | BG25: 5.33833333333333 | BH25: 5.15416666666667 | BI25: 5.295 | BJ25: 6.93416666666667 | BK25: 6.76333333333333 | BL25: 6.68833333333333 | BM25: 6.5375 | BN25: 6.25
A26: Burkina Faso | B26: BFA | C26: Lending interest rate (%) | D26: FR.INR.LEND | AX26: 8.86833333333333 | AY26: 4.73666666666667 | AZ26: 4.75166666666667 | BA26: 4.98416666666667 | BB26: 4.9775 | BC26: 5.11333333333333 | BD26: 5.25591666666667 | BE26: 5.03916666666667 | BF26: 5.2875 | BG26: 5.33833333333333 | BH26: 5.15416666666667 | BI26: 5.295 | BJ26: 6.51166666666667 | BK26: 6.76333333333333 | BL26: 6.68833333333333 | BM26: 6.5375 | BN26: 6.25
A27: Bangladesh | B27: BGD | C27: Lending interest rate (%) | D27: FR.INR.LEND | U27: 10.2064285714286 | V27: 10.2064285714286 | W27: 10.2064285714286 | X27: 10.2064285714286 | Y27: 10.5157142857143 | Z27: 11.1342857142857 | AA27: 11.1342857142857 | AB27: 11.1342857142857 | AC27: 11.1342857142857 | AD27: 11.1342857142857 | AE27: 12.99 | AF27: 14.8457142857143 | AG27: 14.8457142857143 | AH27: 14.8457142857143 | AI27: 14.8457142857143 | AJ27: 14.7683928571429 | AK27: 13.9178571428571 | AL27: 13.9178571428571 | AM27: 13.4539285714286 | AN27: 12.99 | AO27: 12.99 | AP27: 12.99 | AQ27: 12.9325 | AR27: 13.0991666666667 | AS27: 12.755 | AT27: 12.82 | AU27: 12.6091666666667 | AV27: 12.0425 | AW27: 10.3991666666667 | AX27: 10.615 | AY27: 11.6641666666667 | AZ27: 12.635 | BA27: 12.8891666666667 | BB27: 13.3266666666667 | BC27: 12.2191666666667 | BD27: 13.3216666666667 | BE27: 13.9441666666667 | BF27: 13.5933333333333 | BG27: 12.945 | BH27: 11.7091666666667 | BI27: 10.4091666666667 | BJ27: 9.54 | BK27: 9.65083333333333 | BL27: 9.55583333333333 | BM27: 8.295 | BN27: 7.32416666666667 | BO27: 7.12109342742786 | BP27: 7.57 | BQ27: 9.8525
A28: Bulgaria | B28: BGR | C28: Lending interest rate (%) | D28: FR.INR.LEND | AK28: 74.05 | AL28: 76.8558333333333 | AM28: 102.515875 | AN28: 79.3615 | AO28: 291.05985 | AP28: 213.018416666667 | AQ28: 14.08335 | AR28: 13.498425 | AS28: 11.3433833333333 | AT28: 11.1107666666667 | AU28: 9.20784166666667 | AV28: 8.54336666666667 | AW28: 8.871325 | AX28: 8.66098333333333 | AY28: 8.892525 | AZ28: 9.99776666666667 | BA28: 10.861425 | BB28: 11.335 | BC28: 11.1443666666667 | BD28: 10.6294583333333 | BE28: 9.71420833333333 | BF28: 9.04340833333333 | BG28: 8.26264166666667 | BH28: 7.44886666666667 | BI28: 6.39301666666667 | BJ28: 5.43955833333333 | BK28: 4.963225 | BL28: 4.54920833333333 | BM28: 4.33663333333333 | BN28: 4.11618333333333 | BO28: 3.74595833333333 | BP28: 4.43805833333333 | BQ28: 4.61249166666667
A29: Bahrain | B29: BHR | C29: Lending interest rate (%) | D29: FR.INR.LEND | AE29: 8.95833333333333 | AF29: 7.5 | AG29: 7.8 | AH29: 8.41148197596796 | AI29: 8.41148197596796 | AJ29: 9.37632843791722 | AK29: 11.7265954606142 | AL29: 10.8359679572764 | AM29: 10.7122696929239 | AN29: 11.7018558077437 | AO29: 12.320347129506 | AP29: 12.1966488651535 | AQ29: 11.7958664886515 | AR29: 11.7340173564753 | AS29: 11.6028971962617 | AT29: 10.6924779706275 | AU29: 8.40653404539386 | AV29: 8.29520560747664 | AW29: 7.90431909212283 | AX29: 7.82185358255452 | AY29: 7.97523943035158 | AZ29: 8.26634267912772 | BA29: 8.2234606141522 | BB29: 7.94142857142857 | BC29: 7.2475 | BD29: 6.79083333333333 | BE29: 6.035 | BF29: 5.935 | BG29: 5.86833333333333 | BH29: 5.16083333333333
A30: Bahamas, The | B30: BHS | C30: Lending interest rate (%) | D30: FR.INR.LEND | U30: 9.5 | V30: 9.5 | W30: 9.5 | X30: 9.125 | Y30: 10.8333333333333 | Z30: 11 | AA30: 11 | AB30: 11 | AC30: 11 | AD30: 10.3333333333333 | AE30: 9.25 | AF30: 9 | AG30: 9 | AH30: 9 | AI30: 9 | AJ30: 9 | AK30: 8.08333333333333 | AL30: 7.45833333333333 | AM30: 6.875 | AN30: 6.75 | AO30: 6.75 | AP30: 6.75 | AQ30: 6.75 | AR30: 6.375 | AS30: 6 | AT30: 6 | AU30: 6 | AV30: 6 | AW30: 6 | AX30: 5.54166666666667 | AY30: 5.5 | AZ30: 5.5 | BA30: 5.5 | BB30: 5.5 | BC30: 5.5 | BD30: 5.0625 | BE30: 4.75 | BF30: 4.75 | BG30: 4.75 | BH30: 4.75 | BI30: 4.75 | BJ30: 4.25 | BK30: 4.25 | BL30: 4.25 | BM30: 4.25 | BN30: 4.25 | BO30: 4.25 | BP30: 4.25
A31: Bosnia and Herzegovina | B31: BIH | C31: Lending interest rate (%) | D31: FR.INR.LEND | AU31: 12.6958333333333 | AV31: 10.87 | AW31: 10.2816666666667 | AX31: 9.6125 | AY31: 8.01416666666667 | AZ31: 7.1725 | BA31: 6.97833333333333 | BB31: 7.9325 | BC31: 7.88833333333333 | BD31: 7.43166666666667 | BE31: 7.32891666666667 | BF31: 7.03604811133436 | BG31: 6.64150863945302 | BH31: 5.78888799043185 | BI31: 5.23816683778765 | BJ31: 4.37958143265647 | BK31: 3.79028136918822 | BL31: 3.28722715810128 | BM31: 3.07187413211574 | BN31: 3.20129279505403 | BO31: 3.36081655916726 | BP31: 4.11153155413122 | BQ31: 4.4501687610148
A32: Belarus | B32: BLR | C32: Lending interest rate (%) | D32: FR.INR.LEND | AK32: 21 | AL32: 71.625 | AM32: 148.5 | AN32: 175 | AO32: 62.3333333333333 | AP32: 31.8 | AQ32: 26.9916666666667 | AR32: 51.0416666666667 | AS32: 67.6666666666667 | AT32: 46.9666666666667 | AU32: 36.8833333333333 | AV32: 23.975 | AW32: 16.9083333333333 | AX32: 11.3583333333333 | AY32: 8.84166666666667 | AZ32: 8.575 | BA32: 8.55 | BB32: 11.675 | BC32: 9.21666666666667 | BD32: 13.575 | BE32: 19.4916666666667 | BF32: 19.1333333333333 | BG32: 18.7416666666667 | BH32: 18.0833333333333 | BI32: 14.4 | BJ32: 9.65871241633364 | BK32: 8.69583333333333 | BL32: 9.02333333333333 | BM32: 9.0325 | BN32: 10.1175 | BO32: 12.7158333333333 | BP32: 9.9623073222544 | BQ32: 9.99166666666667
A33: Belize | B33: BLZ | C33: Lending interest rate (%) | D33: FR.INR.LEND | AA33: 14.5916666666667 | AB33: 14.5916666666667 | AC33: 14.5916666666667 | AD33: 14.5916666666667 | AE33: 14.6916666666667 | AF33: 14.1416666666667 | AG33: 13.5583333333333 | AH33: 13.7666666666667 | AI33: 14.0416666666667 | AJ33: 14.2416666666667 | AK33: 14.3166666666667 | AL33: 14.3666666666667 | AM33: 14.775 | AN33: 15.6916666666667 | AO33: 16.3 | AP33: 16.2916666666667 | AQ33: 16.5 | AR33: 16.2725 | AS33: 16.005 | AT33: 15.4541666666667 | AU33: 14.8341666666667 | AV33: 14.345 | AW33: 13.9416666666667 | AX33: 14.255 | AY33: 14.2091666666667 | AZ33: 14.3333333333333 | BA33: 14.1408333333333 | BB33: 14.0816666666667 | BC33: 13.8833333333333 | BD33: 13.3633333333333 | BE33: 12.4408333333333 | BF33: 11.5691666666667 | BG33: 10.8217831837388 | BH33: 10.320279926803 | BI33: 9.84091010965423 | BJ33: 9.4625 | BK33: 9.115 | BL33: 9.06666666666667 | BM33: 8.73416666666667 | BN33: 8.43833333333333 | BO33: 8.52349151589079 | BP33: 8.4375 | BQ33: 8.41743522598784
A34: Bermuda | B34: BMU | C34: Lending interest rate (%) | D34: FR.INR.LEND
A35: Bolivia | B35: BOL | C35: Lending interest rate (%) | D35: FR.INR.LEND | AF35: 49.4141666666667 | AG35: 39.7941666666667 | AH35: 37.2733333333333 | AI35: 41.8133333333333 | AJ35: 41.1475 | AK35: 45.5116666666667 | AL35: 53.8766666666667 | AM35: 55.5733333333333 | AN35: 51.0175 | AO35: 55.9666666666667 | AP35: 50.05 | AQ35: 39.4116666666667 | AR35: 35.3691666666667 | AS35: 34.5958333333333 | AT35: 20.0570612222166 | AU35: 20.6324567427484 | AV35: 17.6632890518186 | AW35: 14.4698833333333 | AX35: 16.6150416666667 | AY35: 11.8912833333333 | AZ35: 12.8608083333333 | BA35: 13.8733333333333 | BB35: 12.359625 | BC35: 9.90992714868378 | BD35: 10.915392341297 | BE35: 11.1349478606743 | BF35: 11.0513992821176 | BG35: 9.69422821628935 | BH35: 8.07325379670779 | BI35: 7.95202606117997 | BJ35: 8.10989203240817 | BK35: 8.03724252665112 | BL35: 8.39953170954602 | BM35: 7.59222372184479 | BN35: 8.01711817014333 | BO35: 7.76498872156729 | BP35: 8.64390131615292
A36: Brazil | B36: BRA | C36: Lending interest rate (%) | D36: FR.INR.LEND | AP36: 78.1933333333333 | AQ36: 86.3633333333333 | AR36: 80.4433333333333 | AS36: 56.83 | AT36: 57.6166666666667 | AU36: 62.875 | AV36: 67.0833333333333 | AW36: 54.925 | AX36: 55.3833333333333 | AY36: 50.8083333333333 | AZ36: 43.7166666666667 | BA36: 47.25 | BB36: 44.65 | BC36: 39.9916666666667 | BD36: 43.8833333333333 | BE36: 36.6366666666667 | BF36: 27.3916666666667 | BG36: 32.0083333333333 | BH36: 43.9583333333333 | BI36: 52.1 | BJ36: 46.9166666666667 | BK36: 39.0833333333333 | BL36: 37.475 | BM36: 29.0416666666667 | BN36: 30.0166666666667 | BO36: 39.4 | BP36: 43.6 | BQ36: 40.225
A37: Barbados | B37: BRB | C37: Lending interest rate (%) | D37: FR.INR.LEND | Z37: 11.4583333333333 | AA37: 13.375 | AB37: 11.7916666666667 | AC37: 11.5 | AD37: 10.5625 | AE37: 9.0625 | AF37: 8.75 | AG37: 9.4375 | AH37: 9.91666666666667 | AI37: 11.4166666666667 | AJ37: 12.4166666666667 | AK37: 13.5416666666667 | AL37: 8.91666666666667 | AM37: 9.08333333333333 | AN37: 10 | AO37: 10 | AP37: 9.83333333333333 | AQ37: 9.75 | AR37: 9.39583333333333 | AS37: 10.1875 | AT37: 9.58333333333333 | AU37: 8.5 | AV37: 8.5 | AW37: 8.33333333333333 | AX37: 9.16666666666667 | AY37: 10.2916666666667 | AZ37: 10.7583333333333 | BA37: 10.0333333333333 | BB37: 9.20416666666667 | BC37: 8.7 | BD37: 8.7 | BE37: 8.7 | BF37: 8.7 | BG37: 8.38333333333333 | BH37: 8.05833333333333 | BI37: 8.05 | BJ37: 8.05 | BK37: 8.05 | BL37: 8.05 | BM37: 8.05 | BN37: 8.05 | BO37: 8.05
A38: Brunei Darussalam | B38: BRN | C38: Lending interest rate (%) | D38: FR.INR.LEND | AQ38: 6.5 | AR38: 5.5 | AS38: 5.5 | AT38: 5.5 | AU38: 5.5 | AV38: 5.5 | AW38: 5.5 | AX38: 5.5 | AY38: 5.5 | AZ38: 5.5 | BA38: 5.5 | BB38: 5.5 | BC38: 5.5 | BD38: 5.5 | BE38: 5.5 | BF38: 5.5 | BG38: 5.5 | BH38: 5.5 | BI38: 5.5 | BJ38: 5.5 | BK38: 5.5 | BL38: 5.5 | BM38: 5.5 | BN38: 5.5 | BO38: 5.5 | BP38: 5.5 | BQ38: 5.5
A39: Bhutan | B39: BTN | C39: Lending interest rate (%) | D39: FR.INR.LEND | AA39: 15 | AB39: 15 | AC39: 15 | AD39: 15 | AE39: 15 | AF39: 15 | AG39: 15 | AH39: 15 | AI39: 15 | AJ39: 15 | AK39: 17 | AL39: 17 | AM39: 16.5833333333333 | AN39: 16 | AO39: 16 | AP39: 16 | AQ39: 16 | AR39: 16 | AS39: 16 | AT39: 15.8541666666667 | AU39: 15.4583333333333 | AV39: 15.1875 | AW39: 15 | AX39: 14.5 | AY39: 14 | AZ39: 14 | BA39: 13.8541666666667 | BB39: 13.75 | BC39: 13.9166666666667 | BD39: 14 | BE39: 14 | BF39: 14.0375 | BG39: 14.025 | BH39: 14.8958333333333 | BI39: 14.15 | BJ39: 14.25 | BK39: 14 | BL39: 14 | BM39: 14 | BN39: 14 | BO39: 14 | BP39: 12.27
A40: Botswana | B40: BWA | C40: Lending interest rate (%) | D40: FR.INR.LEND | Y40: 8.475 | Z40: 9.625 | AA40: 24.2083333333333 | AB40: 13.375 | AC40: 12 | AD40: 11.5 | AE40: 11 | AF40: 10 | AG40: 7.83333333333333 | AH40: 7.66666666666667 | AI40: 7.875 | AJ40: 11.8333333333333 | AK40: 14 | AL40: 14.9166666666667 | AM40: 13.9166666666667 | AN40: 14.4166666666667 | AO40: 14.5 | AP40: 13.9466666666667 | AQ40: 13.6508333333333 | AR40: 14.7758333333333 | AS40: 15.4791666666667 | AT40: 15.75 | AU40: 16.2083333333333 | AV40: 16.4 | AW40: 15.75 | AX40: 15.7375 | AY40: 16.4583333333333 | AZ40: 16.215 | BA40: 16.5416666666667 | BB40: 13.755625 | BC40: 11.4583333333333 | BD40: 11 | BE40: 11 | BF40: 10.1892333333333 | BG40: 9 | BH40: 7.95 | BI40: 7.3 | BJ40: 6.875 | BK40: 6.5 | BL40: 6.39583333333333 | BM40: 5.75 | BN40: 5.25 | BO40: 6.1323 | BP40: 6.73859953703704 | BQ40: 6.26
A41: Central African Republic | B41: CAF | C41: Lending interest rate (%) | D41: FR.INR.LEND
A42: Canada | B42: CAN | C42: Lending interest rate (%) | D42: FR.INR.LEND | E42: 5.75 | F42: 5.60416666666667 | G42: 5.70833333333333 | H42: 5.75 | I42: 5.75 | J42: 5.77083333333333 | K42: 6 | L42: 5.91666666666667 | M42: 6.91666666666667 | N42: 7.95833333333333 | O42: 8.16666666666667 | P42: 6.47916666666667 | Q42: 6 | R42: 7.64583333333333 | S42: 10.75 | T42: 9.41666666666667 | U42: 10.0416666666667 | V42: 8.5 | W42: 9.6875 | X42: 12.8958333333333 | Y42: 14.25 | Z42: 19.2916666666667 | AA42: 15.8125 | AB42: 11.1666666666667 | AC42: 12.0625 | AD42: 10.5833333333333 | AE42: 10.5208333333333 | AF42: 9.52083333333333 | AG42: 10.8333333333333 | AH42: 13.3333333333333 | AI42: 14.0625 | AJ42: 9.9375 | AK42: 7.47916666666667 | AL42: 5.9375 | AM42: 6.875 | AN42: 8.64583333333333 | AO42: 6.0625 | AP42: 4.95833333333333 | AQ42: 6.60416666666667 | AR42: 6.4375 | AS42: 7.27083333333333 | AT42: 5.8125 | AU42: 4.20833333333333 | AV42: 4.6875 | AW42: 4 | AX42: 4.41666666666667 | AY42: 5.8125 | AZ42: 6.10416666666667 | BA42: 4.72916666666667 | BB42: 2.39583333333333 | BC42: 2.60416666666667 | BD42: 3 | BE42: 3 | BF42: 3 | BG42: 3 | BH42: 2.775 | BI42: 2.7 | BJ42: 2.7
A43: Central Europe and the Baltics | B43: CEB | C43: Lending interest rate (%) | D43: FR.INR.LEND
A44: Switzerland | B44: CHE | C44: Lending interest rate (%) | D44: FR.INR.LEND | BA44: 3.3425 | BB44: 2.75083333333333 | BC44: 2.73333333333333 | BD44: 2.71833333333333 | BE44: 2.68833333333333 | BF44: 2.68916666666667 | BG44: 2.69 | BH44: 2.68083333333333 | BI44: 2.64666666666667 | BJ44: 2.62743867833333 | BK44: 2.62742559333333 | BL44: 2.63292318 | BM44: 2.63484670416667 | BN44: 2.63985731416667 | BO44: 2.64672373583333 | BP44: 2.86414745583333 | BQ44: 2.97616142777778
A45: Channel Islands | B45: CHI | C45: Lending interest rate (%) | D45: FR.INR.LEND
A46: Chile | B46: CHL | C46: Lending interest rate (%) | D46: FR.INR.LEND | AD46: 39.9655239888964 | AE46: 26.3591384058586 | AF46: 32.6655350973518 | AG46: 21.2134249729057 | AH46: 36.009133634171 | AI46: 48.8691791893508 | AJ46: 28.5754178909029 | AK46: 23.9705261388324 | AL46: 24.3458278419054 | AM46: 20.3396521773457 | AN46: 18.1595558966592 | AO46: 17.3678567329936 | AP46: 15.670265400513 | AQ46: 20.1695011436128 | AR46: 12.6231518368615 | AS46: 14.8433912347788 | AT46: 11.8910098561076 | AU46: 7.75807289652374 | AV46: 6.17877873086097 | AW46: 5.12700362788107 | AX46: 6.67787900981346 | AY46: 7.99948207856606 | AZ46: 8.67125848644778 | BA46: 13.261771366415 | BB46: 7.25063476884463 | BC46: 4.75482680518703 | BD46: 9.03015252269429 | BE46: 10.0572624433615 | BF46: 9.26187678192101 | BG46: 8.09805824839012 | BH46: 5.51492732291402 | BI46: 5.58839657725206 | BJ46: 4.55285507889072 | BK46: 4.17801925025561
A47: China | B47: CHN | C47: Lending interest rate (%) | D47: FR.INR.LEND | Y47: 5.039999999 | Z47: 5.039999999 | AA47: 7.199999999 | AB47: 7.199999999 | AC47: 7.199999999 | AD47: 7.919999999 | AE47: 7.92 | AF47: 7.92 | AG47: 9 | AH47: 11.34 | AI47: 9.36 | AJ47: 8.64 | AK47: 8.64 | AL47: 10.98 | AM47: 10.98 | AN47: 12.06 | AO47: 10.08 | AP47: 8.64 | AQ47: 6.39 | AR47: 5.85 | AS47: 5.85 | AT47: 5.85 | AU47: 5.31 | AV47: 5.31 | AW47: 5.58 | AX47: 5.58 | AY47: 6.12 | AZ47: 7.47 | BA47: 5.31 | BB47: 5.31 | BC47: 5.81 | BD47: 6.56 | BE47: 6 | BF47: 6 | BG47: 5.6 | BH47: 4.35 | BI47: 4.35 | BJ47: 4.35 | BK47: 4.35 | BL47: 4.35 | BM47: 4.35 | BN47: 4.35 | BO47: 4.35 | BP47: 4.35 | BQ47: 4.35
A48: Cote d'Ivoire | B48: CIV | C48: Lending interest rate (%) | D48: FR.INR.LEND | AX48: 7.04916666666667 | AY48: 4.73666666666667 | AZ48: 4.75166666666667 | BA48: 4.98416666666667 | BB48: 4.9775 | BC48: 5.11333333333333 | BD48: 5.25591666666667 | BE48: 5.03916666666667 | BF48: 5.2875 | BG48: 5.33833333333333 | BH48: 5.15416666666667 | BI48: 5.295 | BJ48: 5.14
A49: Cameroon | B49: CMR | C49: Lending interest rate (%) | D49: FR.INR.LEND
A50: Congo, Dem. Rep. | B50: COD | C50: Lending interest rate (%) | D50: FR.INR.LEND | AY50: 46.4358333333333 | AZ50: 47.0010183333333 | BA50: 43.1541666666667 | BB50: 65.4175 | BC50: 56.5183333333333 | BD50: 43.75340275 | BE50: 28.4466666666667 | BF50: 19.3660119047619 | BG50: 18.6925 | BH50: 19.3708333333333 | BI50: 19.0458333333333 | BJ50: 20.6208333333333 | BK50: 24.7483333333333 | BL50: 26.7358333333333 | BM50: 25.9584937147496 | BN50: 23.2857241932595
A51: Congo, Rep. | B51: COG | C51: Lending interest rate (%) | D51: FR.INR.LEND
A52: Colombia | B52: COL | C52: Lending interest rate (%) | D52: FR.INR.LEND | AE52: 40.2201365187713 | AF52: 40.4844402730375 | AG52: 42.0456382252559 | AH52: 42.3920238907849 | AI52: 44.569656996587 | AJ52: 46.4206040955631 | AK52: 36.7193430034129 | AL52: 35.2763430034129 | AM52: 39.8573344709897 | AN52: 42.0760085324232 | AO52: 41.3618959044368 | AP52: 33.7102201365188 | AQ52: 41.6048583617747 | AR52: 29.4258003412969 | AS52: 18.7866666666667 | AT52: 20.72 | AU52: 16.3267983308288 | AV52: 15.187101145088 | AW52: 15.0830567168883 | AX52: 14.5608333333333 | AY52: 12.893913084832 | AZ52: 15.3818501011015 | BA52: 17.1756231436697 | BB52: 13.0080746033842 | BC52: 9.38148993683401 | BD52: 11.2199184470583 | BE52: 12.5850402049247 | BF52: 10.9855861710036 | BG52: 10.8673350376127 | BH52: 11.4499872575296 | BI52: 14.6454318106769 | BJ52: 13.6858303184817 | BK52: 12.1148777449182 | BL52: 11.7690653821827 | BM52: 9.85052425129014 | BN52: 9.3378484091001 | BO52: 15.8075088706303 | BP52: 21.0306368304862 | BQ52: 16.3744226380092
A53: Comoros | B53: COM | C53: Lending interest rate (%) | D53: FR.INR.LEND | AR53: 13.6666666666667 | AS53: 12 | AT53: 12 | AU53: 12 | AV53: 11.8333333333333 | AW53: 11 | AX53: 11 | AY53: 10.5 | AZ53: 10.5 | BA53: 10.5 | BB53: 10.5 | BC53: 10.5 | BD53: 10.5 | BE53: 10.5 | BF53: 10.5 | BG53: 10.5 | BH53: 10.5 | BI53: 10.5 | BJ53: 10.5 | BK53: 10.5 | BL53: 10.5 | BM53: 8.09375 | BN53: 7.875 | BO53: 8.03375
A54: Cabo Verde | B54: CPV | C54: Lending interest rate (%) | D54: FR.INR.LEND | AY54: 10.8041599222222 | AZ54: 10.5510481523038 | BA54: 9.98901352284579 | BB54: 10.9766450308146 | BC54: 11.0398987608935 | BD54: 9.81080381518199 | BE54: 9.90035884746328 | BF54: 10.520099018866 | BG54: 10.8937565287826 | BH54: 10.4058225644923 | BI54: 9.60664701973665 | BJ54: 9.48812259528097 | BK54: 8.97292567041423 | BL54: 9.14083475915223 | BM54: 8.19451484269313 | BN54: 7.61928566776367 | BO54: 7.83172030290501 | BP54: 7.5285150596832 | BQ54: 7.79135488631362
A55: Costa Rica | B55: CRI | C55: Lending interest rate (%) | D55: FR.INR.LEND | AA55: 25 | AB55: 23.25 | AC55: 18 | AD55: 20.9166666666667 | AE55: 21.7991666666667 | AF55: 23.8233333333333 | AG55: 28.6883333333333 | AH55: 29.1691666666667 | AI55: 32.5566666666667 | AJ55: 38.8758333333333 | AK55: 28.4608333333333 | AL55: 30.0208333333333 | AM55: 33.0258333333333 | AN55: 36.695 | AO55: 26.2741666666667 | AP55: 22.4766666666667 | AQ55: 22.4733333333333 | AR55: 25.737 | AS55: 24.8891666666667 | AT55: 23.8327694441667 | AU55: 26.4166666666667 | AV55: 25.5833333333333 | AW55: 23.4255555555556 | AX55: 24.6558333333333 | AY55: 22.1883333333333 | AZ55: 12.7983333333333 | BA55: 15.8275 | BB55: 19.7233333333333 | BC55: 17.0908333333333 | BD55: 16.1458333333333 | BE55: 18.2125 | BF55: 15.1883333333333 | BG55: 14.9030555555556 | BH55: 14.2333333333334 | BI55: 11.6386111111111 | BJ55: 11.3651388888889 | BK55: 11.1232908801993 | BL55: 8.74614960993387 | BM55: 6.63808237583333 | BN55: 5.51221232 | BO55: 7.36085073166667 | BP55: 9.09653675666667 | BQ55: 7.33487695166667
A56: Caribbean small states | B56: CSS | C56: Lending interest rate (%) | D56: FR.INR.LEND
A57: Cuba | B57: CUB | C57: Lending interest rate (%) | D57: FR.INR.LEND
A58: Curacao | B58: CUW | C58: Lending interest rate (%) | D58: FR.INR.LEND
A59: Cayman Islands | B59: CYM | C59: Lending interest rate (%) | D59: FR.INR.LEND
A60: Cyprus | B60: CYP | C60: Lending interest rate (%) | D60: FR.INR.LEND
A61: Czechia | B61: CZE | C61: Lending interest rate (%) | D61: FR.INR.LEND | AL61: 14.0708333333333 | AM61: 13.1183333333333 | AN61: 12.7991666666667 | AO61: 12.5441666666667 | AP61: 13.2041666666667 | AQ61: 12.8071666666667 | AR61: 8.68416666666667 | AS61: 7.16225 | AT61: 7.19641666666667 | AU61: 6.72416666666667 | AV61: 5.94916666666667 | AW61: 6.0275 | AX61: 5.77666666666667 | AY61: 5.59366602166667 | AZ61: 5.78837958370079 | BA61: 6.25170833333333 | BB61: 5.98995833333333 | BC61: 5.88783333333333 | BD61: 5.71783333333333 | BE61: 5.40672323724727 | BF61: 4.96989301373891 | BG61: 4.64490546444 | BH61: 4.28253332923937 | BI61: 3.9072462757748 | BJ61: 3.58974364323778 | BK61: 3.54161587741081 | BL61: 3.68603218349692 | BM61: 3.34430704292427 | BN61: 3.20212533339961 | BO61: 4.22500917823384 | BP61: 4.68277500627328 | BQ61: 4.71376531072935
A62: Germany | B62: DEU | C62: Lending interest rate (%) | D62: FR.INR.LEND
A63: Djibouti | B63: DJI | C63: Lending interest rate (%) | D63: FR.INR.LEND
A64: Dominica | B64: DMA | C64: Lending interest rate (%) | D64: FR.INR.LEND | AA64: 10.184890795448 | AB64: 10.4529142374335 | AC64: 11.2123139897257 | AD64: 10.7656082530832 | AE64: 10.9889611214044 | AF64: 11.2569845633899 | AG64: 11.2569845633899 | AH64: 11.2569845633899 | AI64: 11.2569845633899 | AJ64: 11.2163014829248 | AK64: 11.5231698453901 | AL64: 11.9238245391238 | AM64: 11.6104913178287 | AN64: 11.5007436413857 | AO64: 11.4303325301194 | AP64: 11.1730597100209 | AQ64: 11.2725600466202 | AR64: 11.3956730721677 | AS64: 11.6808005322677 | AT64: 11.1397494990693 | AU64: 10.9728957217648 | AV64: 11.5007049422952 | AW64: 8.94144093203256 | AX64: 9.91817590459821 | AY64: 9.50240122157026 | AZ64: 9.16801247233374 | BA64: 9.06404638816547 | BB64: 10.0192940627616 | BC64: 9.45501398850831 | BD64: 8.84037965492994 | BE64: 9.04298186920945 | BF64: 9.07396001934442 | BG64: 8.93663314196025 | BH64: 8.66866666666666 | BI64: 8.2775 | BJ64: 8.075 | BK64: 7.81221991666667 | BL64: 7.53996066666667 | BM64: 6.89907858333333 | BN64: 6.29791625 | BO64: 6.53699175 | BP64: 5.935577 | BQ64: 5.83305675
A65: Denmark | B65: DNK | C65: Lending interest rate (%) | D65: FR.INR.LEND
A66: Dominican Republic | B66: DOM | C66: Lending interest rate (%) | D66: FR.INR.LEND | AJ66: 35.26 | AK66: 28.34 | AL66: 29.89 | AM66: 28.68 | AN66: 30.6825 | AO66: 23.7341666666667 | AP66: 21.0066666666667 | AQ66: 25.6425 | AR66: 25.045 | AS66: 26.7991666666667 | AT66: 24.2633333333333 | AU66: 26.055 | AV66: 31.3916666666667 | AW66: 32.6308333333333 | AX66: 24.1091666666667 | AY66: 19.475 | AZ66: 15.8275 | BA66: 19.945 | BB66: 18.1358333333333 | BC66: 12.1366666666667 | BD66: 15.55 | BE66: 15.4825 | BF66: 13.5914005366667 | BG66: 13.9025 | BH66: 14.8766666666667 | BI66: 15.0841666666667 | BJ66: 13.91 | BK66: 12.5337 | BL66: 12.4867666666667 | BM66: 10.9796416666667 | BN66: 9.60830833333333 | BO66: 11.85005 | BP66: 14.4345416666667 | BQ66: 15.2531
A67: Algeria | B67: DZA | C67: Lending interest rate (%) | D67: FR.INR.LEND | AN67: 18.4166666666667 | AO67: 19 | AP67: 15.7083333333333 | AQ67: 11.5 | AR67: 10.75 | AS67: 10 | AT67: 9.5 | AU67: 8.58333333333333 | AV67: 8.125 | AW67: 8 | AX67: 8 | AY67: 8 | AZ67: 8 | BA67: 8 | BB67: 8 | BC67: 8 | BD67: 8 | BE67: 8 | BF67: 8 | BG67: 8 | BH67: 8 | BI67: 8 | BJ67: 8 | BK67: 8 | BL67: 8 | BM67: 8 | BN67: 8 | BO67: 8 | BP67: 8 | BQ67: 8
A68: East Asia & Pacific (excluding high income) | B68: EAP | C68: Lending interest rate (%) | D68: FR.INR.LEND
A69: Early-demographic dividend | B69: EAR | C69: Lending interest rate (%) | D69: FR.INR.LEND
A70: East Asia & Pacific | B70: EAS | C70: Lending interest rate (%) | D70: FR.INR.LEND
A71: Europe & Central Asia (excluding high income) | B71: ECA | C71: Lending interest rate (%) | D71: FR.INR.LEND
A72: Europe & Central Asia | B72: ECS | C72: Lending interest rate (%) | D72: FR.INR.LEND
A73: Ecuador | B73: ECU | C73: Lending interest rate (%) | D73: FR.INR.LEND
A74: Egypt, Arab Rep. | B74: EGY | C74: Lending interest rate (%) | D74: FR.INR.LEND | U74: 8 | V74: 8.83333333333333 | W74: 10.1666666666667 | X74: 12 | Y74: 13.3333333333333 | Z74: 15 | AA74: 15 | AB74: 15 | AC74: 15 | AD74: 15 | AE74: 15 | AF74: 16.3333333333333 | AG74: 17 | AH74: 18.3333333333333 | AI74: 19 | AJ74: 19.8466666666667 | AK74: 20.3283333333333 | AL74: 18.2975 | AM74: 16.5125 | AN74: 16.4708333333333 | AO74: 15.5833333333333 | AP74: 13.7916666666667 | AQ74: 13.0166666666667 | AR74: 12.965 | AS74: 13.2158333333333 | AT74: 13.2916666666667 | AU74: 13.7916666666667 | AV74: 13.5333333333333 | AW74: 13.375 | AX74: 13.1416666666667 | AY74: 12.6 | AZ74: 12.5083333333333 | BA74: 12.325 | BB74: 11.975 | BC74: 11.0083333333333 | BD74: 11.0333333333333 | BE74: 12 | BF74: 12.2916666666667 | BG74: 11.7083333333333 | BH74: 11.625 | BI74: 13.6 | BJ74: 18.175 | BK74: 18.3166666666667 | BL74: 16.1166666666667 | BM74: 11.3666666666667 | BN74: 9.425 | BO74: 10.5833333333333 | BP74: 17.7583333333333 | BQ74: 24.2916666666667
A75: Euro area | B75: EMU | C75: Lending interest rate (%) | D75: FR.INR.LEND
A76: Eritrea | B76: ERI | C76: Lending interest rate (%) | D76: FR.INR.LEND
A77: Spain | B77: ESP | C77: Lending interest rate (%) | D77: FR.INR.LEND
A78: Estonia | B78: EST | C78: Lending interest rate (%) | D78: FR.INR.LEND
A79: Ethiopia | B79: ETH | C79: Lending interest rate (%) | D79: FR.INR.LEND | AD79: 8.5 | AE79: 7.25 | AF79: 6 | AG79: 6 | AH79: 6 | AI79: 6 | AJ79: 6 | AK79: 8 | AL79: 14 | AM79: 14.3333333333333 | AN79: 15.0833333333333 | AO79: 13.9166666666667 | AP79: 10.5 | AQ79: 10.5 | AR79: 10.5816666666667 | AS79: 10.8916666666667 | AT79: 10.8651666666667 | AU79: 8.661 | AV79: 7 | AW79: 7 | AX79: 7 | AY79: 7 | AZ79: 7.5 | BA79: 8
A80: European Union | B80: EUU | C80: Lending interest rate (%) | D80: FR.INR.LEND
A81: Fragile and conflict affected situations | B81: FCS | C81: Lending interest rate (%) | D81: FR.INR.LEND
A82: Finland | B82: FIN | C82: Lending interest rate (%) | D82: FR.INR.LEND
A83: Fiji | B83: FJI | C83: Lending interest rate (%) | D83: FR.INR.LEND | AK83: 12.45 | AL83: 11.8891666666667 | AM83: 11.4416666666667 | AN83: 11.2375 | AO83: 11.1383333333333 | AP83: 11.0266666666667 | AQ83: 9.63666666666667 | AR83: 8.76583333333333 | AS83: 8.3975 | AT83: 8.34457575862199 | AU83: 8.0525 | AV83: 7.60249694765339 | AW83: 7.16924874091492 | AX83: 6.77996099984964 | AY83: 7.34996258823936 | AZ83: 9.0055873301356 | BA83: 7.99726954431674 | BB83: 7.85341601530875 | BC83: 7.48964734611671 | BD83: 7.46605819217571 | BE83: 7.00306444698518 | BF83: 6.10472546158863 | BG83: 5.76111099677945 | BH83: 5.78930050894162 | BI83: 5.8513236372606 | BJ83: 5.74051096179291 | BK83: 5.67732659254776 | BL83: 6.02745671637929 | BM83: 6.18490255198124 | BN83: 5.94242130030892 | BO83: 5.43188908929798 | BP83: 4.97070088792201 | BQ83: 4.6603226192379
A84: France | B84: FRA | C84: Lending interest rate (%) | D84: FR.INR.LEND
A85: Faroe Islands | B85: FRO | C85: Lending interest rate (%) | D85: FR.INR.LEND
A86: Micronesia, Fed. Sts. | B86: FSM | C86: Lending interest rate (%) | D86: FR.INR.LEND | AN86: 15 | AO86: 15 | AP86: 15 | AQ86: 15 | AR86: 15.165 | AS86: 15.33 | AT86: 15.33 | AU86: 15.275 | AV86: 15 | AW86: 15.375 | AX86: 16.375 | AY86: 15.615 | AZ86: 14.0295833333333 | BA86: 14.3783333333333 | BB86: 15.38 | BC86: 15.13 | BD86: 14.35 | BE86: 14.32 | BF86: 15.7 | BG86: 15.7 | BH86: 15.7 | BI86: 15.7 | BJ86: 16.1 | BK86: 15.7 | BL86: 14.7 | BM86: 14.47 | BN86: 12.62
A87: Gabon | B87: GAB | C87: Lending interest rate (%) | D87: FR.INR.LEND
A88: United Kingdom | B88: GBR | C88: Lending interest rate (%) | D88: FR.INR.LEND | L88: 5.5 | M88: 6.125 | N88: 6.625 | O88: 7.25 | P88: 7.5 | Q88: 7.5 | R88: 8 | S88: 9 | T88: 10.4676916666667 | U88: 11.10095 | V88: 8.91186666666667 | W88: 9.09315 | X88: 13.6948083333333 | Y88: 16.3126833333333 | Z88: 13.255 | AA88: 11.9309666666667 | AB88: 9.82526666666667 | AC88: 9.6801 | AD88: 12.2529833333333 | AE88: 10.9013583333333 | AF88: 9.7355 | AG88: 10.0957083333333 | AH88: 13.8418083333333 | AI88: 14.7681166666667 | AJ88: 11.6949833333333 | AK88: 9.56348333333333 | AL88: 6.01363333333333 | AM88: 5.46278333333333 | AN88: 6.693675 | AO88: 5.95853333333333 | AP88: 6.5634 | AQ88: 7.23205 | AR88: 5.34440833333333 | AS88: 5.96389166666667 | AT88: 5.122375 | AU88: 4 | AV88: 3.69579166666667 | AW88: 4.37981666666667 | AX88: 4.648675 | AY88: 4.63825833333333 | AZ88: 5.50870833333333 | BA88: 4.67530833333333 | BB88: 0.644866666666667 | BC88: 0.5 | BD88: 0.5 | BE88: 0.5 | BF88: 0.5 | BG88: 0.5
A89: Georgia | B89: GEO | C89: Lending interest rate (%) | D89: FR.INR.LEND | AV89: 23.755375 | AW89: 22.087125 | AX89: 17.5508916666667 | AY89: 17.0602583333333 | AZ89: 17.0861166666667 | BA89: 18.0441333333333 | BB89: 17.8663166666667 | BC89: 15.845075 | BD89: 14.9951666666667 | BE89: 14.80845 | BF89: 13.5948916043986 | BG89: 11.9097117693843 | BH89: 12.4884754630803 | BI89: 12.6209166666667 | BJ89: 11.4853833333333 | BK89: 11.1193916666667 | BL89: 10.8164 | BM89: 11.8008 | BN89: 12.5104916666667 | BO89: 13.655325 | BP89: 13.5107 | BQ89: 12.0339916666667
A90: Ghana | B90: GHA | C90: Lending interest rate (%) | D90: FR.INR.LEND
A91: Gibraltar | B91: GIB | C91: Lending interest rate (%) | D91: FR.INR.LEND
A92: Guinea | B92: GIN | C92: Lending interest rate (%) | D92: FR.INR.LEND | AE92: 14 | AF92: 15 | AG92: 15 | AH92: 17.25 | AI92: 21.1666666666667 | AJ92: 24.5 | AK92: 27 | AL92: 24.5 | AM92: 22 | AN92: 21.5 | AO92: 21 | AP92: 20.5 | AQ92: 19.5625 | AR92: 19.875 | AS92: 19.375 | AT92: 12.875
A93: Gambia, The | B93: GMB | C93: Lending interest rate (%) | D93: FR.INR.LEND | AD93: 14.483333333 | AE93: 28 | AF93: 27.9166666666667 | AG93: 29.5416666666667 | AH93: 26.8333333333333 | AI93: 26.5 | AJ93: 26.5 | AK93: 26.75 | AL93: 26.0833333333333 | AM93: 25 | AN93: 25.0416666666667 | AO93: 25.5 | AP93: 25.5 | AQ93: 25.375 | AR93: 24 | AS93: 24 | AT93: 24 | AU93: 24 | AV93: 29.3333333333333 | AW93: 36.5 | AX93: 34.9166666666667 | AY93: 29.75 | AZ93: 27.9166666666667 | BA93: 27 | BB93: 27 | BC93: 27 | BD93: 28 | BE93: 28 | BF93: 28 | BG93: 28.5 | BJ93: 29 | BK93: 28 | BL93: 28 | BM93: 28 | BN93: 19.5 | BO93: 19 | BP93: 20.75
A94: Guinea-Bissau | B94: GNB | C94: Lending interest rate (%) | D94: FR.INR.LEND | AX94: 10.3670833333333 | AY94: 4.73666666666667 | AZ94: 4.75166666666667 | BA94: 4.98416666666667 | BB94: 4.9775 | BC94: 5.11333333333333 | BD94: 5.25591666666667 | BE94: 5.03916666666667 | BF94: 5.2875 | BG94: 5.33833333333333 | BH94: 5.15416666666667 | BI94: 5.295 | BJ94: 5.14
A95: Equatorial Guinea | B95: GNQ | C95: Lending interest rate (%) | D95: FR.INR.LEND
A96: Greece | B96: GRC | C96: Lending interest rate (%) | D96: FR.INR.LEND
A97: Grenada | B97: GRD | C97: Lending interest rate (%) | D97: FR.INR.LEND | AA97: 12.325478090371 | AB97: 12.325478090371 | AC97: 12.325478090371 | AD97: 13.4015118919113 | AE97: 13.4993331465968 | AF97: 13.3036906372258 | AG97: 12.325478090371 | AH97: 12.325478090371 | AI97: 12.325478090371 | AJ97: 12.3019964706182 | AK97: 12.0231759977324 | AL97: 11.8323783953494 | AM97: 11.0280532690074 | AN97: 11.0753458564035 | AO97: 9.99198375522363 | AP97: 11.2359789946248 | AQ97: 11.7324774335856 | AR97: 11.6211732253369 | AS97: 11.5991975555663 | AT97: 10.1867211949273 | AU97: 11.3092285846433 | AV97: 12.0482151558632 | AW97: 10.184842378691 | AX97: 10.0650792583996 | AY97: 9.85230165386714 | AZ97: 9.75594317205468 | BA97: 9.52898492988282 | BB97: 10.9930534805853 | BC97: 10.5750130912526 | BD97: 10.6859790060702 | BE97: 9.72590000699412 | BF97: 9.27020682532407 | BG97: 9.18598040160867 | BH97: 8.96258333333333 | BI97: 8.635 | BJ97: 8.3125 | BK97: 7.835705 | BL97: 7.57102791666667 | BM97: 6.83319808333333 | BN97: 6.5453035 | BO97: 6.438381 | BP97: 6.9300195 | BQ97: 6.8868315
A98: Greenland | B98: GRL | C98: Lending interest rate (%) | D98: FR.INR.LEND
A99: Guatemala | B99: GTM | C99: Lending interest rate (%) | D99: FR.INR.LEND | AP99: 18.6375 | AQ99: 16.5641666666667 | AR99: 19.5116666666667 | AS99: 20.8816666666667 | AT99: 18.9575 | AU99: 16.8641666666667 | AV99: 14.9783333333333 | AW99: 13.8108333333333 | AX99: 13.0333333333333 | AY99: 12.7625 | AZ99: 12.8366666666667 | BA99: 13.3916666666667 | BB99: 13.8491666666667 | BC99: 13.3416666666667 | BD99: 13.43 | BE99: 13.4866666666667 | BF99: 13.5975 | BG99: 13.7733333333333 | BH99: 13.2275 | BI99: 13.1016666666667 | BJ99: 13.0541666666667 | BK99: 12.9233333333333 | BL99: 12.7408333333333 | BM99: 12.5258333333333 | BN99: 12.1875 | BO99: 11.9233333333333 | BP99: 11.9616666666667 | BQ99: 12.395
A100: Guam | B100: GUM | C100: Lending interest rate (%) | D100: FR.INR.LEND
A101: Guyana | B101: GUY | C101: Lending interest rate (%) | D101: FR.INR.LEND | Z101: 13.5 | AA101: 14.375 | AB101: 15 | AC101: 15 | AD101: 15 | AE101: 15 | AF101: 15 | AG101: 15.0691666666667 | AH101: 18.9375 | AI101: 32.75 | AJ101: 33.55 | AK101: 28.6875 | AL101: 19.3625 | AM101: 18.3608333333333 | AN101: 19.22 | AO101: 17.7933333333333 | AP101: 17.0441666666667 | AQ101: 16.7675 | AR101: 17.1083333333333 | AS101: 17.3016666666667 | AT101: 17.0075 | AU101: 16.325 | AV101: 14.9919047619048 | AW101: 14.5416666666667 | AX101: 14.5408333333333 | AY101: 14.5409722222222 | AZ101: 14.6108333333333 | BA101: 14.5825 | BB101: 14.5414083333333 | BC101: 14.5417 | BD101: 14.4514027777778 | BE101: 13.8611111111111 | BF101: 13.5 | BG101: 12.8333333333333 | BH101: 12.8333305555555 | BI101: 13 | BJ101: 13 | BK101: 13 | BL101: 10.4791666666667 | BM101: 9.46527777777779 | BN101: 8.875 | BO101: 8.41666666666667 | BP101: 8.375 | BQ101: 8.375
A102: High income | B102: HIC | C102: Lending interest rate (%) | D102: FR.INR.LEND
...

Sheet GDP deflator
A1: Data Source | B1: World Development Indicators | C1: Column1 | D1: _1 | E1: _2 | F1: _3 | G1: _4 | H1: _5 | I1: _6 | J1: _7 | K1: _8 | L1: _9 | M1: _10 | N1: _11 | O1: _12 | P1: _13 | Q1: _14 | R1: _15 | S1: _16 | T1: _17 | U1: _18 | V1: _19 | W1: _20 | X1: _21 | Y1: _22 | Z1: _23 | AA1: _24 | AB1: _25 | AC1: _26 | AD1: _27 | AE1: _28 | AF1: _29 | AG1: _30 | AH1: _31 | AI1: _32 | AJ1: _33 | AK1: _34 | AL1: _35 | AM1: _36 | AN1: _37 | AO1: _38 | AP1: _39 | AQ1: _40 | AR1: _41 | AS1: _42 | AT1: _43 | AU1: _44 | AV1: _45 | AW1: _46 | AX1: _47 | AY1: _48 | AZ1: _49 | BA1: _50 | BB1: _51 | BC1: _52 | BD1: _53 | BE1: _54 | BF1: _55 | BG1: _56 | BH1: _57 | BI1: _58 | BJ1: _59 | BK1: _60 | BL1: _61 | BM1: _62 | BN1: _63 | BO1: _64 | BP1: _65 | BQ1: _66 | BR1: _67
A3: Last Updated Date | B3: 2025-04-15
A5: Country Name | B5: Country Code | C5: Indicator Name | D5: Indicator Code | E5: 1960 | F5: 1961 | G5: 1962 | H5: 1963 | I5: 1964 | J5: 1965 | K5: 1966 | L5: 1967 | M5: 1968 | N5: 1969 | O5: 1970 | P5: 1971 | Q5: 1972 | R5: 1973 | S5: 1974 | T5: 1975 | U5: 1976 | V5: 1977 | W5: 1978 | X5: 1979 | Y5: 1980 | Z5: 1981 | AA5: 1982 | AB5: 1983 | AC5: 1984 | AD5: 1985 | AE5: 1986 | AF5: 1987 | AG5: 1988 | AH5: 1989 | AI5: 1990 | AJ5: 1991 | AK5: 1992 | AL5: 1993 | AM5: 1994 | AN5: 1995 | AO5: 1996 | AP5: 1997 | AQ5: 1998 | AR5: 1999 | AS5: 2000 | AT5: 2001 | AU5: 2002 | AV5: 2003 | AW5: 2004 | AX5: 2005 | AY5: 2006 | AZ5: 2007 | BA5: 2008 | BB5: 2009 | BC5: 2010 | BD5: 2011 | BE5: 2012 | BF5: 2013 | BG5: 2014 | BH5: 2015 | BI5: 2016 | BJ5: 2017 | BK5: 2018 | BL5: 2019 | BM5: 2020 | BN5: 2021 | BO5: 2022 | BP5: 2023 | BQ5: 2024
A6: Aruba | B6: ABW | C6: Inflation, GDP deflator (annual %) | D6: NY.GDP.DEFL.KD.ZG | AF6: 3.59197006652872 | AG6: 3.10843918798423 | AH6: 3.96254301358969 | AI6: 5.76986990784422 | AJ6: 5.61485982807162 | AK6: 3.82233511678332 | AL6: 5.30031405765243 | AM6: 6.28797536126895 | AN6: 3.37583749127457 | AO6: 3.25948642303557 | AP6: 3.70423775271973 | AQ6: 6.59295050184228 | AR6: 2.19006066092493 | AS6: 1.03610080269524 | AT6: -2.83550241253081 | AU6: 4.43468813342022 | AV6: 3.04904620110997 | AW6: 2.80990970893053 | AX6: 5.06749722968669 | AY6: 3.48434619543613 | AZ6: 5.16689296887391 | BA6: 4.26244900176589 | BB6: 1.70328044813839 | BC6: -1.22340655068425 | BD6: 4.00567421402882 | BE6: 0.184032701346126 | BF6: -1.99594849465619 | BG6: 3.95889741019282 | BH6: 6.831286936157 | BI6: -1.00279969703662 | BJ6: -3.17816679833555 | BK6: 3.46202953211427 | BL6: 6.01781611792313 | BM6: -0.951473042327038 | BN6: -4.91262490390014 | BO6: 3.15727939363973 | BP6: 6.70946117676064
A7: Africa Eastern and Southern | B7: AFE | C7: Inflation, GDP deflator (annual %) | D7: NY.GDP.DEFL.KD.ZG | F7: 1.93394654573322 | G7: 0.596607181612448 | H7: 3.15005277433804 | I7: 3.72697762199365 | J7: 2.96282610936504 | K7: 3.44451810994963 | L7: 1.7793841509497 | M7: 3.22709425782465 | N7: 4.66069284074154 | O7: 4.9375235930307 | P7: 3.27935307157383 | Q7: 9.8145760348434 | R7: 12.2244748984293 | S7: 15.1283461204314 | T7: 11.884430878284 | U7: 9.53063246851585 | V7: 10.4081011819644 | W7: 10.5402897346018 | X7: 14.5712374011675 | Y7: 19.2052947603321 | Z7: 10.8584883691295 | AA7: 7.69747177812898 | AB7: 11.5568417169857 | AC7: 12.7347557716885 | AD7: 16.1443312605572 | AE7: 13.9165769085523 | AF7: 12.6940698241788 | AG7: 20.1526012665392 | AH7: 14.8392839136103 | AI7: 11.9939039075081 | AJ7: 14.9789364246749 | AK7: 14.6406552101884 | AL7: 13.8705025913749 | AM7: 17.0164147872542 | AN7: 16.1027117424962 | AO7: 15.1761803358905 | AP7: 10.5450486551459 | AQ7: 9.10917293901807 | AR7: 8.00681329656179 | AS7: 11.1173058824862 | AT7: 8.31282499951298 | AU7: 8.91492825674993 | AV7: 7.8067408729751 | AW7: 9.60039256006742 | AX7: 7.62368935878268 | AY7: 7.65225430526529 | AZ7: 8.24576476611674 | BA7: 10.961412407556 | BB7: 8.28143239119243 | BC7: 5.88302203486953 | BD7: 9.74570998523772 | BE7: 6.20387787625781 | BF7: 5.54626698664435 | BG7: 5.40353538297499 | BH7: 5.63628010156222 | BI7: 6.73515766010987 | BJ7: 6.28646467124097 | BK7: 4.32175867770079 | BL7: 4.44437946494116 | BM7: 5.29813226108107 | BN7: 6.22269912307469 | BO7: 9.35876732357862 | BP7: 7.80122989057329
A8: Afghanistan | B8: AFG | C8: Inflation, GDP deflator (annual %) | D8: NY.GDP.DEFL.KD.ZG | AT8: -11.7745360319214 | AU8: 6.12552202910163 | AV8: 11.655238221181 | AW8: 11.2714320572149 | AX8: 10.9127735503048 | AY8: 7.19975129292388 | AZ8: 22.5277562007029 | BA8: 2.09628875042125 | BB8: -2.16340442746143 | BC8: 3.81463031545211 | BD8: 16.5933467401627 | BE8: 7.30175646760432 | BF8: 4.82278547876986 | BG8: 0.56694454253261 | BH8: 2.44756300147404 | BI8: -2.19752646733461 | BJ8: 2.40365618765746 | BK8: 2.07134857783487 | BL8: 6.52147984832531 | BM8: 6.9629462552564 | BN8: 2.83899625081041 | BO8: 9.40623933931322 | BP8: 2.9616535410169
A9: Africa Western and Central | B9: AFW | C9: Inflation, GDP deflator (annual %) | D9: NY.GDP.DEFL.KD.ZG | F9: 3.2784459977796 | G9: 2.48595550659368 | H9: 2.78147914636031 | I9: 3.38106058115134 | J9: 2.40502608843418 | K9: 4.13875253122386 | L9: 1.22775183399891 | M9: 1.62794933529348 | N9: 4.21395854238489 | O9: 3.35065176133496 | P9: 4.18919648768647 | Q9: 5.14581076875683 | R9: 7.61859793514425 | S9: 13.4225905212845 | T9: 8.58680753081824 | U9: 11.3197643284874 | V9: 10.8719879924003 | W9: 6.61649466282473 | X9: 10.7617886745716 | Y9: 11.0012811184527 | Z9: 10.0100209420354 | AA9: 13.8205590460171 | AB9: 9.92793639904325 | AC9: 11.3150500363978 | AD9: 5.29721350623177 | AE9: 0.32606411260803 | AF9: 2.35651163978966 | AG9: 3.69277055172387 | AH9: 3.50011875843632 | AI9: 4.82244315622001 | AJ9: 3.31280575359608 | AK9: 0.482938222012713 | AL9: 2.80670798967146 | AM9: 24.7941952455716 | AN9: 7.39692068899853 | AO9: 6.18642809934072 | AP9: 2.96013877018802 | AQ9: 5.30948306910901 | AR9: 4.50109730901824 | AS9: 4.815430261735 | AT9: 3.86179519283827 | AU9: 2.67339738740157 | AV9: 1.71882163202884 | AW9: 5.68195133906449 | AX9: 6.68893394853546 | AY9: 4.64332213979795 | AZ9: 5.47702898238883 | BA9: 9.11699967289589 | BB9: 1.48940469185958 | BC9: 5.42967319163332 | BD9: 8.51666048093151 | BE9: 4.73009483577319 | BF9: 1.55401804889429 | BG9: 0.731853329618588 | BH9: 1.91155941571227 | BI9: 1.736323129284 | BJ9: 1.75910578032053 | BK9: 2.15033893298982 | BL9: 1.95694728078307 | BM9: 1.71555846208987 | BN9: 4.64220371005912 | BO9: 6.58712256843671 | BP9: 3.38669113752862
A10: Angola | B10: AGO | C10: Inflation, GDP deflator (annual %) | D10: NY.GDP.DEFL.KD.ZG | Z10: -2.1003061669614 | AA10: 0 | AB10: 0.0127635583866379 | AC10: 0.0011881098994877 | AD10: 19.0352057407944 | AE10: -9.01306191994358 | AF10: 9.8233113499663 | AG10: 2.21377444948736 | AH10: 16.2796626853837 | AI10: 14.0074398272592 | AJ10: 106.309982268478 | AK10: 476.51575086326 | AL10: 917.783468411763 | AM10: 2175.97895508759 | AN10: 1825.49514900731 | AO10: 4800.53164415744 | AP10: 95.4530221791129 | AQ10: 39.3593483252693 | AR10: 557.501113091215 | AS10: 418.018991534099 | AT10: 106.352125501451 | AU10: 196.984099399931 | AV10: 93.9265669067308 | AW10: 33.4435947900255 | AX10: 42.3742492617284 | AY10: 17.1156651448542 | AZ10: 4.30843221207182 | BA10: 19.3657735558326 | BB10: -16.7621402901592 | BC10: 32.2704691224412 | BD10: 31.7714601558986 | BE10: 7.25574990943825 | BF10: 2.83972412637765 | BG10: 3.56088477205805 | BH10: -3.51838534598478 | BI10: 21.7742355863884 | BJ10: 22.6145140271114 | BK10: 28.1670932554891 | BL10: 19.1870038271785 | BM10: 10.7631052824799 | BN10: 38.8237218374918 | BO10: 13.7105940226231 | BP10: 17.6195377226942
A11: Albania | B11: ALB | C11: Inflation, GDP deflator (annual %) | D11: NY.GDP.DEFL.KD.ZG | Z11: -2.13957198618188 | AA11: -0.0177190996205354 | AB11: -0.0167551716364898 | AC11: -0.0283602576437829 | AD11: 0.35122234783789 | AE11: -2.41730042881588 | AF11: -0.000306092920837386 | AG11: -0.00057857927218663 | AH11: 0.0036791601611128 | AI11: -0.431368812605911 | AJ11: 35.5142469575829 | AK11: 232.984658866956 | AL11: 125.650814219817 | AM11: 35.8424752083078 | AN11: 9.9706626786687 | AO11: 38.1720581994814 | AP11: 11.2396444802125 | AQ11: 6.73085990507577 | AR11: 2.10284998886902 | AS11: 5.6474714679938 | AT11: 3.81085737408868 | AU11: 3.6474762708812 | AV11: 5.19863530307683 | AW11: 3.15236892537025 | AX11: 3.30681814689954 | AY11: 2.47818888688769 | AZ11: 4.3867093833438 | BA11: 4.11708542559394 | BB11: 2.41833605890835 | BC11: 4.49314320031891 | BD11: 2.31474379699794 | BE11: 1.04271460643407 | BF11: 0.288745964127756 | BG11: 1.54991706986272 | BH11: 0.563991350160876 | BI11: -0.632653419095547 | BJ11: 1.45073158124514 | BK11: 2.9665236560994 | BL11: 1.00059083830071 | BM11: 0.0410649973272115 | BN11: 3.44439880912799 | BO11: 9.86157415467682 | BP11: 6.06604947510885
A12: Andorra | B12: AND | C12: Inflation, GDP deflator (annual %) | D12: NY.GDP.DEFL.KD.ZG | P12: 7.84587099758265 | Q12: 8.51807767365098 | R12: 11.8494338124947 | S12: 15.9452014096622 | T12: 16.7817953953987 | U12: 16.4898572074663 | V12: 23.3830925555267 | W12: 20.63104141592 | X12: 16.9316890399132 | Y12: 13.3548138413184 | Z12: 12.3511731944832 | AA12: 13.5823498012472 | AB12: 11.8842353012303 | AC12: 10.8647343940798 | AD12: 8.59546375926088 | AE12: 10.8788152026056 | AF12: 5.94419881956037 | AG12: 5.9361249975981 | AH12: 6.89620711872611 | AI12: 7.32624369631456 | AJ12: 6.93514835426407 | AK12: 6.71076896051142 | AL12: 4.53723214675858 | AM12: 3.87985832158631 | AN12: 4.93312104936552 | AO12: 0.797177729321263 | AP12: 2.22816030666122 | AQ12: 1.49955384331271 | AR12: 2.73197952535102 | AS12: 28.7415528975991 | AT12: 3.08053517916559 | AU12: 3.23953176987777 | AV12: 3.17748421556476 | AW12: 3.04242399802695 | AX12: 3.39610212995052 | AY12: 3.45718408670396 | AZ12: 3.21122734131436 | BA12: 2.27433831984322 | BB12: 0.132136132405464 | BC12: 0.374313758110119 | BD12: 0.196764152031051 | BE12: 0.174556905779482 | BF12: 0.448492200194735 | BG12: -0.0840193165570753 | BH12: 0.660588959137868 | BI12: 0.347795381575793 | BJ12: 1.13650934319639 | BK12: 1.01247848005298 | BL12: 1.37475350829189 | BM12: 1.11378607410401 | BN12: 2.5588606935971 | BO12: 4.23665226454663 | BP12: 6.29560082401824
A13: Arab World | B13: ARB | C13: Inflation, GDP deflator (annual %) | D13: NY.GDP.DEFL.KD.ZG | G13: 2.01537452545222 | H13: 3.29617204048303 | I13: 3.19390148594043 | J13: -0.440429932829574 | K13: 2.75119762106486 | L13: 2.38960219490593 | M13: 2.75484922141703 | N13: 1.06482414619676 | O13: 3.91033373750788 | P13: 7.35709355603809 | Q13: 3.14290859280182 | R13: 15.2464081259903 | S13: 34.6065505598652 | T13: 5.59914413260866 | U13: 8.62978218612457 | V13: 10.3700771762441 | W13: 4.16049327419121 | X13: 19.271855817196 | Y13: 24.1580815878628 | Z13: 10.2466291101412 | AA13: 6.36523697789958 | AB13: 6.88749696075298 | AC13: 6.18040856863473 | AD13: 4.23208188574494 | AE13: 2.96400555028724 | AF13: 9.36808989082694 | AG13: 4.17732530004293 | AH13: 7.97612484555617 | AI13: 12.7463177181753 | AJ13: 7.44099981033727 | AK13: 5.716743758978 | AL13: 3.86316291751921 | AM13: 7.60245225222921 | AN13: 7.76719774306125 | AO13: 6.65755753090085 | AP13: 2.75712224933042 | AQ13: -3.13108869741967 | AR13: 8.44337746020058 | AS13: 11.4595357939894 | AT13: 1.86769984238948 | AU13: 3.77083954826043 | AV13: 5.11182917627502 | AW13: 10.9375405233887 | AX13: 14.5852590982142 | AY13: 9.09650632380644 | AZ13: 8.04658597487651 | BA13: 15.9501259770903 | BB13: -2.78022303939403 | BC13: 12.0069506981357 | BD13: 13.1672193765795 | BE13: 4.67972511760814 | BF13: 1.26026248256035 | BG13: 1.04867463772903 | BH13: -2.11493646984442 | BI13: 0.920589535113145 | BJ13: 4.8259464942787 | BK13: 7.04467101748188 | BL13: 2.3662310647694 | BM13: 0.406043178192824 | BN13: 12.7208752145056 | BO13: 14.8098061189166 | BP13: 0.854841037372282
A14: United Arab Emirates | B14: ARE | C14: Inflation, GDP deflator (annual %) | D14: NY.GDP.DEFL.KD.ZG | P14: 7.09843561708112E-09 | Q14: 3.50932793935499E-09 | R14: 54.2528269904672 | S14: 138.263492562272 | T14: 19.0009160013165 | U14: 11.7743313548719 | V14: 5.25575609116014 | W14: -3.66111149549619 | X14: 7.05102054464086 | Y14: 9.51597603461369 | Z14: 7.054483982438 | AA14: 1.31286872874293 | AB14: -3.61801721863773 | AC14: -6.09746718626482 | AD14: 0.740532889918782 | AE14: -1.69848529731705 | AF14: 3.685584802515 | AG14: 2.38104573161 | AH14: 1.75127660948431 | AI14: 3.33590049400134 | AJ14: 0.810848722776853 | AK14: 1.80682612323693 | AL14: 1.27803631115864 | AM14: -0.262474925014473 | AN14: 3.90747975797208 | AO14: 5.77304389866605 | AP14: -0.952300713494253 | AQ14: -4.25444531455858 | AR14: 8.44337746020058 | AS14: 11.4595357939894 | AT14: -2.34930767820795 | AU14: 3.77083954826043 | AV14: 4.07240679733007 | AW14: 8.50142205885294 | AX14: 16.5263069327845 | AY14: 11.9621492865846 | AZ14: 12.5339606714946 | BA14: 18.5333530849246 | BB14: -15.1829798865339 | BC14: 16.5278863640702 | BD14: 13.1672193765795 | BE14: 4.67972511760814 | BF14: -0.94932531950414 | BG14: -0.668049355939203 | BH14: -16.2670060316676 | BI14: -5.52947860546242 | BJ14: 4.98621314114183 | BK14: 7.93674803487896 | BL14: -3.19440940863002 | BM14: -12.0313052945464 | BN14: 13.8437703394455 | BO14: 12.6298936875673 | BP14: -1.30420016236501
A15: Argentina | B15: ARG | C15: Inflation, GDP deflator (annual %) | D15: NY.GDP.DEFL.KD.ZG | F15: 20.3106975290508 | G15: 28.8718416496811 | H15: 25.5911543466798 | I15: 28.7746173194355 | J15: 21.2329349264853 | K15: 25.603462425178 | L15: 29.0182629355813 | M15: 10.2753105598205 | N15: 7.79583003393792 | O15: 6.46787463920629 | P15: 31.2710638842292 | Q15: 64.2447859149364 | R15: 65.535287370144 | S15: 30.630441370412 | T15: 197.697364543187 | U15: 438.322779739816 | V15: 159.42717769645 | W15: 161.372172004157 | X15: 147.377044034473 | Y15: 95.7904246128352 | Z15: 105.276366380064 | AA15: 194.535299663443 | AB15: 380.158528521919 | AC15: 611.196303891913 | AD15: 607.447497830085 | AE15: 77.2922366864133 | AF15: 127.539918059086 | AG15: 381.24634440952 | AH15: 3046.09115201119 | AI15: 2078.31681806978 | AJ15: 140.502378661012 | AK15: 16.0719935356945 | AL15: -3.56109557576575 | AM15: 2.84933971509302 | AN15: 3.16512339016516 | AO15: -0.0523754965904146 | AP15: -0.46391313116429 | AQ15: -1.70527962400085 | AR15: -1.83655839220664 | AS15: 1.03728710073175 | AT15: -1.09576771833679 | AU15: 30.555204053903 | AV15: 10.4957030215496 | AW15: 18.3633542492033 | AX15: 10.3175111982406 | AY15: 13.7410524859152 | AZ15: 14.9399250245835 | BA15: 23.1711649813124 | BB15: 15.3776493708921 | BC15: 20.915124272047 | BD15: 23.7034721839593 | BE15: 22.3148806733049 | BF15: 23.9487984162746 | BG15: 40.2829716315506 | BH15: 26.5799916024707 | BI15: 41.1193799882279 | BJ15: 26.0063792819079 | BK15: 42.0336689575031 | BL15: 49.1955790596612 | BM15: 40.0830878011993 | BN15: 53.8020877665554 | BO15: 69.8760842459268 | BP15: 135.368876310592
A16: Armenia | B16: ARM | C16: Inflation, GDP deflator (annual %) | D16: NY.GDP.DEFL.KD.ZG | AJ16: 79.386104296155 | AK16: 568.807295439343 | AL16: 1391.16654315168 | AM16: 4107.29676994743 | AN16: 161.163917579159 | AO16: 19.5917703052133 | AP16: 17.7359944945837 | AQ16: 10.6984977562983 | AR16: 0.0538040809325366 | AS16: -1.37367599828147 | AT16: 4.02796948177824 | AU16: 2.35739901911141 | AV16: 4.5985157283794 | AW16: 6.27859410767147 | AX16: 3.20875666635281 | AY16: 4.61801250818827 | AZ16: 4.2778755387818 | BA16: 5.98956236068734 | BB16: 2.49725307891563 | BC16: 7.76871548067652 | BD16: 4.28154999826118 | BE16: 5.34580441814725 | BF16: 3.36682464224465 | BG16: 2.30918242990974 | BH16: 1.21390990471085 | BI16: 0.268575076501392 | BJ16: 2.15064189848613 | BK16: 2.78770951425761 | BL16: 1.06562263923419 | BM16: 1.80659270159933 | BN16: 6.90051365787157 | BO16: 7.98587852828175 | BP16: 2.67300354889213
A17: American Samoa | B17: ASM | C17: Inflation, GDP deflator (annual %) | D17: NY.GDP.DEFL.KD.ZG | AV17: 1.36505293715847 | AW17: -3.25907462221531 | AX17: -1.36558343263874 | AY17: 2.81367521367521 | AZ17: 3.16061220726536 | BA17: 11.0593351972663 | BB17: 25.776397515528 | BC17: -15.3648895532304 | BD17: -0.52356020942409 | BE17: 17.3684210526316 | BF17: 2.24358974358974 | BG17: -0.962160294226521 | BH17: 1.4697327650683 | BI17: 1.40582171236608 | BJ17: -1.94089005769675 | BK17: 1.69536107125778 | BL17: 1.74828930007058 | BM17: 6.72878072142282 | BN17: 4.8425556863277 | BO17: 14.1527648578811
A18: Antigua and Barbuda | B18: ATG | C18: Inflation, GDP deflator (annual %) | D18: NY.GDP.DEFL.KD.ZG | W18: 8.82645062612013 | X18: 15.1750067607584 | Y18: 11.7375182480628 | Z18: 8.64343267249721 | AA18: 11.5067195282661 | AB18: 5.41509007725438 | AC18: 4.20075189943394 | AD18: 7.85084492490826 | AE18: 8.32931416017392 | AF18: 9.32656261851652 | AG18: 12.7288317145654 | AH18: 5.11981109118966 | AI18: 2.09841051655768 | AJ18: 3.10653747347762 | AK18: 2.93123372538055 | AL18: 2.31585364144694 | AM18: 3.58924100547307 | AN18: 3.0463687910141 | AO18: 3.41240765944926 | AP18: 2.53062058558473 | AQ18: 2.68151672210762 | AR18: 2.01084703483052 | AS18: 1.48825220695463 | AT18: 2.08478316538981 | AU18: 1.29268465711701 | AV18: -0.483244128267359 | AW18: 2.34982330100517 | AX18: 4.67677680492626 | AY18: 1.12406956736658 | AZ18: 4.37354365910269 | BA18: 4.73737157423442 | BB18: 1.11082507238632 | BC18: 1.60551428909972 | BD18: 0.668645512053459 | BE18: 0.192742785601624 | BF18: 0.476877446195644 | BG18: 1.77839219993881 | BH18: 2.78817037438111 | BI18: -0.468201309637678 | BJ18: 0.312054499370376 | BK18: 1.46029012290431 | BL18: 0.718452311457611 | BM18: 0.800069551909715 | BN18: 4.91376057826946 | BO18: 6.49885619566375 | BP18: 4.80547577274675
A19: Australia | B19: AUS | C19: Inflation, GDP deflator (annual %) | D19: NY.GDP.DEFL.KD.ZG | F19: 3.22196795615888 | G19: -0.0756038248018314 | H19: 1.78993098902399 | I19: 3.2830542276814 | J19: 2.98448250378847 | K19: 2.68348009513745 | L19: 4.86368073064634 | M19: 2.25264476451015 | N19: 4.75630153684699 | O19: 5.13233864241059 | P19: 5.18608376438183 | Q19: 6.18861390811001 | R19: 8.9839737566421 | S19: 16.3775623167018 | T19: 16.4897877086073 | U19: 14.0198687822264 | V19: 11.4186605819591 | W19: 8.23618363096672 | X19: 8.63443123752833 | Y19: 10.0165696784018 | Z19: 9.52478964604649 | AA19: 11.7092329249508 | AB19: 10.1575581386061 | AC19: 7.86300441854821 | AD19: 4.68070643690324 | AE19: 6.54751099766295 | AF19: 7.03173832337612 | AG19: 7.1742599600064 | AH19: 9.23190922376165 | AI19: 6.09458983592408 | AJ19: 3.02017557973888 | AK19: 1.47902574629622 | AL19: 0.867377619434805 | AM19: 1.01880233824261 | AN19: 2.28914316458206 | AO19: 2.71144222672184 | AP19: 1.27279080728206 | AQ19: 1.13564190464284 | AR19: 0.475365976445929 | AS19: 2.5507652827131 | AT19: 4.63074057685395 | AU19: 2.84035444214652 | AV19: 2.98554508941196 | AW19: 3.23229936195307 | AX19: 3.82548066795754 | AY19: 5.11533977799769 | AZ19: 4.98605173231132 | BA19: 4.56978290693471 | BB19: 4.94917908012782 | BC19: 1.15377249328591 | BD19: 6.20197668065047 | BE19: 1.8056989221342 | BF19: -0.163600551424906 | BG19: 1.40539601622476 | BH19: -0.623858470510584 | BI19: -0.663157619625991 | BJ19: 3.65318441813451 | BK19: 1.86901478899458 | BL19: 3.46820261012924 | BM19: 1.88550119010648 | BN19: 3.0799498600023 | BO19: 7.17553361510235 | BP19: 6.51199894950456
A20: Austria | B20: AUT | C20: Inflation, GDP deflator (annual %) | D20: NY.GDP.DEFL.KD.ZG | F20: 5.08715371682054 | G20: 3.34020321438598 | H20: 3.67826612051927 | I20: 3.18378821910466 | J20: 5.32141544871361 | K20: 3.12236608115563 | L20: 3.24776256800851 | M20: 2.83803195138866 | N20: 2.73357287683751 | O20: 4.74209753751786 | P20: 6.20437307255557 | Q20: 7.59993178976686 | R20: 8.04554335193663 | S20: 9.50213933746554 | T20: 6.45777551561679 | U20: 5.62491786511249 | V20: 5.19871332953932 | W20: 5.99301610369258 | X20: 4.11437045422589 | Y20: 5.58062878744539 | Z20: 6.71666844180592 | AA20: 5.35528990224338 | AB20: 3.47278360488259 | AC20: 4.94977305907392 | AD20: 2.96299586752589 | AE20: 2.95099747866612 | AF20: 2.43694807558032 | AG20: 1.52685492085918 | AH20: 2.9647607154772 | AI20: 2.99968065945104 | AJ20: 3.64187152255646 | AK20: 3.47909296982908 | AL20: 2.75708451946717 | AM20: 2.52494309684019 | AN20: 1.81391843002299 | AO20: 0.960435623684603 | AP20: 1.26254419605465 | AQ20: 0.482061857743417 | AR20: 0.219322650024296 | AS20: 1.36731401336769 | AT20: 1.93728367228805 | AU20: 1.10421508890414 | AV20: 1.26700272386712 | AW20: 1.72796220966988 | AX20: 2.53196772218678 | AY20: 2.04461988969157 | AZ20: 2.2592709576015 | BA20: 1.93379073721434 | BB20: 1.73939285831332 | BC20: 0.891338457893553 | BD20: 1.81993753082695 | BE20: 2.09166482584344 | BF20: 1.70872300692841 | BG20: 2.00674390270015 | BH20: 2.29263492397251 | BI20: 1.81475079739224 | BJ20: 0.975317709275998 | BK20: 1.81048023343624 | BL20: 1.47368476959242 | BM20: 2.59313274910787 | BN20: 1.92612910926519 | BO20: 4.75477834804261 | BP20: 6.64765341628686
A21: Azerbaijan | B21: AZE | C21: Inflation, GDP deflator (annual %) | D21: NY.GDP.DEFL.KD.ZG | AJ21: 83.5495126683364 | AK21: 1065.32923018531 | AL21: 747.12452012683 | AM21: 1386.06739767987 | AN21: 545.656352266205 | AO21: 26.4191629382316 | AP21: 9.24250444099582 | AQ21: -0.96513336719066 | AR21: 2.16214167529371 | AS21: 12.4927738128452 | AT21: 2.51501022581932 | AU21: 4.21438623360075 | AV21: 6.96146570847378 | AW21: 9.25196510735844 | AX21: 14.7234965182528 | AY21: 11.3012191438311 | AZ21: 21.0293287543152 | BA21: 27.777459536561 | BB21: -18.8449572890202 | BC21: 13.5458167908374 | BD21: 22.524361140543 | BE21: 2.88293295403217 | BF21: 0.445064509020867 | BG21: -1.28499552026639 | BH21: -8.84969256895297 | BI21: 14.6714002511137 | BJ21: 16.1724003104411 | BK21: 12.1848769569655 | BL21: -0.241307927446329 | BM21: -7.39596582740913 | BN21: 21.5888241949245 | BO21: 37.2705611565603 | BP21: -9.20663944963042
A22: Burundi | B22: BDI | C22: Inflation, GDP deflator (annual %) | D22: NY.GDP.DEFL.KD.ZG | F22: 20.0774363431424 | G22: -3.56741645307069 | H22: 4.68714930026979 | I22: 5.4172175752595 | J22: -1.02936377839632 | K22: 3.15203396174695 | L22: -5.31798617192774 | M22: 3.05681315002275 | N22: 5.36187983493693 | O22: 5.18451180666659 | P22: 1.38021894639897 | Q22: 4.29080997127038 | R22: 5.51044247050103 | S22: 12.4551776403177 | T22: 21.0869057883016 | U22: 8.0749482461168 | V22: 14.3041256060103 | W22: 12.5077052224577 | X22: 26.1307076116281 | Y22: 16.3840243620867 | Z22: -6.0633150865134 | AA22: 5.67202154795532 | AB22: 6.4285488030003 | AC22: 17.2161949890367 | AD22: 5.06883898015293 | AE22: -4.25741423815771 | AF22: -3.41779507858824 | AG22: 3.49122270126601 | AH22: 14.7571848169704 | AI22: 5.98556154520156 | AJ22: 4.09314079275475 | AK22: 5.40176069954681 | AL22: 7.74264567579905 | AM22: 6.63844545647953 | AN22: 16.1027117424962 | AO22: 14.4531114060499 | AP22: 32.3977892307747 | AQ22: 11.4505560048054 | AR22: 14.9541402608853 | AS22: 38.9448932030909 | AT22: 13.7164067920133 | AU22: 1.02785857373888 | AV22: 11.9457486448591 | AW22: 13.1461593314354 | AX22: 18.8415894769233 | AY22: 2.84566633376673 | AZ22: 8.27337562886336 | BA22: 24.2157937434401 | BB22: 10.4587965254196 | BC22: 8.56155516425477 | BD22: 8.36425019828808 | BE22: 14.294071682425 | BF22: 7.9531039994456 | BG22: 5.30565602774391 | BH22: 21.3187470230149 | BI22: 0.97317644189674 | BJ22: 11.4491826066034 | BK22: -2.85085930198137 | BL22: 0.851867434051655 | BM22: 5.9665023314011 | BN22: 8.51671971494707 | BO22: 18.3317223148693 | BP22: 11.3760314899613
A23: Belgium | B23: BEL | C23: Inflation, GDP deflator (annual %) | D23: NY.GDP.DEFL.KD.ZG | F23: 1.31546869427677 | G23: 1.66769194647161 | H23: 3.02579670028393 | I23: 4.64242655848656 | J23: 5.10071293696193 | K23: 4.08601493307428 | L23: 3.19343093712614 | M23: 2.62028927660216 | N23: 4.02382631115445 | O23: 4.54619573897246 | P23: 5.35821760989761 | Q23: 6.31781973169122 | R23: 6.80698646513234 | S23: 12.1683398872165 | T23: 12.8897229515416 | U23: 7.57526346822965 | V23: 7.47805988572962 | W23: 4.42325022360627 | X23: 4.50524106489813 | Y23: 4.12659694695165 | Z23: 5.13919687490983 | AA23: 7.57041621451407 | AB23: 5.6128505058284 | AC23: 5.43871721514574 | AD23: 4.62774245535957 | AE23: 2.79678045159528 | AF23: 1.68411135983652 | AG23: 2.16898958166314 | AH23: 4.79745782559817 | AI23: 2.81240338876658 | AJ23: 2.87662434854509 | AK23: 3.42452490217883 | AL23: 3.99323167580741 | AM23: 2.09430476426498 | AN23: 1.22076972852592 | AO23: 0.476638129958133 | AP23: 0.75761089644017 | AQ23: 1.80561954635252 | AR23: 0.598922412877229 | AS23: 2.01459203440002 | AT23: 1.98281815411856 | AU23: 1.63999827941501 | AV23: 1.85011616570733 | AW23: 1.91498852327605 | AX23: 2.08307330437046 | AY23: 2.26471638352143 | AZ23: 1.9316781494056 | BA23: 1.90886955920959 | BB23: 0.781821008464917 | BC23: 1.70310453341449 | BD23: 2.29252176896657 | BE23: 2.20573636168733 | BF23: 1.41248972600334 | BG23: 0.840395739536802 | BH23: 1.12183847077587 | BI23: 1.89528922644591 | BJ23: 1.98316339488014 | BK23: 1.71728226802716 | BL23: 1.85424074414335 | BM23: 1.59611666393067 | BN23: 2.7426355945688 | BO23: 6.84397975156924 | BP23: 4.508102848783
A24: Benin | B24: BEN | C24: Inflation, GDP deflator (annual %) | D24: NY.GDP.DEFL.KD.ZG | F24: 1.04143567396571 | G24: 3.7805611339427 | H24: 2.54904113694245 | I24: -0.363671991954803 | J24: 2.05762046368159 | K24: 1.13666559901029 | L24: 0.141072430094951 | M24: 3.27352495312587 | N24: 3.4541955241058 | O24: 5.04704693755775 | P24: 1.57328377262995 | Q24: 5.31722607727731 | R24: 4.82273994136393 | S24: 14.9207099075904 | T24: 14.2469357612696 | U24: 14.0354300183818 | V24: 5.17688681033776 | W24: 12.3344589560374 | X24: 13.0046858245988 | Y24: 10.1878198573196 | Z24: 7.4689482651344 | AA24: 16.148284015281 | AB24: 4.74620974295648 | AC24: 1.95358095750957 | AD24: -4.8769817363666 | AE24: -3.6041725823892 | AF24: 3.02845985259779 | AG24: -0.610506907481181 | AH24: 2.2249344566343 | AI24: 2.17659692554506 | AJ24: 0.756620150311463 | AK24: 3.0251344649124 | AL24: 2.37832182418319 | AM24: 35.0301127836754 | AN24: 15.0994519080227 | AO24: 6.90729366487193 | AP24: 3.66750917412438 | AQ24: 5.23160474756106 | AR24: 48.3425433908146 | AS24: 4.3410556635676 | AT24: 1.97028558167254 | AU24: 3.55421325456054 | AV24: 3.06170412441227 | AW24: 0.769711003809874 | AX24: 4.29366413526147 | AY24: 2.09431707279076 | AZ24: 0.390153238195737 | BA24: 6.43415220578032 | BB24: 2.53969206095486 | BC24: 0.880885670477909 | BD24: 3.73308304042652 | BE24: 7.69890807691425 | BF24: 1.39729839455183 | BG24: -0.247782653882282 | BH24: 0.85150426118021 | BI24: 0.683591111274652 | BJ24: -0.367897725119164 | BK24: 0.670447614217636 | BL24: -0.39755379308734 | BM24: 2.87803228859791 | BN24: 1.61872506665755 | BO24: 4.13878000011482 | BP24: 3.38546435195668
A25: Burkina Faso | B25: BFA | C25: Inflation, GDP deflator (annual %) | D25: NY.GDP.DEFL.KD.ZG | F25: 1.90060824059779 | G25: 2.01037157042501 | H25: 5.14752475383766 | I25: 1.8122165810679 | J25: -0.656072018182812 | K25: 2.30311694399366 | L25: -4.41100840434797 | M25: -0.263878695591529 | N25: 6.91315419325167 | O25: 1.78342721857652 | P25: 3.37747532556914 | Q25: 7.29664525500058 | R25: 2.67785896654267 | S25: 11.0147093853435 | T25: 8.1761559668212 | U25: 6.72550567482627 | V25: 18.6619763309535 | W25: 14.5323255016216 | X25: 7.7535255123222 | Y25: 8.69436852095804 | Z25: 13.584619381945 | AA25: 9.0465164203043 | AB25: 5.40931696202939 | AC25: 6.50108528918713 | AD25: 0.757066710315698 | AE25: -6.34567686458379 | AF25: 1.23732316838962 | AG25: 3.40855660018133 | AH25: 4.83162041216929 | AI25: 1.81001541960049 | AJ25: -3.96778074755804 | AK25: 0.227059619996879 | AL25: -1.44183978328999 | AM25: 14.6389618841227 | AN25: 6.76956903796038 | AO25: 0.348705151128442 | AP25: 1.55619984983713 | AQ25: 7.94031603070835 | AR25: 17.3908245064623 | AS25: -0.819773185220825 | AT25: 3.96155291715017 | AU25: 3.05698609068348 | AV25: 1.48472881492427 | AW25: 0.0906485898375564 | AX25: 3.73938539728054 | AY25: -0.662826822466556 | AZ25: 2.49234918341701 | BA25: 9.15980043749074 | BB25: 2.40550487042772 | BC25: 3.77961872815705 | BD25: 6.73800480732596 | BE25: 5.82399948795916 | BF25: -2.12917117768745 | BG25: -0.620386925840478 | BH25: -2.22395417919314 | BI25: 2.60429919226561 | BJ25: 1.41629727998107 | BK25: 1.07396688968345 | BL25: 0.51290051556127 | BM25: 6.46559578788029 | BN25: 0.112863112943955 | BO25: 5.88896511236759 | BP25: 1.99804752407688
A26: Bangladesh | B26: BGD | C26: Inflation, GDP deflator (annual %) | D26: NY.GDP.DEFL.KD.ZG | F26: 6.25748157867088 | G26: 0.0222234958223737 | H26: 5.16405902184019 | I26: -8.74322462414321 | J26: 7.93170495657343 | K26: 6.29618883406606 | L26: 14.7919634515746 | M26: -5.7695843810757 | N26: 11.8277158013198 | O26: 0.510309048628059 | P26: 2.96325493220053 | Q26: 4.40201965202864 | R26: 61.4057832765998 | S26: 44.5427168978939 | T26: 80.5697564038071 | U26: -17.6304192925882 | V26: -3.21015592855957 | W26: 25.6188855872458 | X26: 12.5645059899639 | Y26: 17.55506709007 | Z26: 9.89469031190922 | AA26: 9.85581246334655 | AB26: 8.48775587837945 | AC26: 7.87556634908888 | AD26: 18.4951156996356 | AE26: 8.25440489427334 | AF26: 11.1196311686194 | AG26: 7.49583529710168 | AH26: 8.337973249846 | AI26: 6.53273529225868 | AJ26: 2.72953199538708 | AK26: 2.58216189991052 | AL26: 0.155518172723973 | AM26: 3.96621631555998 | AN26: 7.14493870340395 | AO26: 19.1432131128285 | AP26: 3.80023220091314 | AQ26: 4.73621256184072 | AR26: 3.78103773665002 | AS26: 3.44665934914798 | AT26: 3.26116013222439 | AU26: 3.8928674350377 | AV26: 5.81581664789621 | AW26: 4.5621363796936 | AX26: 4.58636070641845 | AY26: 5.87593581109938 | AZ26: 6.47126010502515 | BA26: 7.86096609394262 | BB26: 6.76435468091874 | BC26: 7.14466302810841 | BD26: 7.85945085272492 | BE26: 8.16457367624635 | BF26: 7.17495343232414 | BG26: 5.66878852513904 | BH26: 5.87277704102323 | BI26: 27.8507377248339 | BJ26: 5.04759758203714 | BK26: 5.80553876704575 | BL26: 3.65813755162172 | BM26: 3.84106338588026 | BN26: 4.1211747067957 | BO26: 5.04902187883131 | BP26: 6.89712404003441
A27: Bulgaria | B27: BGR | C27: Inflation, GDP deflator (annual %) | D27: NY.GDP.DEFL.KD.ZG | Z27: 2.82093836829875 | AA27: 1.9164728045925 | AB27: -0.645271729639816 | AC27: 2.73674849638195 | AD27: 0.229177128441023 | AE27: 1.34548961532425 | AF27: 0.0638388002034702 | AG27: -5.38974383656908 | AH27: 6.72968413426919 | AI27: 26.188000659147 | AJ27: 226.537859856257 | AK27: 59.5786493866892 | AL27: 51.0910538964772 | AM27: 72.7049682379487 | AN27: 135.955619033174 | AO27: 62.9662451838659 | AP27: 913.213096376198 | AQ27: 33.9510300748266 | AR27: 3.31913809004136 | AS27: 7.38083885101 | AT27: 6.11773237385735 | AU27: 3.84837869171173 | AV27: 2.18941082692299 | AW27: 5.58155791993171 | AX27: 6.59425897441935 | AY27: 6.75647490079174 | AZ27: 11.0514316831737 | BA27: 8.10345619465454 | BB27: 3.9380183620588 | BC27: 0.764129878916592 | BD27: 6.11283035981589 | BE27: 1.11217885256747 | BF27: 0.0719518095394278 | BG27: 1.34078287386647 | BH27: 2.94774648723617 | BI27: 3.32355920411145 | BJ27: 4.81312131224342 | BK27: 4.25525729817191 | BL27: 5.23548704810747 | BM27: 4.34103862385629 | BN27: 6.96662433933332 | BO27: 15.9183596891222 | BP27: 7.98419924336682
A28: Bahrain | B28: BHR | C28: Inflation, GDP deflator (annual %) | D28: NY.GDP.DEFL.KD.ZG | P28: 5.79964857386999 | Q28: 5.21139975174552 | R28: 13.9800997035499 | S28: 24.6854163593515 | T28: 15.9057993765104 | U28: 10.3223718714327 | V28: 11.2976030457294 | W28: 7.68712128208571 | X28: 13.5122278303138 | Y28: 24.1580815878628 | Z28: 18.9117650195847 | AA28: 13.723994141722 | AB28: -3.68996713845982 | AC28: -0.418480086865131 | AD28: -1.82499453259432 | AE28: -17.3926503148808 | AF28: 0.659048458704106 | AG28: 2.00942771420604 | AH28: 3.97466040979498 | AI28: 4.82669555236323 | AJ28: -1.88252400246994 | AK28: -3.53265287221519 | AL28: -3.02581476787157 | AM28: 7.33118744403285 | AN28: 1.09067017528857 | AO28: 0.196720000526128 | AP28: 0.931716358623348 | AQ28: -7.05741107773432 | AR28: 2.65643643982591 | AS28: 14.3225233904652 | AT28: -3.36382791997714 | AU28: 3.41434955563101 | AV28: 8.60258061783617 | AW28: 10.9910846225111 | AX28: 13.7349678263372 | AY28: 8.84243671557729 | AZ28: 8.43563269466976 | BA28: 11.3650919229748 | BB28: -12.9939412103814 | BC28: 12.0069506981357 | BD28: 9.48596325068939 | BE28: 2.93394725551211 | BF28: 0.499828956383851 | BG28: -1.44043683471969 | BH28: -8.75667340246945 | BI28: 0.35724777804711 | BJ28: 4.61583421430929 | BK28: 4.21271352571605 | BL28: 0.164802199458762 | BM28: -5.8288484641256 | BN28: 9.20840263580602 | BO28: 7.84929462083215 | BP28: -4.14375165818939
A29: Bahamas, The | B29: BHS | C29: Inflation, GDP deflator (annual %) | D29: NY.GDP.DEFL.KD.ZG | F29: 1.16060127946953 | G29: 1.08963254329397 | H29: 1.34376417302924 | I29: 1.50530105203264 | J29: 2.01172774571943 | K29: 3.77131853984707 | L29: 4.71307253846376 | M29: 5.16348079645223 | N29: 8.92537280104706 | O29: 6.14534565612223 | P29: 4.58255157948102 | Q29: 6.78665890094263 | R29: 5.55102347676812 | S29: 13.2327069818163 | T29: 10.6563782684998 | U29: 2.38966526710907 | V29: 1.72870303781684 | W29: 2.2478837709413 | X29: 8.5540965371676 | Y29: 10.0068656202029 | Z29: 17.68832770698 | AA29: 3.6950075490398 | AB29: 5.97696702414777 | AC29: 3.17143545923837 | AD29: 8.46072715196375 | AE29: 4.66038702363605 | AF29: 6.58634765784333 | AG29: 1.48431064242516 | AH29: 1.81317132899601 | AI29: 5.07371104738799 | AJ29: 2.556539887887 | AK29: 3.90556543657969 | AL29: -0.851983747862761 | AM29: 2.18336657794642 | AN29: 0.802435337290049 | AO29: 0.984243640773144 | AP29: 73.2294702373079 | AQ29: 3.04892132747692 | AR29: 4.95093892443033 | AS29: 0.92270742527738 | AT29: 0.353150704560917 | AU29: 3.96047432502201 | AV29: 1.15487905427804 | AW29: 1.19499759116476 | AX29: 5.05600839849254 | AY29: 0.828194507426659 | AZ29: 2.94796581175521 | BA29: 1.48861068805519 | BB29: -1.03638031397996 | BC29: -0.392565565624793 | BD29: -0.858605322784499 | BE29: 3.35553252540916 | BF29: -0.169413674488652 | BG29: 3.64817136334401 | BH29: 5.30893214629577 | BI29: 1.60448975573296 | BJ29: 1.34831042029538 | BK29: 0.456170832413122 | BL29: 4.59340787218045 | BM29: -2.6348030197491 | BN29: -1.07183744667745 | BO29: 4.30104615816353 | BP29: 6.34442014479342
A30: Bosnia and Herzegovina | B30: BIH | C30: Inflation, GDP deflator (annual %) | D30: NY.GDP.DEFL.KD.ZG | AJ30: 48.4724077601571 | AK30: 1362.0287835516 | AL30: 7544.81368150569 | AM30: 49.1182675614766 | AN30: 13.3824463507885 | AO30: 1.63963391457347 | AP30: 11.1492939468364 | AQ30: -2.4396946739963 | AR30: 8.43332373993806 | AS30: 30.3325930267657 | AT30: 4.72611761621648 | AU30: 5.00786637251515 | AV30: 1.41086147967751 | AW30: 2.16197157775764 | AX30: 6.18901576798206 | AY30: 7.80012735973601 | AZ30: 6.19756939107606 | BA30: 7.33535128597794 | BB30: 0.18546652937485 | BC30: 1.40629396620604 | BD30: 2.43252790824482 | BE30: 0.795773347301477 | BF30: -0.224122003175367 | BG30: 1.00033721930362 | BH30: 1.36573070914964 | BI30: 1.33330596746471 | BJ30: 1.77870702677497 | BK30: 2.79162490401892 | BL30: 2.47150468459363 | BM30: 0.0621425496305932 | BN30: 4.96460441570017 | BO30: 11.8088401064015 | BP30: 6.76270435629395
A31: Belarus | B31: BLR | C31: Inflation, GDP deflator (annual %) | D31: NY.GDP.DEFL.KD.ZG | AJ31: 110.376705259785 | AK31: 1030.7768106265 | AL31: 1058.7144977475 | AM31: 1945.7486042475 | AN31: 661.504077120537 | AO31: 53.7143273468705 | AP31: 71.6495747331926 | AQ31: 76.5804464542025 | AR31: 316.793434825199 | AS31: 185.290760909447 | AT31: 79.5345724468495 | AU31: 44.8937388361962 | AV31: 30.6853215603655 | AW31: 22.675122504115 | AX31: 18.9721605296381 | AY31: 10.7486157350723 | AZ31: 12.8727022297205 | BA31: 21.2135361351524 | BB31: 9.25866190363965 | BC31: 11.3403098820796 | BD31: 70.7612909673781 | BE31: 75.2416666493216 | BF31: 21.263000253545 | BG31: 18.1922024446735 | BH31: 16.0231277230064 | BI31: 8.34168809944582 | BJ31: 8.62294196692545 | BK31: 12.1397170957777 | BL31: 8.57664221529303 | BM31: 11.8776975676281 | BN31: 15.3264196397445 | BO31: 14.8848623664839 | BP31: 7.36823053571227
A32: Belize | B32: BLZ | C32: Inflation, GDP deflator (annual %) | D32: NY.GDP.DEFL.KD.ZG | F32: 1.76302704632303 | G32: 1.35696450638156 | H32: 0.937659309925181 | I32: 2.13617110596674 | J32: 5.61061422339853 | K32: 5.7739337057622 | L32: 3.12244366461177 | M32: 1.679358127299 | N32: 0.215932315119844 | O32: 7.36964236602419 | P32: 5.06390361694 | Q32: -1.23523507979597 | R32: 14.6762708805407 | S32: 21.7106229145247 | T32: 16.8772914345555 | U32: 1.15748444536293 | V32: 2.24249533399528 | W32: 7.34918198994508 | X32: 3.58543427956945 | Y32: 51.2506539571552 | Z32: 0.166294336518447 | AA32: -4.57697224475748 | AB32: 7.78637947458508 | AC32: 8.61083463584158 | AD32: -2.03638565504288 | AE32: 3.70728475414255 | AF32: 7.59188821865718 | AG32: 3.44233798532821 | AH32: 3.11070679813454 | AI32: -0.0299159891442002 | AJ32: -2.3721033117321 | AK32: 3.43668966895795 | AL32: 1.87610848225768 | AM32: 2.60383658195195 | AN32: 5.28170880963582 | AO32: 2.74603158310431 | AP32: -1.52046077562431 | AQ32: 2.43785985479757 | AR32: -1.65702215463904 | AS32: 1.44428759552335 | AT32: -1.9214546052185 | AU32: 0.691897818951915 | AV32: -4.10750365836 | AW32: 2.14174873146229 | AX32: 3.00344412152837 | AY32: 3.22145168702571 | AZ32: 3.80629927037283 | BA32: 3.60557468225117 | BB32: -2.51886906561739 | BC32: 2.2485368571529 | BD32: 4.91658876106118 | BE32: 0.741764529847956 | BF32: 1.92028288137456 | BG32: 1.11425408928791 | BH32: -0.304580065916582 | BI32: 2.09427966302344 | BJ32: 3.03291030935591 | BK32: 0.0777284726732006 | BL32: -0.11783540640397 | BM32: -0.652000223707887 | BN32: 0.630768469073601 | BO32: 7.25244797063618 | BP32: 6.50970161380764
A33: Bermuda | B33: BMU | C33: Inflation, GDP deflator (annual %) | D33: NY.GDP.DEFL.KD.ZG | F33: 0.939036548137139 | G33: 0.976544491119895 | H33: 1.27080143898519 | I33: 0.461053047919037 | J33: 1.46112298152146 | K33: 2.60861104007444 | L33: 3.48033559332201 | M33: 8.98161462654834 | N33: 6.28106312240102 | O33: 6.26951942625101 | P33: 9.54621154208391 | Q33: 9.52577077506547 | R33: 12.812209651434 | S33: 14.9839477362144 | T33: 6.35702717701415 | U33: 2.78364922323371 | V33: 9.26910109909009 | W33: 4.91871023947657 | X33: 6.41536341744464 | Y33: 9.85408705621815 | Z33: 17.7093913080706 | AA33: 12.2085919697942 | AB33: 10.9973810679425 | AC33: 10.2965524860844 | AD33: 7.61408817849274 | AE33: 5.83513671152525 | AF33: 6.48815418331381 | AG33: 4.89301397274433 | AH33: 5.63671313382395 | AI33: 6.03357232192793 | AJ33: 6.43059116205715 | AK33: 2.81388110098526 | AL33: 5.19630458908094 | AM33: 1.95956796770183 | AN33: 4.17846351515574 | AO33: 29.3646976052491 | AP33: 4.02390310161174 | AQ33: 2.74155110645576 | AR33: 2.7121512028961 | AS33: -4.23635614734731 | AT33: -1.36919574128204 | AU33: 8.58044229104615 | AV33: 2.82473952065922 | AW33: 4.6921425981385 | AX33: 6.7623747376536 | AY33: 19.5791618081038 | AZ33: 6.57489483173077 | BA33: 5.10891410236363 | BB33: 1.04358316995928 | BC33: 2.23622200255707 | BD33: -1.15125598094265 | BE33: 6.69820369155734 | BF33: 1.65727319420499 | BG33: 3.01189087721518 | BH33: 2.95202006984243 | BI33: 4.37320384221451 | BJ33: -0.094833735989738 | BK33: 1.6111169764896 | BL33: 2.41935194490377 | BM33: -0.409804359592485 | BN33: 0.361400030497762 | BO33: 0.938226826481198 | BP33: 4.10639245421443
A34: Bolivia | B34: BOL | C34: Inflation, GDP deflator (annual %) | D34: NY.GDP.DEFL.KD.ZG | F34: 6.54817331154322 | G34: 3.561471052941 | H34: 0.824214669778314 | I34: 8.38594305461066 | J34: 5.89102517476303 | K34: 3.31587642784557 | L34: 6.2324586169217 | M34: 4.58848423666298 | N34: 3.71900826681724 | O34: 3.96056114383558 | P34: 2.53863226297418 | Q34: 18.9777488047166 | R34: 42.9445090900202 | S34: 61.5459604674601 | T34: 6.69527765368763 | U34: 8.5989208742604 | V34: 12.5406184290034 | W34: 14.1038108089384 | X34: 19.7971736389825 | Y34: 25.0487177686459 | Z34: 29.4860941190977 | AA34: 158.283333281687 | AB34: 265.197668097752 | AC34: 1443.39713629255 | AD34: 12338.6601412904 | AE34: 230.105222297583 | AF34: 14.5841938205856 | AG34: 17.5233370983455 | AH34: 13.1864212723539 | AI34: 16.2679419830218 | AJ34: 17.6894402203167 | AK34: 13.1992044095149 | AL34: 6.5571581914609 | AM34: 7.95220772509668 | AN34: 11.4272817104485 | AO34: 11.5802068693934 | AP34: 5.70504335822339 | AQ34: 7.05112676533632 | AR34: 2.41156588906529 | AS34: 5.19540520801752 | AT34: 1.87009365776751 | AU34: 2.82075739734616 | AV34: 6.32999229252485 | AW34: 7.96770950924268 | AX34: 5.94079763021928 | AY34: 13.6636795403543 | AZ34: 7.37335386111839 | BA34: 10.381181762675 | BB34: -2.41989432827502 | BC34: 8.77750811554523 | BD34: 14.6023542400665 | BE34: 7.10027550115058 | BF34: 5.99538836854924 | BG34: 2.04949764468354 | BH34: -4.62060229480602 | BI34: -1.3548705355405 | BJ34: 6.06139996076533 | BK34: 3.05626590816588 | BL34: -0.693003422953112 | BM34: -1.85438658655737 | BN34: 3.95611963961919 | BO34: 5.12446446625671 | BP34: -0.505250428968196
A35: Brazil | B35: BRA | C35: Inflation, GDP deflator (annual %) | D35: NY.GDP.DEFL.KD.ZG | F35: 34.6178049419981 | G35: 50.2494544807889 | H35: 78.4174334561054 | I35: 89.5336653268287 | J35: 58.9331842000454 | K35: 37.9360979573494 | L35: 26.528941929666 | M35: 26.7067163627493 | N35: 20.0517842311481 | O35: 16.2551115402188 | P35: 19.3845851134334 | Q35: 19.867091675534 | R35: 29.5803566969394 | S35: 34.6058549964615 | T35: 33.9294367418917 | U35: 41.2036240161754 | V35: 45.3980562145509 | W35: 38.227611227227 | X35: 54.365960027812 | Y35: 92.1419446109039 | Z35: 100.528877121889 | AA35: 101.034394745721 | AB35: 131.484045057202 | AC35: 201.740282133397 | AD35: 248.543659125921 | AE35: 149.179318289698 | AF35: 206.208708657138 | AG35: 627.951470204274 | AH35: 1304.42420943485 | AI35: 2736.97067768831 | AJ35: 416.678093932004 | AK35: 969.012962839962 | AL35: 1996.15024717719 | AM35: 2240.16886623198 | AN35: 93.9780430551367 | AO35: 18.4562437687673 | AP35: 7.72902341184411 | AQ35: 4.92436158488788 | AR35: 8.0105008831072 | AS35: 5.60606514085735 | AT35: 8.22509432125631 | AU35: 9.79811223755975 | AV35: 14.0910215230394 | AW35: 7.75206076321267 | AX35: 7.43122475252851 | AY35: 6.77427411913297 | AZ35: 6.43903808702757 | BA35: 8.7785527236756 | BB35: 7.31348274592885 | BC35: 8.42333833667878 | BD35: 8.3185922188201 | BE35: 7.9431269413538 | BF35: 7.50456453292993 | BG35: 7.84670974352809 | BH35: 7.56617501207116 | BI35: 8.10360435870246 | BJ35: 3.67138451275035 | BK35: 4.49353433137021 | BL35: 4.22425886899158 | BM35: 6.47249960755747 | BN35: 13.047270877833 | BO35: 8.5702819532232 | BP35: 4.65899475870381
A36: Barbados | B36: BRB | C36: Inflation, GDP deflator (annual %) | D36: NY.GDP.DEFL.KD.ZG | F36: -0.947999269781036 | G36: -4.63572064136059 | H36: 18.5347352010554 | I36: -5.3774524989538 | J36: -5.04522769808936 | K36: 3.63346668204332 | L36: 1.64735602390572 | M36: 7.7730420109187 | N36: 4.59091105629439 | O36: 7.34403675118362 | P36: 6.81246016963519 | Q36: 9.89330334754608 | R36: 22.7741343187316 | S36: 31.4213942614682 | T36: 29.3607284286293 | U36: 3.02098255963466 | V36: 9.75033575653946 | W36: 6.71750617431934 | X36: 12.378333445183 | Y36: 44.6781020487812 | Z36: 12.2002890324817 | AA36: 9.8457670839303 | AB36: 5.66428865895905 | AC36: 5.18324310134047 | AD36: 3.51432724252501 | AE36: 4.47349515734052 | AF36: 7.33777019238275 | AG36: 2.75735511474133 | AH36: 6.82357775062113 | AI36: 3.72830835473779 | AJ36: 4.49528291877914 | AK36: 2.1223935897718 | AL36: 5.19536641314413 | AM36: 2.20984265586837 | AN36: 1.01614920853137 | AO36: 2.53841641959511 | AP36: 0.916898497893698 | AQ36: 8.70325615354062 | AR36: 4.43342351579936 | AS36: -1.32283915072432 | AT36: 2.2553892518755 | AU36: 0.907856236699956 | AV36: 1.11587216720588 | AW36: 5.82814413602402 | AX36: 6.66772455718578 | AY36: 4.09637073569277 | AZ36: 8.61226108302537 | BA36: 1.80693487399488 | BB36: -1.82970441549448 | BC36: 18.8527284822355 | BD36: 3.66694041932899 | BE36: -1.01754183582014 | BF36: 2.74359414985743 | BG36: 0.00746353844473902 | BH36: -0.611165126966512 | BI36: -0.967050709686362 | BJ36: 3.36727197112887 | BK36: 3.25265217777908 | BL36: 2.14644727501501 | BM36: 5.1139219922773 | BN36: 2.32921875143295 | BO36: 0.664976976473824 | BP36: 3.18212980720116
A37: Brunei Darussalam | B37: BRN | C37: Inflation, GDP deflator (annual %) | D37: NY.GDP.DEFL.KD.ZG | T37: 5.40841250879831 | U37: 5.48367913232401 | V37: 8.22370986590828 | W37: -2.9746800408402 | X37: 13.3685689329452 | Y37: 94.7724665478483 | Z37: 10.3065506616772 | AA37: -5.58342929839709 | AB37: -12.7143643318788 | AC37: -0.439743751162723 | AD37: -3.02513075616653 | AE37: -37.0798606330313 | AF37: 11.1997682582331 | AG37: -10.5074011684662 | AH37: 9.47928387762059 | AI37: 9.73556985962955 | AJ37: -3.63340548298319 | AK37: -1.99597149195178 | AL37: -2.14230707000969 | AM37: -2.4067437987094 | AN37: 9.00608865153572 | AO37: -0.965394903565368 | AP37: 0.695854302302251 | AQ37: -13.9889900220022 | AR37: 10.4058180464333 | AS37: 2.37672035245946 | AT37: -4.97305267701049 | AU37: -0.135384149567656 | AV37: 6.30997052770057 | AW37: 16.5419530801955 | AX37: 20.5036158493576 | AY37: 9.94435222859258 | AZ37: 4.69688854570667 | BA37: 16.0207669612963 | BB37: -21.7392663171489 | BC37: 4.98008956509719 | BD37: 20.1807686846284 | BE37: 1.22025197904199 | BF37: -2.82348952713912 | BG37: -1.84601542355594 | BH37: -17.6127432412634 | BI37: -9.16949513646259 | BJ37: 4.95526868232284 | BK37: 9.21562481534343 | BL37: -3.33372764830381 | BM37: -10.8637594994 | BN37: 15.4659284363945 | BO37: 24.2367266802876 | BP37: -12.8961956287324
A38: Bhutan | B38: BTN | C38: Inflation, GDP deflator (annual %) | D38: NY.GDP.DEFL.KD.ZG | P38: 4.45844432658933 | Q38: 5.89793371068087 | R38: 13.0176970089472 | S38: 17.170329640786 | T38: -0.0768638780979245 | U38: 0.0416224732643826 | V38: 0.0107594042819841 | W38: -15.8780630297509 | X38: 6.00618397533914 | Y38: 12.5171777751875 | Z38: 3.46255527068837 | AA38: 7.28714919176407 | AB38: 7.15835942749703 | AC38: 10.1636889932223 | AD38: 6.5086147454451 | AE38: 7.18543787496726 | AF38: 1.1011726823489 | AG38: 14.9648718330335 | AH38: 5.60791537601837 | AI38: 6.20535307251815 | AJ38: 8.94128430964388 | AK38: 8.92328955866431 | AL38: 8.51345075725479 | AM38: 12.3412550618465 | AN38: 8.28438262087263 | AO38: 8.11263278407877 | AP38: 12.9068747964519 | AQ38: 10.6962671056476 | AR38: 6.17025915764653 | AS38: 16.5271465766662 | AT38: 5.33733054010742 | AU38: 5.16519301584195 | AV38: 3.62430623598658 | AW38: 4.34588162820633 | AX38: 6.4792024025566 | AY38: 6.57512374147177 | AZ38: 4.68817791946599 | BA38: 5.60618091108023 | BB38: 4.4240994174459 | BC38: 8.32696239631917 | BD38: 8.88020593346201 | BE38: 8.63679344825027 | BF38: 6.16413159831512 | BG38: 5.72222883359687 | BH38: 3.20977724189126 | BI38: 4.0489129986434 | BJ38: 4.34963395991817 | BK38: 1.15086273454624 | BL38: 3.10800839980718 | BM38: 5.28737431504244 | BN38: 7.62801338690346 | BO38: 5.7948551929732
A39: Botswana | B39: BWA | C39: Inflation, GDP deflator (annual %) | D39: NY.GDP.DEFL.KD.ZG | F39: 1.93394654573322 | G39: 1.36073530511867 | H39: 1.17682676860338 | I39: 2.54749888017885 | J39: 3.84627563139497 | K39: 5.78874199620294 | L39: 7.58155108394078 | M39: 2.16614944689633 | N39: 1.58435523727398 | O39: 5.97859338189495 | P39: 4.66418003521538 | Q39: 10.7754221855342 | R39: 9.90661233608165 | S39: 12.796924146026 | T39: 16.4672818630996 | U39: 11.3155298849017 | V39: 4.93738330724686 | W39: 12.4668113563582 | X39: 21.8563617394272 | Y39: 10.1902825295163 | Z39: -0.0883228377325622 | AA39: 3.69541837346672 | AB39: 8.74548539674289 | AC39: 15.4269850656216 | AD39: 22.8936594340284 | AE39: 14.0612498754001 | AF39: 12.6940698241788 | AG39: 22.6970595672875 | AH39: 13.648777260206 | AI39: 6.30001828340927 | AJ39: 5.17770993695599 | AK39: 6.63928085355347 | AL39: 13.0647004889209 | AM39: 9.46380470158942 | AN39: 7.15529485253452 | AO39: 16.1121954488091 | AP39: 4.99060848779871 | AQ39: 9.96727081881656 | AR39: 14.2352084945169 | AS39: 14.1709669143697 | AT39: 8.31282499951298 | AU39: 1.18737069613121 | AV39: 3.25908437200664 | AW39: 10.0787886535731 | AX39: 15.4717065693105 | AY39: 5.1543983602337 | AZ39: 6.02919765064402 | BA39: 9.37273025563468 | BB39: 15.1089337480839 | BC39: 7.6830614533247 | BD39: 12.6533215833519 | BE39: 3.01184160842378 | BF39: 1.5321209980109 | BG39: 9.60400220258751 | BH39: 3.73031737555105 | BI39: 11.9049111318198 | BJ39: -2.64991927643297 | BK39: 0.0571969585408283 | BL39: 0.507585435653098 | BM39: 4.37899382741232 | BN39: 8.38144972399829 | BO39: 14.6175509748138 | BP39: 2.12467971961613
A40: Central African Republic | B40: CAF | C40: Inflation, GDP deflator (annual %) | D40: NY.GDP.DEFL.KD.ZG | F40: 4.63501852407487 | G40: 4.88874686844647 | H40: 4.67447570130837 | I40: 7.54197105015557 | J40: 5.03913870121602 | K40: 4.47541104842317 | L40: -0.774417229772368 | M40: 16.1724010608566 | N40: -3.85268771319454 | O40: 4.49087969968032 | P40: 4.93826828935202 | Q40: 4.64423708915463 | R40: 2.19949026241304 | S40: 5.38099970484274 | T40: 19.3262162143988 | U40: 25.9966269302932 | V40: 11.3724628206274 | W40: 9.22839370206516 | X40: 10.9266339771195 | Y40: 18.2653791713287 | Z40: 13.8727460514407 | AA40: 20.9142340489744 | AB40: 11.1028813560158 | AC40: 1.41940106495943 | AD40: 34.1451753514768 | AE40: -3.42903722815151 | AF40: -2.30335118277361 | AG40: 2.62405594015438 | AH40: 2.45620480015998 | AI40: 1.83664510564687 | AJ40: -0.389815607540783 | AK40: 2.78264702243938 | AL40: -3.43302031766279 | AM40: 24.4125696821529 | AN40: 9.89797585830159 | AO40: -3.54304573295389 | AP40: 0.823381000647387 | AQ40: -0.414154094982351 | AR40: 4.08471548975844 | AS40: 8.5066010783456 | AT40: 0.425938675009292 | AU40: -2.37188170574854 | AV40: 1.33641863140784 | AW40: -4.43978593836373 | AX40: 4.18843708159385 | AY40: 3.33404593869069 | AZ40: 1.83823165042337 | BA40: 7.07707072361423 | BB40: 0.711628390754186 | BC40: 4.21130931097511 | BD40: 4.00911505710052 | BE40: 6.18103617692616 | BF40: 2.48748677760067 | BG40: 11.8938033016777 | BH40: 2.70826310785282 | BI40: 2.98011408445534 | BJ40: 6.44370628779525 | BK40: -1.22411715845705 | BL40: 2.32783705140642 | BM40: 1.98216055627785 | BN40: 3.18576646900353 | BO40: 5.9679244498741 | BP40: 3.39995299007134
A41: Canada | B41: CAN | C41: Inflation, GDP deflator (annual %) | D41: NY.GDP.DEFL.KD.ZG | F41: 2.44442707980437 | G41: 1.30987461608481 | H41: 2.18222642526791 | I41: 2.83181940854789 | J41: 3.7750321193182 | K41: 4.92090461079211 | L41: 4.45413882488484 | M41: 4.06513392892218 | N41: 4.82678269131655 | O41: 4.72201383000848 | P41: 4.93143997588837 | Q41: 5.82604410879335 | R41: 9.92880660941735 | S41: 15.5694800549171 | T41: 10.997734532867 | U41: 8.78342642035651 | V41: 6.71753507741943 | W41: 6.82659461471485 | X41: 10.0700506013902 | Y41: 10.0558897409454 | Z41: 10.8709573442936 | AA41: 8.8270784009845 | AB41: 5.82447504958721 | AC41: 3.54539026295097 | AD41: 3.33838918991506 | AE41: 3.13237904093367 | AF41: 4.79160141366921 | AG41: 4.53999817633812 | AH41: 4.68125324002972 | AI41: 3.35230172492575 | AJ41: 3.05676989607522 | AK41: 1.47085083373742 | AL41: 1.28904288219367 | AM41: 1.45563096077591 | AN41: 2.26332573160717 | AO41: 1.67527501989628 | AP41: 1.14412830670354 | AQ41: -0.176225256269674 | AR41: 1.92385564173627 | AS41: 4.37419903079417 | AT41: 1.5736767667921 | AU41: 1.25752345524339 | AV41: 3.24973700697623 | AW41: 3.26087389828982 | AX41: 3.11663850487676 | AY41: 2.57017267466084 | AZ41: 3.30054564423155 | BA41: 3.99631645542576 | BB41: -2.32492207227941 | BC41: 2.84863776634425 | BD41: 3.24445517550211 | BE41: 1.21844370738719 | BF41: 1.74073790573416 | BG41: 1.94119897748668 | BH41: -0.867651312323389 | BI41: 0.716978140660657 | BJ41: 2.57101465425282 | BK41: 1.6511181981862 | BL41: 1.54607075438069 | BM41: 1.07081026807496 | BN41: 7.66486542253131 | BO41: 7.65381992676227 | BP41: 1.5347101132531
A42: Central Europe and the Baltics | B42: CEB | C42: Inflation, GDP deflator (annual %) | D42: NY.GDP.DEFL.KD.ZG | AJ42: 99.2954217924989 | AK42: 199.858895609549 | AL42: 51.0910538964772 | AM42: 37.234034809391 | AN42: 27.4436170381266 | AO42: 17.9812076556664 | AP42: 9.92247771949688 | AQ42: 8.17944424818104 | AR42: 6.17757158989451 | AS42: 5.53606478204385 | AT42: 5.37523124435772 | AU42: 3.84837869171173 | AV42: 3.88938600534479 | AW42: 4.9331164049614 | AX42: 3.11436952510556 | AY42: 3.88062372679858 | AZ42: 5.44367721666583 | BA42: 5.52922978301194 | BB42: 2.73284071725568 | BC42: 0.920113149429753 | BD42: 3.06571454649757 | BE42: 2.18343357394524 | BF42: 1.1327980246691 | BG42: 1.34078287386647 | BH42: 1.23453645747557 | BI42: 0.987474343866324 | BJ42: 2.7092393048564 | BK42: 3.5930097078956 | BL42: 3.82267611749334 | BM42: 2.40777968361606 | BN42: 5.34023602800748 | BO42: 10.689577427514 | BP42: 9.54718862520608
A43: Switzerland | B43: CHE | C43: Inflation, GDP deflator (annual %) | D43: NY.GDP.DEFL.KD.ZG | F43: 4.05828923728673 | G43: 5.8270682242229 | H43: 4.84776024217327 | I43: 5.3107281269253 | J43: 3.79724141899177 | K43: 4.8050096929547 | L43: 4.45331556147023 | M43: 3.0811057929822 | N43: 2.57439164656685 | O43: 4.71275554296899 | P43: 9.15112371907077 | Q43: 9.80195916958131 | R43: 8.14042509758283 | S43: 6.93261888069129 | T43: 7.13294120114362 | U43: 2.72985453980796 | V43: 0.25801177789846 | W43: 3.61276500844454 | X43: 1.988368644864 | Y43: 2.70668273781347 | Z43: 5.66110770362236 | AA43: 7.34804061217811 | AB43: 2.3668842526853 | AC43: 3.75963798821918 | AD43: 2.27073072584507 | AE43: 3.03459397604009 | AF43: 2.19348208822963 | AG43: 2.79023880959011 | AH43: 3.45846016176607 | AI43: 4.60362132287064 | AJ43: 5.40910475702043 | AK43: 2.12463504318221 | AL43: 2.32202399254446 | AM43: 1.18438713620428 | AN43: 0.737757710726214 | AO43: 0.280022460607341 | AP43: -0.476483336948348 | AQ43: -0.189259059141946 | AR43: 0.0437705570972611 | AS43: 1.36728550428708 | AT43: 0.974383320001323 | AU43: -0.249463899497144 | AV43: 1.17975924142517 | AW43: 0.296627279296985 | AX43: 0.924638291551645 | AY43: 2.15025798459116 | AZ43: 2.37706132688891 | BA43: 1.44992801006573 | BB43: 0.457543979622471 | BC43: 0.312736574258764 | BD43: -0.0204529167059491 | BE43: 0.0637202631572649 | BF43: -0.0868426404352363 | BG43: -0.653123803620176 | BH43: -1.2650568747671 | BI43: -0.583291591583972 | BJ43: -0.367869216813958 | BK43: 0.764289197175742 | BL43: -0.103895158007788 | BM43: -0.699187622738137 | BN43: 1.24619196669597 | BO43: 2.4971595038279 | BP43: 1.02331402592833
A44: Channel Islands | B44: CHI | C44: Inflation, GDP deflator (annual %) | D44: NY.GDP.DEFL.KD.ZG | BC44: 2.31458585810039 | BD44: 3.36234799786833 | BE44: 5.45465670838978 | BF44: 2.03816645010104 | BG44: 1.7787742558955 | BH44: 3.03415108880192 | BI44: 1.39650492613288 | BJ44: 3.06230710188164 | BK44: 4.30931162934687 | BL44: 2.95476691310121 | BM44: 2.83334988896617 | BN44: 0.21684009581287 | BO44: 7.35832205919618 | BP44: 5.75258334988345
A45: Chile | B45: CHL | C45: Inflation, GDP deflator (annual %) | D45: NY.GDP.DEFL.KD.ZG | F45: 6.56898159255763 | G45: 12.9485164298092 | H45: 43.8204273483907 | I45: 47.9343620799658 | J45: 38.840095374724 | K45: 28.5813608055762 | L45: 25.1448875388215 | M45: 33.4686701543951 | N45: 40.1605325593821 | O45: 40.5757859262539 | P45: 17.6716716514363 | Q45: 87.5948636847101 | R45: 414.8103110022 | S45: 678.608462183612 | T45: 347.201209420558 | U45: 247.308508558584 | V45: 101.773621844757 | W45: 56.2846405522624 | X45: 47.9776851024258 | Y45: 29.1176599025163 | Z45: 11.5688525347473 | AA45: 7.6563472551216 | AB45: 30.963672486807 | AC45: 15.7375320928942 | AD45: 41.6819057285687 | AE45: 21.4548966568031 | AF45: 25.8484189824583 | AG45: 21.7178811867143 | AH45: 13.7560317686944 | AI45: 22.4709370974075 | AJ45: 21.3909823000852 | AK45: 13.4643770215386 | AL45: 12.1644196722728 | AM45: 14.4639849515997 | AN45: 11.6807181078817 | AO45: 4.07977619624471 | AP45: 3.33058050494175 | AQ45: 0.778990205960753 | AR45: 2.18776787056487 | AS45: 4.56004348689325 | AT45: 4.27714698160932 | AU45: 3.34066036755067 | AV45: 4.30030088589093 | AW45: 7.02476170687822 | AX45: 7.12031535651923 | AY45: 12.3498959180141 | AZ45: 5.08875706456591 | BA45: 0.31113250293626 | BB45: 3.57779503707295 | BC45: 8.85744149583176 | BD45: 3.26051486014924 | BE45: 0.76346667921203 | BF45: 2.26077061226466 | BG45: 5.85289162817273 | BH45: 4.95436552710441 | BI45: 4.56065604390805 | BJ45: 4.82819188168904 | BK45: 1.59019973757384 | BL45: 2.56778721379496 | BM45: 9.66572269693961 | BN45: 6.9147558846894 | BO45: 7.91378346570282 | BP45: 6.59951204566833
A46: China | B46: CHN | C46: Inflation, GDP deflator (annual %) | D46: NY.GDP.DEFL.KD.ZG | F46: 15.2539937422295 | G46: -0.114964918339382 | H46: -2.62161065082633 | I46: -0.362038483228218 | J46: 0.869780803545027 | K46: -1.5620708278273 | L46: 0.813497276305114 | M46: 1.36357574813657 | N46: -3.7925287173275 | O46: -2.61457045011514 | P46: 0.665937402347524 | Q46: 0.0741856162067052 | R46: 0.208465019313863 | S46: 0.277735670872488 | T46: -1.13117515356886 | U46: -0.106286227905457 | V46: 1.09377177565865 | W46: 1.67514249839924 | X46: 3.600054771534 | Y46: 3.75177705669101 | Z46: 2.35787142114833 | AA46: -0.140355089605009 | AB46: 1.15679526219108 | AC46: 4.94416271276128 | AD46: 10.2093990441261 | AE46: 4.66902079731935 | AF46: 5.08251646766406 | AG46: 12.1076614989562 | AH46: 8.60246513371632 | AI46: 5.71122416868202 | AJ46: 6.71453695848909 | AK46: 8.19032302163217 | AL46: 15.1858645089504 | AM46: 20.6169888119177 | AN46: 13.6656964001969 | AO46: 6.50673063542777 | AP46: 1.61656874206059 | AQ46: -0.900251628944076 | AR46: -1.26305893875535 | AS46: 2.06279261346987 | AT46: 2.04704945728633 | AU46: 0.602099078250106 | AV46: 2.60317771902103 | AW46: 6.95199268086466 | AX46: 3.90374426907985 | AY46: 3.92654939643413 | AZ46: 7.74968649303898 | BA46: 7.79534603698191 | BB46: -0.209533361180647 | BC46: 6.88138025334055 | BD46: 8.07568446704094 | BE46: 2.33121757581199 | BF46: 2.16337002665455 | BG46: 1.03106368780396 | BH46: -0.00294409364951775 | BI46: 1.40734602732051 | BJ46: 4.2326819752236 | BK46: 3.49974763567195 | BL46: 1.28670040766232 | BM46: 0.49249391805742 | BN46: 4.55232657897571 | BO46: 1.82367710735865 | BP46: -0.582393794026771
A47: Cote d'Ivoire | B47: CIV | C47: Inflation, GDP deflator (annual %) | D47: NY.GDP.DEFL.KD.ZG | F47: 2.99006346469766 | G47: 3.0048198149284 | H47: 3.01391715577817 | I47: 2.906177950873 | J47: 3.07886780467852 | K47: 0.0416032240180328 | L47: 1.22775183399891 | M47: 5.79379997879829 | N47: 1.85391784764981 | O47: 2.99084831038685 | P47: -0.941093871223046 | Q47: 2.51161642845075 | R47: 13.2279689683128 | S47: 26.6941713348517 | T47: 4.31395366224771 | U47: 18.2229732475378 | V47: 28.7512918339878 | W47: 4.43330463446982 | X47: 6.54139713343109 | Y47: 24.1436771091168 | Z47: 2.97699115837639 | AA47: 8.301317589562 | AB47: 9.0467819094663 | AC47: 17.9098958917756 | AD47: 0.343657064772017 | AE47: -2.0204048360965 | AF47: -4.07520680060972 | AG47: -0.380926014955392 | AH47: -1.01240652384017 | AI47: -4.52327354283084 | AJ47: 0.663489267146474 | AK47: -0.0238371372650903 | AL47: 6.15419429089883 | AM47: 46.386069435419 | AN47: 11.0437898513941 | AO47: 56.2837762738966 | AP47: 3.9214742013522 | AQ47: 5.38736139065696 | AR47: -0.775911929443382 | AS47: 1.60101728726917 | AT47: 6.87596879742645 | AU47: 4.58213735216555 | AV47: 3.27812069285412 | AW47: -2.50335752004385 | AX47: 1.21513493970562 | AY47: 1.3595382596009 | AZ47: 3.08854944572292 | BA47: 5.37293348500339 | BB47: 1.20777929723688 | BC47: 1.5162179241976 | BD47: 5.70932050005679 | BE47: -0.404098360740875 | BF47: 2.87673042852516 | BG47: 4.40733235572075 | BH47: 4.77568237270827 | BI47: -1.17983243565696 | BJ47: -1.04167724817084 | BK47: 1.68197647173226 | BL47: 1.98335249260808 | BM47: 1.82838309372076 | BN47: 3.93013137544369 | BO47: 2.08589858906348 | BP47: 2.92244000008407
